Workbook

Sheet Model
B1: Lufthansa Group – FY fuel price sensitivity after hedging
B2: Blue = input you can change · black = formula · green = link to Calibration sheet · yellow = key levers
B4: Global parameters (calibrated on 8 published grids, 2024–26)
B5: Barrels per tonne of jet fuel (k) | C5: 7.88
B6: Crack weight vs Brent (w) | C6: 1.15
B7: Strike dispersion σ ($/t) | C7: 181
B9: Scenario inputs | J9: Base FY price build-up: realised to date + remaining at base forwards
B10: Base Brent, months not yet realised ($/bbl) | C10: 84 | J10: H1 reported fuel expense incl. SAF (€m) | K10: 4176
B11: Base jet crack ($/bbl) | C11: 64 | J11: H1 mandatory SAF (€m) | K11: 90
B12: Base FY post-hedge jet price P0 ($/t) – calculated | C12: =($K$20+$K$15*$K$21+$K$22*$K$23)/$C$18 -> 1036.2086 | J12: H1 average USD/EUR | K12: 1.1664
B13: Months of the year not yet realised | C13: 5 | J13: H1 volume (mt) | K13: 4.4
B14: Share of FY volume still to price (s) | C14: =$K$22/$C$18 -> 0.43807502 | J14: Q3 volume (mt) | K14: 2.68
B15: Hedge ratio on remaining volume (h) | C15: 0.81 | J15: July volume (mt) | K15: =K14/3 -> 0.89333333
B16: Call-spread lower strike K1 ($/t jet) | C16: =Calibration!$C$6 -> 691 | J16: July Brent ($/bbl) | K16: 79.8
B17: Call-spread upper strike K2 ($/t jet) | C17: =Calibration!$D$6 -> 1299 | J17: July jet crack ($/bbl) | K17: 75.6
B18: FY jet fuel volume (mt) | C18: 9.42 | J18: July hedge ratio | K18: 0.82
B19: USD/EUR | C19: 1.151 | J19: Level offset A ($/t) | K19: 155
B20: Scenario Brent ($/bbl) | C20: 94 | J20: H1 realised fossil cost ($m) | K20: =(K10-K11)*K12 -> 4765.9104
B21: Scenario jet crack ($/bbl) | C21: 64 | J21: July post-hedge price ($/t) | K21: =((Model!$C$5*((K16)+Model!$C$6*(K17)))+$K$19-(K18)*((((Model!$C$5*((K16)+Model!$C$6*(K17)))-($C$16))*NORMSDIST(((Model!$C$5*((K16)+Model!$C$6*(K17)))-($C$16))/Model!$C$7)+Model!$C$7*EXP(-((((Model!$C$5*((K16)+Model!$C$6*(K17)))-($C$16))/Model!$C$7)^2)/2)/SQRT(2*PI()))-(((Model!$C$5*((K16)+Model!$C$6*(K17)))-($C$17))*NORMSDIST(((Model!$C$5*((K16)+Model!$C$6*(K17)))-($C$17))/Model!$C$7)+Model!$C$7*EXP(-((((Model!$C$5*((K16)+Model!$C$6*(K17)))-($C$17))/Model!$C$7)^2)/2)/SQRT(2*PI())))) -> 1023.6385
J22: Remaining volume Aug–Dec (mt) | K22: =$C$18-K13-K15 -> 4.1266667
B23: Outputs | J23: Remaining post-hedge price at base forwards ($/t) | K23: =((Model!$C$5*(($C$10)+Model!$C$6*($C$11)))+$K$19-($C$15)*((((Model!$C$5*(($C$10)+Model!$C$6*($C$11)))-($C$16))*NORMSDIST(((Model!$C$5*(($C$10)+Model!$C$6*($C$11)))-($C$16))/Model!$C$7)+Model!$C$7*EXP(-((((Model!$C$5*(($C$10)+Model!$C$6*($C$11)))-($C$16))/Model!$C$7)^2)/2)/SQRT(2*PI()))-(((Model!$C$5*(($C$10)+Model!$C$6*($C$11)))-($C$17))*NORMSDIST(((Model!$C$5*(($C$10)+Model!$C$6*($C$11)))-($C$17))/Model!$C$7)+Model!$C$7*EXP(-((((Model!$C$5*(($C$10)+Model!$C$6*($C$11)))-($C$17))/Model!$C$7)^2)/2)/SQRT(2*PI())))) -> 988.86704
B24: Market jet price at base, J0 ($/t) | C24: =Model!$C$5*(($C$10)+Model!$C$6*($C$11)) -> 1241.888 | J24: Calculated base FY price P0 ($/t) | K24: =$C$12 -> 1036.2086
B25: Market jet price in scenario, J ($/t) | C25: =Model!$C$5*(($C$20)+Model!$C$6*($C$21)) -> 1320.688 | J25: Lufthansa FY post-hedge price, 27 Jul 2026 ($/t) | K25: 1036
B26: Hedge protection at base ($/t hedged) | C26: =(((C24)-($C$16))*NORMSDIST(((C24)-($C$16))/Model!$C$7)+Model!$C$7*EXP(-((((C24)-($C$16))/Model!$C$7)^2)/2)/SQRT(2*PI()))-(((C24)-($C$17))*NORMSDIST(((C24)-($C$17))/Model!$C$7)+Model!$C$7*EXP(-((((C24)-($C$17))/Model!$C$7)^2)/2)/SQRT(2*PI())) -> 503.72958 | J26: Difference ($/t) | K26: =K24-K25 -> 0.20864524
B27: Hedge protection in scenario ($/t hedged) | C27: =(((C25)-($C$16))*NORMSDIST(((C25)-($C$16))/Model!$C$7)+Model!$C$7*EXP(-((((C25)-($C$16))/Model!$C$7)^2)/2)/SQRT(2*PI()))-(((C25)-($C$17))*NORMSDIST(((C25)-($C$17))/Model!$C$7)+Model!$C$7*EXP(-((((C25)-($C$17))/Model!$C$7)^2)/2)/SQRT(2*PI())) -> 546.1292 | J27: P0 = [H1 cost + July vol × July price + remaining vol × remaining price] ÷ FY volume
B28: Scenario FY post-hedge price P ($/t) | C28: =$C$12+$C$14*((C25-C24)-$C$15*(C27-C26)) -> 1055.6838 | J28: Remaining price = J0 + A − h·Prot(J0); July uses July prices and the July hedge ratio
B29: Base FY fossil fuel cost (€bn) | C29: =$C$18*$C$12/$C$19/1000 -> 8.480526
B30: Scenario FY fossil fuel cost (€bn) | C30: =$C$18*C28/$C$19/1000 -> 8.6399147
B31: Change vs base (€m) | C31: =(C30-C29)*1000 -> 159.38867
B32: Formula: P = P0 + s·[(J−J0) − h·(Prot(J) − Prot(J0))], J = k·(Brent + w·crack), Prot = smoothed call spread K1–K2
B34: Sensitivity grid: FY post-hedge price ($/t)
B35: Brent ↓ / crack → | C35: =$C$11+(-20) -> 44 | D35: =$C$11+(-10) -> 54 | E35: =$C$11+(0) -> 64 | F35: =$C$11+(10) -> 74 | G35: =$C$11+(20) -> 84
B36: =$C$10+(30) -> 114 | C36: =$C$12+$C$14*((Model!$C$5*(($B36)+Model!$C$6*(C$35)))-(Model!$C$5*(($C$10)+Model!$C$6*($C$11)))-$C$15*(((((Model!$C$5*(($B36)+Model!$C$6*(C$35)))-($C$16))*NORMSDIST(((Model!$C$5*(($B36)+Model!$C$6*(C$35)))-($C$16))/Model!$C$7)+Model!$C$7*EXP(-((((Model!$C$5*(($B36)+Model!$C$6*(C$35)))-($C$16))/Model!$C$7)^2)/2)/SQRT(2*PI()))-(((Model!$C$5*(($B36)+Model!$C$6*(C$35)))-($C$17))*NORMSDIST(((Model!$C$5*(($B36)+Model!$C$6*(C$35)))-($C$17))/Model!$C$7)+Model!$C$7*EXP(-((((Model!$C$5*(($B36)+Model!$C$6*(C$35)))-($C$17))/Model!$C$7)^2)/2)/SQRT(2*PI())))-((((Model!$C$5*(($C$10)+Model!$C$6*($C$11)))-($C$16))*NORMSDIST(((Model!$C$5*(($C$10)+Model!$C$6*($C$11)))-($C$16))/Model!$C$7)+Model!$C$7*EXP(-((((Model!$C$5*(($C$10)+Model!$C$6*($C$11)))-($C$16))/Model!$C$7)^2)/2)/SQRT(2*PI()))-(((Model!$C$5*(($C$10)+Model!$C$6*($C$11)))-($C$17))*NORMSDIST(((Model!$C$5*(($C$10)+Model!$C$6*($C$11)))-($C$17))/Model!$C$7)+Model!$C$7*EXP(-((((Model!$C$5*(($C$10)+Model!$C$6*($C$11)))-($C$17))/Model!$C$7)^2)/2)/SQRT(2*PI()))))) -> 1049.337 | D36: =$C$12+$C$14*((Model!$C$5*(($B36)+Model!$C$6*(D$35)))-(Model!$C$5*(($C$10)+Model!$C$6*($C$11)))-$C$15*(((((Model!$C$5*(($B36)+Model!$C$6*(D$35)))-($C$16))*NORMSDIST(((Model!$C$5*(($B36)+Model!$C$6*(D$35)))-($C$16))/Model!$C$7)+Model!$C$7*EXP(-((((Model!$C$5*(($B36)+Model!$C$6*(D$35)))-($C$16))/Model!$C$7)^2)/2)/SQRT(2*PI()))-(((Model!$C$5*(($B36)+Model!$C$6*(D$35)))-($C$17))*NORMSDIST(((Model!$C$5*(($B36)+Model!$C$6*(D$35)))-($C$17))/Model!$C$7)+Model!$C$7*EXP(-((((Model!$C$5*(($B36)+Model!$C$6*(D$35)))-($C$17))/Model!$C$7)^2)/2)/SQRT(2*PI())))-((((Model!$C$5*(($C$10)+Model!$C$6*($C$11)))-($C$16))*NORMSDIST(((Model!$C$5*(($C$10)+Model!$C$6*($C$11)))-($C$16))/Model!$C$7)+Model!$C$7*EXP(-((((Model!$C$5*(($C$10)+Model!$C$6*($C$11)))-($C$16))/Model!$C$7)^2)/2)/SQRT(2*PI()))-(((Model!$C$5*(($C$10)+Model!$C$6*($C$11)))-($C$17))*NORMSDIST(((Model!$C$5*(($C$10)+Model!$C$6*($C$11)))-($C$17))/Model!$C$7)+Model!$C$7*EXP(-((((Model!$C$5*(($C$10)+Model!$C$6*($C$11)))-($C$17))/Model!$C$7)^2)/2)/SQRT(2*PI()))))) -> 1075.9764 | E36: =$C$12+$C$14*((Model!$C$5*(($B36)+Model!$C$6*(E$35)))-(Model!$C$5*(($C$10)+Model!$C$6*($C$11)))-$C$15*(((((Model!$C$5*(($B36)+Model!$C$6*(E$35)))-($C$16))*NORMSDIST(((Model!$C$5*(($B36)+Model!$C$6*(E$35)))-($C$16))/Model!$C$7)+Model!$C$7*EXP(-((((Model!$C$5*(($B36)+Model!$C$6*(E$35)))-($C$16))/Model!$C$7)^2)/2)/SQRT(2*PI()))-(((Model!$C$5*(($B36)+Model!$C$6*(E$35)))-($C$17))*NORMSDIST(((Model!$C$5*(($B36)+Model!$C$6*(E$35)))-($C$17))/Model!$C$7)+Model!$C$7*EXP(-((((Model!$C$5*(($B36)+Model!$C$6*(E$35)))-($C$17))/Model!$C$7)^2)/2)/SQRT(2*PI())))-((((Model!$C$5*(($C$10)+Model!$C$6*($C$11)))-($C$16))*NORMSDIST(((Model!$C$5*(($C$10)+Model!$C$6*($C$11)))-($C$16))/Model!$C$7)+Model!$C$7*EXP(-((((Model!$C$5*(($C$10)+Model!$C$6*($C$11)))-($C$16))/Model!$C$7)^2)/2)/SQRT(2*PI()))-(((Model!$C$5*(($C$10)+Model!$C$6*($C$11)))-($C$17))*NORMSDIST(((Model!$C$5*(($C$10)+Model!$C$6*($C$11)))-($C$17))/Model!$C$7)+Model!$C$7*EXP(-((((Model!$C$5*(($C$10)+Model!$C$6*($C$11)))-($C$17))/Model!$C$7)^2)/2)/SQRT(2*PI()))))) -> 1108.2182 | F36: =$C$12+$C$14*((Model!$C$5*(($B36)+Model!$C$6*(F$35)))-(Model!$C$5*(($C$10)+Model!$C$6*($C$11)))-$C$15*(((((Model!$C$5*(($B36)+Model!$C$6*(F$35)))-($C$16))*NORMSDIST(((Model!$C$5*(($B36)+Model!$C$6*(F$35)))-($C$16))/Model!$C$7)+Model!$C$7*EXP(-((((Model!$C$5*(($B36)+Model!$C$6*(F$35)))-($C$16))/Model!$C$7)^2)/2)/SQRT(2*PI()))-(((Model!$C$5*(($B36)+Model!$C$6*(F$35)))-($C$17))*NORMSDIST(((Model!$C$5*(($B36)+Model!$C$6*(F$35)))-($C$17))/Model!$C$7)+Model!$C$7*EXP(-((((Model!$C$5*(($B36)+Model!$C$6*(F$35)))-($C$17))/Model!$C$7)^2)/2)/SQRT(2*PI())))-((((Model!$C$5*(($C$10)+Model!$C$6*($C$11)))-($C$16))*NORMSDIST(((Model!$C$5*(($C$10)+Model!$C$6*($C$11)))-($C$16))/Model!$C$7)+Model!$C$7*EXP(-((((Model!$C$5*(($C$10)+Model!$C$6*($C$11)))-($C$16))/Model!$C$7)^2)/2)/SQRT(2*PI()))-(((Model!$C$5*(($C$10)+Model!$C$6*($C$11)))-($C$17))*NORMSDIST(((Model!$C$5*(($C$10)+Model!$C$6*($C$11)))-($C$17))/Model!$C$7)+Model!$C$7*EXP(-((((Model!$C$5*(($C$10)+Model!$C$6*($C$11)))-($C$17))/Model!$C$7)^2)/2)/SQRT(2*PI()))))) -> 1144.3889 | G36: =$C$12+$C$14*((Model!$C$5*(($B36)+Model!$C$6*(G$35)))-(Model!$C$5*(($C$10)+Model!$C$6*($C$11)))-$C$15*(((((Model!$C$5*(($B36)+Model!$C$6*(G$35)))-($C$16))*NORMSDIST(((Model!$C$5*(($B36)+Model!$C$6*(G$35)))-($C$16))/Model!$C$7)+Model!$C$7*EXP(-((((Model!$C$5*(($B36)+Model!$C$6*(G$35)))-($C$16))/Model!$C$7)^2)/2)/SQRT(2*PI()))-(((Model!$C$5*(($B36)+Model!$C$6*(G$35)))-($C$17))*NORMSDIST(((Model!$C$5*(($B36)+Model!$C$6*(G$35)))-($C$17))/Model!$C$7)+Model!$C$7*EXP(-((((Model!$C$5*(($B36)+Model!$C$6*(G$35)))-($C$17))/Model!$C$7)^2)/2)/SQRT(2*PI())))-((((Model!$C$5*(($C$10)+Model!$C$6*($C$11)))-($C$16))*NORMSDIST(((Model!$C$5*(($C$10)+Model!$C$6*($C$11)))-($C$16))/Model!$C$7)+Model!$C$7*EXP(-((((Model!$C$5*(($C$10)+Model!$C$6*($C$11)))-($C$16))/Model!$C$7)^2)/2)/SQRT(2*PI()))-(((Model!$C$5*(($C$10)+Model!$C$6*($C$11)))-($C$17))*NORMSDIST(((Model!$C$5*(($C$10)+Model!$C$6*($C$11)))-($C$17))/Model!$C$7)+Model!$C$7*EXP(-((((Model!$C$5*(($C$10)+Model!$C$6*($C$11)))-($C$17))/Model!$C$7)^2)/2)/SQRT(2*PI()))))) -> 1182.7242
B37: =$C$10+(20) -> 104 | C37: =$C$12+$C$14*((Model!$C$5*(($B37)+Model!$C$6*(C$35)))-(Model!$C$5*(($C$10)+Model!$C$6*($C$11)))-$C$15*(((((Model!$C$5*(($B37)+Model!$C$6*(C$35)))-($C$16))*NORMSDIST(((Model!$C$5*(($B37)+Model!$C$6*(C$35)))-($C$16))/Model!$C$7)+Model!$C$7*EXP(-((((Model!$C$5*(($B37)+Model!$C$6*(C$35)))-($C$16))/Model!$C$7)^2)/2)/SQRT(2*PI()))-(((Model!$C$5*(($B37)+Model!$C$6*(C$35)))-($C$17))*NORMSDIST(((Model!$C$5*(($B37)+Model!$C$6*(C$35)))-($C$17))/Model!$C$7)+Model!$C$7*EXP(-((((Model!$C$5*(($B37)+Model!$C$6*(C$35)))-($C$17))/Model!$C$7)^2)/2)/SQRT(2*PI())))-((((Model!$C$5*(($C$10)+Model!$C$6*($C$11)))-($C$16))*NORMSDIST(((Model!$C$5*(($C$10)+Model!$C$6*($C$11)))-($C$16))/Model!$C$7)+Model!$C$7*EXP(-((((Model!$C$5*(($C$10)+Model!$C$6*($C$11)))-($C$16))/Model!$C$7)^2)/2)/SQRT(2*PI()))-(((Model!$C$5*(($C$10)+Model!$C$6*($C$11)))-($C$17))*NORMSDIST(((Model!$C$5*(($C$10)+Model!$C$6*($C$11)))-($C$17))/Model!$C$7)+Model!$C$7*EXP(-((((Model!$C$5*(($C$10)+Model!$C$6*($C$11)))-($C$17))/Model!$C$7)^2)/2)/SQRT(2*PI()))))) -> 1031.278 | D37: =$C$12+$C$14*((Model!$C$5*(($B37)+Model!$C$6*(D$35)))-(Model!$C$5*(($C$10)+Model!$C$6*($C$11)))-$C$15*(((((Model!$C$5*(($B37)+Model!$C$6*(D$35)))-($C$16))*NORMSDIST(((Model!$C$5*(($B37)+Model!$C$6*(D$35)))-($C$16))/Model!$C$7)+Model!$C$7*EXP(-((((Model!$C$5*(($B37)+Model!$C$6*(D$35)))-($C$16))/Model!$C$7)^2)/2)/SQRT(2*PI()))-(((Model!$C$5*(($B37)+Model!$C$6*(D$35)))-($C$17))*NORMSDIST(((Model!$C$5*(($B37)+Model!$C$6*(D$35)))-($C$17))/Model!$C$7)+Model!$C$7*EXP(-((((Model!$C$5*(($B37)+Model!$C$6*(D$35)))-($C$17))/Model!$C$7)^2)/2)/SQRT(2*PI())))-((((Model!$C$5*(($C$10)+Model!$C$6*($C$11)))-($C$16))*NORMSDIST(((Model!$C$5*(($C$10)+Model!$C$6*($C$11)))-($C$16))/Model!$C$7)+Model!$C$7*EXP(-((((Model!$C$5*(($C$10)+Model!$C$6*($C$11)))-($C$16))/Model!$C$7)^2)/2)/SQRT(2*PI()))-(((Model!$C$5*(($C$10)+Model!$C$6*($C$11)))-($C$17))*NORMSDIST(((Model!$C$5*(($C$10)+Model!$C$6*($C$11)))-($C$17))/Model!$C$7)+Model!$C$7*EXP(-((((Model!$C$5*(($C$10)+Model!$C$6*($C$11)))-($C$17))/Model!$C$7)^2)/2)/SQRT(2*PI()))))) -> 1052.4561 | E37: =$C$12+$C$14*((Model!$C$5*(($B37)+Model!$C$6*(E$35)))-(Model!$C$5*(($C$10)+Model!$C$6*($C$11)))-$C$15*(((((Model!$C$5*(($B37)+Model!$C$6*(E$35)))-($C$16))*NORMSDIST(((Model!$C$5*(($B37)+Model!$C$6*(E$35)))-($C$16))/Model!$C$7)+Model!$C$7*EXP(-((((Model!$C$5*(($B37)+Model!$C$6*(E$35)))-($C$16))/Model!$C$7)^2)/2)/SQRT(2*PI()))-(((Model!$C$5*(($B37)+Model!$C$6*(E$35)))-($C$17))*NORMSDIST(((Model!$C$5*(($B37)+Model!$C$6*(E$35)))-($C$17))/Model!$C$7)+Model!$C$7*EXP(-((((Model!$C$5*(($B37)+Model!$C$6*(E$35)))-($C$17))/Model!$C$7)^2)/2)/SQRT(2*PI())))-((((Model!$C$5*(($C$10)+Model!$C$6*($C$11)))-($C$16))*NORMSDIST(((Model!$C$5*(($C$10)+Model!$C$6*($C$11)))-($C$16))/Model!$C$7)+Model!$C$7*EXP(-((((Model!$C$5*(($C$10)+Model!$C$6*($C$11)))-($C$16))/Model!$C$7)^2)/2)/SQRT(2*PI()))-(((Model!$C$5*(($C$10)+Model!$C$6*($C$11)))-($C$17))*NORMSDIST(((Model!$C$5*(($C$10)+Model!$C$6*($C$11)))-($C$17))/Model!$C$7)+Model!$C$7*EXP(-((((Model!$C$5*(($C$10)+Model!$C$6*($C$11)))-($C$17))/Model!$C$7)^2)/2)/SQRT(2*PI()))))) -> 1079.8935 | F37: =$C$12+$C$14*((Model!$C$5*(($B37)+Model!$C$6*(F$35)))-(Model!$C$5*(($C$10)+Model!$C$6*($C$11)))-$C$15*(((((Model!$C$5*(($B37)+Model!$C$6*(F$35)))-($C$16))*NORMSDIST(((Model!$C$5*(($B37)+Model!$C$6*(F$35)))-($C$16))/Model!$C$7)+Model!$C$7*EXP(-((((Model!$C$5*(($B37)+Model!$C$6*(F$35)))-($C$16))/Model!$C$7)^2)/2)/SQRT(2*PI()))-(((Model!$C$5*(($B37)+Model!$C$6*(F$35)))-($C$17))*NORMSDIST(((Model!$C$5*(($B37)+Model!$C$6*(F$35)))-($C$17))/Model!$C$7)+Model!$C$7*EXP(-((((Model!$C$5*(($B37)+Model!$C$6*(F$35)))-($C$17))/Model!$C$7)^2)/2)/SQRT(2*PI())))-((((Model!$C$5*(($C$10)+Model!$C$6*($C$11)))-($C$16))*NORMSDIST(((Model!$C$5*(($C$10)+Model!$C$6*($C$11)))-($C$16))/Model!$C$7)+Model!$C$7*EXP(-((((Model!$C$5*(($C$10)+Model!$C$6*($C$11)))-($C$16))/Model!$C$7)^2)/2)/SQRT(2*PI()))-(((Model!$C$5*(($C$10)+Model!$C$6*($C$11)))-($C$17))*NORMSDIST(((Model!$C$5*(($C$10)+Model!$C$6*($C$11)))-($C$17))/Model!$C$7)+Model!$C$7*EXP(-((((Model!$C$5*(($C$10)+Model!$C$6*($C$11)))-($C$17))/Model!$C$7)^2)/2)/SQRT(2*PI()))))) -> 1112.7539 | G37: =$C$12+$C$14*((Model!$C$5*(($B37)+Model!$C$6*(G$35)))-(Model!$C$5*(($C$10)+Model!$C$6*($C$11)))-$C$15*(((((Model!$C$5*(($B37)+Model!$C$6*(G$35)))-($C$16))*NORMSDIST(((Model!$C$5*(($B37)+Model!$C$6*(G$35)))-($C$16))/Model!$C$7)+Model!$C$7*EXP(-((((Model!$C$5*(($B37)+Model!$C$6*(G$35)))-($C$16))/Model!$C$7)^2)/2)/SQRT(2*PI()))-(((Model!$C$5*(($B37)+Model!$C$6*(G$35)))-($C$17))*NORMSDIST(((Model!$C$5*(($B37)+Model!$C$6*(G$35)))-($C$17))/Model!$C$7)+Model!$C$7*EXP(-((((Model!$C$5*(($B37)+Model!$C$6*(G$35)))-($C$17))/Model!$C$7)^2)/2)/SQRT(2*PI())))-((((Model!$C$5*(($C$10)+Model!$C$6*($C$11)))-($C$16))*NORMSDIST(((Model!$C$5*(($C$10)+Model!$C$6*($C$11)))-($C$16))/Model!$C$7)+Model!$C$7*EXP(-((((Model!$C$5*(($C$10)+Model!$C$6*($C$11)))-($C$16))/Model!$C$7)^2)/2)/SQRT(2*PI()))-(((Model!$C$5*(($C$10)+Model!$C$6*($C$11)))-($C$17))*NORMSDIST(((Model!$C$5*(($C$10)+Model!$C$6*($C$11)))-($C$17))/Model!$C$7)+Model!$C$7*EXP(-((((Model!$C$5*(($C$10)+Model!$C$6*($C$11)))-($C$17))/Model!$C$7)^2)/2)/SQRT(2*PI()))))) -> 1149.2993
B38: =$C$10+(10) -> 94 | C38: =$C$12+$C$14*((Model!$C$5*(($B38)+Model!$C$6*(C$35)))-(Model!$C$5*(($C$10)+Model!$C$6*($C$11)))-$C$15*(((((Model!$C$5*(($B38)+Model!$C$6*(C$35)))-($C$16))*NORMSDIST(((Model!$C$5*(($B38)+Model!$C$6*(C$35)))-($C$16))/Model!$C$7)+Model!$C$7*EXP(-((((Model!$C$5*(($B38)+Model!$C$6*(C$35)))-($C$16))/Model!$C$7)^2)/2)/SQRT(2*PI()))-(((Model!$C$5*(($B38)+Model!$C$6*(C$35)))-($C$17))*NORMSDIST(((Model!$C$5*(($B38)+Model!$C$6*(C$35)))-($C$17))/Model!$C$7)+Model!$C$7*EXP(-((((Model!$C$5*(($B38)+Model!$C$6*(C$35)))-($C$17))/Model!$C$7)^2)/2)/SQRT(2*PI())))-((((Model!$C$5*(($C$10)+Model!$C$6*($C$11)))-($C$16))*NORMSDIST(((Model!$C$5*(($C$10)+Model!$C$6*($C$11)))-($C$16))/Model!$C$7)+Model!$C$7*EXP(-((((Model!$C$5*(($C$10)+Model!$C$6*($C$11)))-($C$16))/Model!$C$7)^2)/2)/SQRT(2*PI()))-(((Model!$C$5*(($C$10)+Model!$C$6*($C$11)))-($C$17))*NORMSDIST(((Model!$C$5*(($C$10)+Model!$C$6*($C$11)))-($C$17))/Model!$C$7)+Model!$C$7*EXP(-((((Model!$C$5*(($C$10)+Model!$C$6*($C$11)))-($C$17))/Model!$C$7)^2)/2)/SQRT(2*PI()))))) -> 1017.4824 | D38: =$C$12+$C$14*((Model!$C$5*(($B38)+Model!$C$6*(D$35)))-(Model!$C$5*(($C$10)+Model!$C$6*($C$11)))-$C$15*(((((Model!$C$5*(($B38)+Model!$C$6*(D$35)))-($C$16))*NORMSDIST(((Model!$C$5*(($B38)+Model!$C$6*(D$35)))-($C$16))/Model!$C$7)+Model!$C$7*EXP(-((((Model!$C$5*(($B38)+Model!$C$6*(D$35)))-($C$16))/Model!$C$7)^2)/2)/SQRT(2*PI()))-(((Model!$C$5*(($B38)+Model!$C$6*(D$35)))-($C$17))*NORMSDIST(((Model!$C$5*(($B38)+Model!$C$6*(D$35)))-($C$17))/Model!$C$7)+Model!$C$7*EXP(-((((Model!$C$5*(($B38)+Model!$C$6*(D$35)))-($C$17))/Model!$C$7)^2)/2)/SQRT(2*PI())))-((((Model!$C$5*(($C$10)+Model!$C$6*($C$11)))-($C$16))*NORMSDIST(((Model!$C$5*(($C$10)+Model!$C$6*($C$11)))-($C$16))/Model!$C$7)+Model!$C$7*EXP(-((((Model!$C$5*(($C$10)+Model!$C$6*($C$11)))-($C$16))/Model!$C$7)^2)/2)/SQRT(2*PI()))-(((Model!$C$5*(($C$10)+Model!$C$6*($C$11)))-($C$17))*NORMSDIST(((Model!$C$5*(($C$10)+Model!$C$6*($C$11)))-($C$17))/Model!$C$7)+Model!$C$7*EXP(-((((Model!$C$5*(($C$10)+Model!$C$6*($C$11)))-($C$17))/Model!$C$7)^2)/2)/SQRT(2*PI()))))) -> 1033.6932 | E38: =$C$12+$C$14*((Model!$C$5*(($B38)+Model!$C$6*(E$35)))-(Model!$C$5*(($C$10)+Model!$C$6*($C$11)))-$C$15*(((((Model!$C$5*(($B38)+Model!$C$6*(E$35)))-($C$16))*NORMSDIST(((Model!$C$5*(($B38)+Model!$C$6*(E$35)))-($C$16))/Model!$C$7)+Model!$C$7*EXP(-((((Model!$C$5*(($B38)+Model!$C$6*(E$35)))-($C$16))/Model!$C$7)^2)/2)/SQRT(2*PI()))-(((Model!$C$5*(($B38)+Model!$C$6*(E$35)))-($C$17))*NORMSDIST(((Model!$C$5*(($B38)+Model!$C$6*(E$35)))-($C$17))/Model!$C$7)+Model!$C$7*EXP(-((((Model!$C$5*(($B38)+Model!$C$6*(E$35)))-($C$17))/Model!$C$7)^2)/2)/SQRT(2*PI())))-((((Model!$C$5*(($C$10)+Model!$C$6*($C$11)))-($C$16))*NORMSDIST(((Model!$C$5*(($C$10)+Model!$C$6*($C$11)))-($C$16))/Model!$C$7)+Model!$C$7*EXP(-((((Model!$C$5*(($C$10)+Model!$C$6*($C$11)))-($C$16))/Model!$C$7)^2)/2)/SQRT(2*PI()))-(((Model!$C$5*(($C$10)+Model!$C$6*($C$11)))-($C$17))*NORMSDIST(((Model!$C$5*(($C$10)+Model!$C$6*($C$11)))-($C$17))/Model!$C$7)+Model!$C$7*EXP(-((((Model!$C$5*(($C$10)+Model!$C$6*($C$11)))-($C$17))/Model!$C$7)^2)/2)/SQRT(2*PI()))))) -> 1055.6838 | F38: =$C$12+$C$14*((Model!$C$5*(($B38)+Model!$C$6*(F$35)))-(Model!$C$5*(($C$10)+Model!$C$6*($C$11)))-$C$15*(((((Model!$C$5*(($B38)+Model!$C$6*(F$35)))-($C$16))*NORMSDIST(((Model!$C$5*(($B38)+Model!$C$6*(F$35)))-($C$16))/Model!$C$7)+Model!$C$7*EXP(-((((Model!$C$5*(($B38)+Model!$C$6*(F$35)))-($C$16))/Model!$C$7)^2)/2)/SQRT(2*PI()))-(((Model!$C$5*(($B38)+Model!$C$6*(F$35)))-($C$17))*NORMSDIST(((Model!$C$5*(($B38)+Model!$C$6*(F$35)))-($C$17))/Model!$C$7)+Model!$C$7*EXP(-((((Model!$C$5*(($B38)+Model!$C$6*(F$35)))-($C$17))/Model!$C$7)^2)/2)/SQRT(2*PI())))-((((Model!$C$5*(($C$10)+Model!$C$6*($C$11)))-($C$16))*NORMSDIST(((Model!$C$5*(($C$10)+Model!$C$6*($C$11)))-($C$16))/Model!$C$7)+Model!$C$7*EXP(-((((Model!$C$5*(($C$10)+Model!$C$6*($C$11)))-($C$16))/Model!$C$7)^2)/2)/SQRT(2*PI()))-(((Model!$C$5*(($C$10)+Model!$C$6*($C$11)))-($C$17))*NORMSDIST(((Model!$C$5*(($C$10)+Model!$C$6*($C$11)))-($C$17))/Model!$C$7)+Model!$C$7*EXP(-((((Model!$C$5*(($C$10)+Model!$C$6*($C$11)))-($C$17))/Model!$C$7)^2)/2)/SQRT(2*PI()))))) -> 1083.9042 | G38: =$C$12+$C$14*((Model!$C$5*(($B38)+Model!$C$6*(G$35)))-(Model!$C$5*(($C$10)+Model!$C$6*($C$11)))-$C$15*(((((Model!$C$5*(($B38)+Model!$C$6*(G$35)))-($C$16))*NORMSDIST(((Model!$C$5*(($B38)+Model!$C$6*(G$35)))-($C$16))/Model!$C$7)+Model!$C$7*EXP(-((((Model!$C$5*(($B38)+Model!$C$6*(G$35)))-($C$16))/Model!$C$7)^2)/2)/SQRT(2*PI()))-(((Model!$C$5*(($B38)+Model!$C$6*(G$35)))-($C$17))*NORMSDIST(((Model!$C$5*(($B38)+Model!$C$6*(G$35)))-($C$17))/Model!$C$7)+Model!$C$7*EXP(-((((Model!$C$5*(($B38)+Model!$C$6*(G$35)))-($C$17))/Model!$C$7)^2)/2)/SQRT(2*PI())))-((((Model!$C$5*(($C$10)+Model!$C$6*($C$11)))-($C$16))*NORMSDIST(((Model!$C$5*(($C$10)+Model!$C$6*($C$11)))-($C$16))/Model!$C$7)+Model!$C$7*EXP(-((((Model!$C$5*(($C$10)+Model!$C$6*($C$11)))-($C$16))/Model!$C$7)^2)/2)/SQRT(2*PI()))-(((Model!$C$5*(($C$10)+Model!$C$6*($C$11)))-($C$17))*NORMSDIST(((Model!$C$5*(($C$10)+Model!$C$6*($C$11)))-($C$17))/Model!$C$7)+Model!$C$7*EXP(-((((Model!$C$5*(($C$10)+Model!$C$6*($C$11)))-($C$17))/Model!$C$7)^2)/2)/SQRT(2*PI()))))) -> 1117.3522
B39: =$C$10+(0) -> 84 | C39: =$C$12+$C$14*((Model!$C$5*(($B39)+Model!$C$6*(C$35)))-(Model!$C$5*(($C$10)+Model!$C$6*($C$11)))-$C$15*(((((Model!$C$5*(($B39)+Model!$C$6*(C$35)))-($C$16))*NORMSDIST(((Model!$C$5*(($B39)+Model!$C$6*(C$35)))-($C$16))/Model!$C$7)+Model!$C$7*EXP(-((((Model!$C$5*(($B39)+Model!$C$6*(C$35)))-($C$16))/Model!$C$7)^2)/2)/SQRT(2*PI()))-(((Model!$C$5*(($B39)+Model!$C$6*(C$35)))-($C$17))*NORMSDIST(((Model!$C$5*(($B39)+Model!$C$6*(C$35)))-($C$17))/Model!$C$7)+Model!$C$7*EXP(-((((Model!$C$5*(($B39)+Model!$C$6*(C$35)))-($C$17))/Model!$C$7)^2)/2)/SQRT(2*PI())))-((((Model!$C$5*(($C$10)+Model!$C$6*($C$11)))-($C$16))*NORMSDIST(((Model!$C$5*(($C$10)+Model!$C$6*($C$11)))-($C$16))/Model!$C$7)+Model!$C$7*EXP(-((((Model!$C$5*(($C$10)+Model!$C$6*($C$11)))-($C$16))/Model!$C$7)^2)/2)/SQRT(2*PI()))-(((Model!$C$5*(($C$10)+Model!$C$6*($C$11)))-($C$17))*NORMSDIST(((Model!$C$5*(($C$10)+Model!$C$6*($C$11)))-($C$17))/Model!$C$7)+Model!$C$7*EXP(-((((Model!$C$5*(($C$10)+Model!$C$6*($C$11)))-($C$17))/Model!$C$7)^2)/2)/SQRT(2*PI()))))) -> 1006.7238 | D39: =$C$12+$C$14*((Model!$C$5*(($B39)+Model!$C$6*(D$35)))-(Model!$C$5*(($C$10)+Model!$C$6*($C$11)))-$C$15*(((((Model!$C$5*(($B39)+Model!$C$6*(D$35)))-($C$16))*NORMSDIST(((Model!$C$5*(($B39)+Model!$C$6*(D$35)))-($C$16))/Model!$C$7)+Model!$C$7*EXP(-((((Model!$C$5*(($B39)+Model!$C$6*(D$35)))-($C$16))/Model!$C$7)^2)/2)/SQRT(2*PI()))-(((Model!$C$5*(($B39)+Model!$C$6*(D$35)))-($C$17))*NORMSDIST(((Model!$C$5*(($B39)+Model!$C$6*(D$35)))-($C$17))/Model!$C$7)+Model!$C$7*EXP(-((((Model!$C$5*(($B39)+Model!$C$6*(D$35)))-($C$17))/Model!$C$7)^2)/2)/SQRT(2*PI())))-((((Model!$C$5*(($C$10)+Model!$C$6*($C$11)))-($C$16))*NORMSDIST(((Model!$C$5*(($C$10)+Model!$C$6*($C$11)))-($C$16))/Model!$C$7)+Model!$C$7*EXP(-((((Model!$C$5*(($C$10)+Model!$C$6*($C$11)))-($C$16))/Model!$C$7)^2)/2)/SQRT(2*PI()))-(((Model!$C$5*(($C$10)+Model!$C$6*($C$11)))-($C$17))*NORMSDIST(((Model!$C$5*(($C$10)+Model!$C$6*($C$11)))-($C$17))/Model!$C$7)+Model!$C$7*EXP(-((((Model!$C$5*(($C$10)+Model!$C$6*($C$11)))-($C$17))/Model!$C$7)^2)/2)/SQRT(2*PI()))))) -> 1019.3221 | E39: =$C$12+$C$14*((Model!$C$5*(($B39)+Model!$C$6*(E$35)))-(Model!$C$5*(($C$10)+Model!$C$6*($C$11)))-$C$15*(((((Model!$C$5*(($B39)+Model!$C$6*(E$35)))-($C$16))*NORMSDIST(((Model!$C$5*(($B39)+Model!$C$6*(E$35)))-($C$16))/Model!$C$7)+Model!$C$7*EXP(-((((Model!$C$5*(($B39)+Model!$C$6*(E$35)))-($C$16))/Model!$C$7)^2)/2)/SQRT(2*PI()))-(((Model!$C$5*(($B39)+Model!$C$6*(E$35)))-($C$17))*NORMSDIST(((Model!$C$5*(($B39)+Model!$C$6*(E$35)))-($C$17))/Model!$C$7)+Model!$C$7*EXP(-((((Model!$C$5*(($B39)+Model!$C$6*(E$35)))-($C$17))/Model!$C$7)^2)/2)/SQRT(2*PI())))-((((Model!$C$5*(($C$10)+Model!$C$6*($C$11)))-($C$16))*NORMSDIST(((Model!$C$5*(($C$10)+Model!$C$6*($C$11)))-($C$16))/Model!$C$7)+Model!$C$7*EXP(-((((Model!$C$5*(($C$10)+Model!$C$6*($C$11)))-($C$16))/Model!$C$7)^2)/2)/SQRT(2*PI()))-(((Model!$C$5*(($C$10)+Model!$C$6*($C$11)))-($C$17))*NORMSDIST(((Model!$C$5*(($C$10)+Model!$C$6*($C$11)))-($C$17))/Model!$C$7)+Model!$C$7*EXP(-((((Model!$C$5*(($C$10)+Model!$C$6*($C$11)))-($C$17))/Model!$C$7)^2)/2)/SQRT(2*PI()))))) -> 1036.2086 | F39: =$C$12+$C$14*((Model!$C$5*(($B39)+Model!$C$6*(F$35)))-(Model!$C$5*(($C$10)+Model!$C$6*($C$11)))-$C$15*(((((Model!$C$5*(($B39)+Model!$C$6*(F$35)))-($C$16))*NORMSDIST(((Model!$C$5*(($B39)+Model!$C$6*(F$35)))-($C$16))/Model!$C$7)+Model!$C$7*EXP(-((((Model!$C$5*(($B39)+Model!$C$6*(F$35)))-($C$16))/Model!$C$7)^2)/2)/SQRT(2*PI()))-(((Model!$C$5*(($B39)+Model!$C$6*(F$35)))-($C$17))*NORMSDIST(((Model!$C$5*(($B39)+Model!$C$6*(F$35)))-($C$17))/Model!$C$7)+Model!$C$7*EXP(-((((Model!$C$5*(($B39)+Model!$C$6*(F$35)))-($C$17))/Model!$C$7)^2)/2)/SQRT(2*PI())))-((((Model!$C$5*(($C$10)+Model!$C$6*($C$11)))-($C$16))*NORMSDIST(((Model!$C$5*(($C$10)+Model!$C$6*($C$11)))-($C$16))/Model!$C$7)+Model!$C$7*EXP(-((((Model!$C$5*(($C$10)+Model!$C$6*($C$11)))-($C$16))/Model!$C$7)^2)/2)/SQRT(2*PI()))-(((Model!$C$5*(($C$10)+Model!$C$6*($C$11)))-($C$17))*NORMSDIST(((Model!$C$5*(($C$10)+Model!$C$6*($C$11)))-($C$17))/Model!$C$7)+Model!$C$7*EXP(-((((Model!$C$5*(($C$10)+Model!$C$6*($C$11)))-($C$17))/Model!$C$7)^2)/2)/SQRT(2*PI()))))) -> 1059.0198 | G39: =$C$12+$C$14*((Model!$C$5*(($B39)+Model!$C$6*(G$35)))-(Model!$C$5*(($C$10)+Model!$C$6*($C$11)))-$C$15*(((((Model!$C$5*(($B39)+Model!$C$6*(G$35)))-($C$16))*NORMSDIST(((Model!$C$5*(($B39)+Model!$C$6*(G$35)))-($C$16))/Model!$C$7)+Model!$C$7*EXP(-((((Model!$C$5*(($B39)+Model!$C$6*(G$35)))-($C$16))/Model!$C$7)^2)/2)/SQRT(2*PI()))-(((Model!$C$5*(($B39)+Model!$C$6*(G$35)))-($C$17))*NORMSDIST(((Model!$C$5*(($B39)+Model!$C$6*(G$35)))-($C$17))/Model!$C$7)+Model!$C$7*EXP(-((((Model!$C$5*(($B39)+Model!$C$6*(G$35)))-($C$17))/Model!$C$7)^2)/2)/SQRT(2*PI())))-((((Model!$C$5*(($C$10)+Model!$C$6*($C$11)))-($C$16))*NORMSDIST(((Model!$C$5*(($C$10)+Model!$C$6*($C$11)))-($C$16))/Model!$C$7)+Model!$C$7*EXP(-((((Model!$C$5*(($C$10)+Model!$C$6*($C$11)))-($C$16))/Model!$C$7)^2)/2)/SQRT(2*PI()))-(((Model!$C$5*(($C$10)+Model!$C$6*($C$11)))-($C$17))*NORMSDIST(((Model!$C$5*(($C$10)+Model!$C$6*($C$11)))-($C$17))/Model!$C$7)+Model!$C$7*EXP(-((((Model!$C$5*(($C$10)+Model!$C$6*($C$11)))-($C$17))/Model!$C$7)^2)/2)/SQRT(2*PI()))))) -> 1088.005
B40: =$C$10+(-10) -> 74 | C40: =$C$12+$C$14*((Model!$C$5*(($B40)+Model!$C$6*(C$35)))-(Model!$C$5*(($C$10)+Model!$C$6*($C$11)))-$C$15*(((((Model!$C$5*(($B40)+Model!$C$6*(C$35)))-($C$16))*NORMSDIST(((Model!$C$5*(($B40)+Model!$C$6*(C$35)))-($C$16))/Model!$C$7)+Model!$C$7*EXP(-((((Model!$C$5*(($B40)+Model!$C$6*(C$35)))-($C$16))/Model!$C$7)^2)/2)/SQRT(2*PI()))-(((Model!$C$5*(($B40)+Model!$C$6*(C$35)))-($C$17))*NORMSDIST(((Model!$C$5*(($B40)+Model!$C$6*(C$35)))-($C$17))/Model!$C$7)+Model!$C$7*EXP(-((((Model!$C$5*(($B40)+Model!$C$6*(C$35)))-($C$17))/Model!$C$7)^2)/2)/SQRT(2*PI())))-((((Model!$C$5*(($C$10)+Model!$C$6*($C$11)))-($C$16))*NORMSDIST(((Model!$C$5*(($C$10)+Model!$C$6*($C$11)))-($C$16))/Model!$C$7)+Model!$C$7*EXP(-((((Model!$C$5*(($C$10)+Model!$C$6*($C$11)))-($C$16))/Model!$C$7)^2)/2)/SQRT(2*PI()))-(((Model!$C$5*(($C$10)+Model!$C$6*($C$11)))-($C$17))*NORMSDIST(((Model!$C$5*(($C$10)+Model!$C$6*($C$11)))-($C$17))/Model!$C$7)+Model!$C$7*EXP(-((((Model!$C$5*(($C$10)+Model!$C$6*($C$11)))-($C$17))/Model!$C$7)^2)/2)/SQRT(2*PI()))))) -> 997.39512 | D40: =$C$12+$C$14*((Model!$C$5*(($B40)+Model!$C$6*(D$35)))-(Model!$C$5*(($C$10)+Model!$C$6*($C$11)))-$C$15*(((((Model!$C$5*(($B40)+Model!$C$6*(D$35)))-($C$16))*NORMSDIST(((Model!$C$5*(($B40)+Model!$C$6*(D$35)))-($C$16))/Model!$C$7)+Model!$C$7*EXP(-((((Model!$C$5*(($B40)+Model!$C$6*(D$35)))-($C$16))/Model!$C$7)^2)/2)/SQRT(2*PI()))-(((Model!$C$5*(($B40)+Model!$C$6*(D$35)))-($C$17))*NORMSDIST(((Model!$C$5*(($B40)+Model!$C$6*(D$35)))-($C$17))/Model!$C$7)+Model!$C$7*EXP(-((((Model!$C$5*(($B40)+Model!$C$6*(D$35)))-($C$17))/Model!$C$7)^2)/2)/SQRT(2*PI())))-((((Model!$C$5*(($C$10)+Model!$C$6*($C$11)))-($C$16))*NORMSDIST(((Model!$C$5*(($C$10)+Model!$C$6*($C$11)))-($C$16))/Model!$C$7)+Model!$C$7*EXP(-((((Model!$C$5*(($C$10)+Model!$C$6*($C$11)))-($C$16))/Model!$C$7)^2)/2)/SQRT(2*PI()))-(((Model!$C$5*(($C$10)+Model!$C$6*($C$11)))-($C$17))*NORMSDIST(((Model!$C$5*(($C$10)+Model!$C$6*($C$11)))-($C$17))/Model!$C$7)+Model!$C$7*EXP(-((((Model!$C$5*(($C$10)+Model!$C$6*($C$11)))-($C$17))/Model!$C$7)^2)/2)/SQRT(2*PI()))))) -> 1008.205 | E40: =$C$12+$C$14*((Model!$C$5*(($B40)+Model!$C$6*(E$35)))-(Model!$C$5*(($C$10)+Model!$C$6*($C$11)))-$C$15*(((((Model!$C$5*(($B40)+Model!$C$6*(E$35)))-($C$16))*NORMSDIST(((Model!$C$5*(($B40)+Model!$C$6*(E$35)))-($C$16))/Model!$C$7)+Model!$C$7*EXP(-((((Model!$C$5*(($B40)+Model!$C$6*(E$35)))-($C$16))/Model!$C$7)^2)/2)/SQRT(2*PI()))-(((Model!$C$5*(($B40)+Model!$C$6*(E$35)))-($C$17))*NORMSDIST(((Model!$C$5*(($B40)+Model!$C$6*(E$35)))-($C$17))/Model!$C$7)+Model!$C$7*EXP(-((((Model!$C$5*(($B40)+Model!$C$6*(E$35)))-($C$17))/Model!$C$7)^2)/2)/SQRT(2*PI())))-((((Model!$C$5*(($C$10)+Model!$C$6*($C$11)))-($C$16))*NORMSDIST(((Model!$C$5*(($C$10)+Model!$C$6*($C$11)))-($C$16))/Model!$C$7)+Model!$C$7*EXP(-((((Model!$C$5*(($C$10)+Model!$C$6*($C$11)))-($C$16))/Model!$C$7)^2)/2)/SQRT(2*PI()))-(((Model!$C$5*(($C$10)+Model!$C$6*($C$11)))-($C$17))*NORMSDIST(((Model!$C$5*(($C$10)+Model!$C$6*($C$11)))-($C$17))/Model!$C$7)+Model!$C$7*EXP(-((((Model!$C$5*(($C$10)+Model!$C$6*($C$11)))-($C$17))/Model!$C$7)^2)/2)/SQRT(2*PI()))))) -> 1021.2358 | F40: =$C$12+$C$14*((Model!$C$5*(($B40)+Model!$C$6*(F$35)))-(Model!$C$5*(($C$10)+Model!$C$6*($C$11)))-$C$15*(((((Model!$C$5*(($B40)+Model!$C$6*(F$35)))-($C$16))*NORMSDIST(((Model!$C$5*(($B40)+Model!$C$6*(F$35)))-($C$16))/Model!$C$7)+Model!$C$7*EXP(-((((Model!$C$5*(($B40)+Model!$C$6*(F$35)))-($C$16))/Model!$C$7)^2)/2)/SQRT(2*PI()))-(((Model!$C$5*(($B40)+Model!$C$6*(F$35)))-($C$17))*NORMSDIST(((Model!$C$5*(($B40)+Model!$C$6*(F$35)))-($C$17))/Model!$C$7)+Model!$C$7*EXP(-((((Model!$C$5*(($B40)+Model!$C$6*(F$35)))-($C$17))/Model!$C$7)^2)/2)/SQRT(2*PI())))-((((Model!$C$5*(($C$10)+Model!$C$6*($C$11)))-($C$16))*NORMSDIST(((Model!$C$5*(($C$10)+Model!$C$6*($C$11)))-($C$16))/Model!$C$7)+Model!$C$7*EXP(-((((Model!$C$5*(($C$10)+Model!$C$6*($C$11)))-($C$16))/Model!$C$7)^2)/2)/SQRT(2*PI()))-(((Model!$C$5*(($C$10)+Model!$C$6*($C$11)))-($C$17))*NORMSDIST(((Model!$C$5*(($C$10)+Model!$C$6*($C$11)))-($C$17))/Model!$C$7)+Model!$C$7*EXP(-((((Model!$C$5*(($C$10)+Model!$C$6*($C$11)))-($C$17))/Model!$C$7)^2)/2)/SQRT(2*PI()))))) -> 1038.827 | G40: =$C$12+$C$14*((Model!$C$5*(($B40)+Model!$C$6*(G$35)))-(Model!$C$5*(($C$10)+Model!$C$6*($C$11)))-$C$15*(((((Model!$C$5*(($B40)+Model!$C$6*(G$35)))-($C$16))*NORMSDIST(((Model!$C$5*(($B40)+Model!$C$6*(G$35)))-($C$16))/Model!$C$7)+Model!$C$7*EXP(-((((Model!$C$5*(($B40)+Model!$C$6*(G$35)))-($C$16))/Model!$C$7)^2)/2)/SQRT(2*PI()))-(((Model!$C$5*(($B40)+Model!$C$6*(G$35)))-($C$17))*NORMSDIST(((Model!$C$5*(($B40)+Model!$C$6*(G$35)))-($C$17))/Model!$C$7)+Model!$C$7*EXP(-((((Model!$C$5*(($B40)+Model!$C$6*(G$35)))-($C$17))/Model!$C$7)^2)/2)/SQRT(2*PI())))-((((Model!$C$5*(($C$10)+Model!$C$6*($C$11)))-($C$16))*NORMSDIST(((Model!$C$5*(($C$10)+Model!$C$6*($C$11)))-($C$16))/Model!$C$7)+Model!$C$7*EXP(-((((Model!$C$5*(($C$10)+Model!$C$6*($C$11)))-($C$16))/Model!$C$7)^2)/2)/SQRT(2*PI()))-(((Model!$C$5*(($C$10)+Model!$C$6*($C$11)))-($C$17))*NORMSDIST(((Model!$C$5*(($C$10)+Model!$C$6*($C$11)))-($C$17))/Model!$C$7)+Model!$C$7*EXP(-((((Model!$C$5*(($C$10)+Model!$C$6*($C$11)))-($C$17))/Model!$C$7)^2)/2)/SQRT(2*PI()))))) -> 1062.463
B41: =$C$10+(-20) -> 64 | C41: =$C$12+$C$14*((Model!$C$5*(($B41)+Model!$C$6*(C$35)))-(Model!$C$5*(($C$10)+Model!$C$6*($C$11)))-$C$15*(((((Model!$C$5*(($B41)+Model!$C$6*(C$35)))-($C$16))*NORMSDIST(((Model!$C$5*(($B41)+Model!$C$6*(C$35)))-($C$16))/Model!$C$7)+Model!$C$7*EXP(-((((Model!$C$5*(($B41)+Model!$C$6*(C$35)))-($C$16))/Model!$C$7)^2)/2)/SQRT(2*PI()))-(((Model!$C$5*(($B41)+Model!$C$6*(C$35)))-($C$17))*NORMSDIST(((Model!$C$5*(($B41)+Model!$C$6*(C$35)))-($C$17))/Model!$C$7)+Model!$C$7*EXP(-((((Model!$C$5*(($B41)+Model!$C$6*(C$35)))-($C$17))/Model!$C$7)^2)/2)/SQRT(2*PI())))-((((Model!$C$5*(($C$10)+Model!$C$6*($C$11)))-($C$16))*NORMSDIST(((Model!$C$5*(($C$10)+Model!$C$6*($C$11)))-($C$16))/Model!$C$7)+Model!$C$7*EXP(-((((Model!$C$5*(($C$10)+Model!$C$6*($C$11)))-($C$16))/Model!$C$7)^2)/2)/SQRT(2*PI()))-(((Model!$C$5*(($C$10)+Model!$C$6*($C$11)))-($C$17))*NORMSDIST(((Model!$C$5*(($C$10)+Model!$C$6*($C$11)))-($C$17))/Model!$C$7)+Model!$C$7*EXP(-((((Model!$C$5*(($C$10)+Model!$C$6*($C$11)))-($C$17))/Model!$C$7)^2)/2)/SQRT(2*PI()))))) -> 987.77824 | D41: =$C$12+$C$14*((Model!$C$5*(($B41)+Model!$C$6*(D$35)))-(Model!$C$5*(($C$10)+Model!$C$6*($C$11)))-$C$15*(((((Model!$C$5*(($B41)+Model!$C$6*(D$35)))-($C$16))*NORMSDIST(((Model!$C$5*(($B41)+Model!$C$6*(D$35)))-($C$16))/Model!$C$7)+Model!$C$7*EXP(-((((Model!$C$5*(($B41)+Model!$C$6*(D$35)))-($C$16))/Model!$C$7)^2)/2)/SQRT(2*PI()))-(((Model!$C$5*(($B41)+Model!$C$6*(D$35)))-($C$17))*NORMSDIST(((Model!$C$5*(($B41)+Model!$C$6*(D$35)))-($C$17))/Model!$C$7)+Model!$C$7*EXP(-((((Model!$C$5*(($B41)+Model!$C$6*(D$35)))-($C$17))/Model!$C$7)^2)/2)/SQRT(2*PI())))-((((Model!$C$5*(($C$10)+Model!$C$6*($C$11)))-($C$16))*NORMSDIST(((Model!$C$5*(($C$10)+Model!$C$6*($C$11)))-($C$16))/Model!$C$7)+Model!$C$7*EXP(-((((Model!$C$5*(($C$10)+Model!$C$6*($C$11)))-($C$16))/Model!$C$7)^2)/2)/SQRT(2*PI()))-(((Model!$C$5*(($C$10)+Model!$C$6*($C$11)))-($C$17))*NORMSDIST(((Model!$C$5*(($C$10)+Model!$C$6*($C$11)))-($C$17))/Model!$C$7)+Model!$C$7*EXP(-((((Model!$C$5*(($C$10)+Model!$C$6*($C$11)))-($C$17))/Model!$C$7)^2)/2)/SQRT(2*PI()))))) -> 998.77053 | E41: =$C$12+$C$14*((Model!$C$5*(($B41)+Model!$C$6*(E$35)))-(Model!$C$5*(($C$10)+Model!$C$6*($C$11)))-$C$15*(((((Model!$C$5*(($B41)+Model!$C$6*(E$35)))-($C$16))*NORMSDIST(((Model!$C$5*(($B41)+Model!$C$6*(E$35)))-($C$16))/Model!$C$7)+Model!$C$7*EXP(-((((Model!$C$5*(($B41)+Model!$C$6*(E$35)))-($C$16))/Model!$C$7)^2)/2)/SQRT(2*PI()))-(((Model!$C$5*(($B41)+Model!$C$6*(E$35)))-($C$17))*NORMSDIST(((Model!$C$5*(($B41)+Model!$C$6*(E$35)))-($C$17))/Model!$C$7)+Model!$C$7*EXP(-((((Model!$C$5*(($B41)+Model!$C$6*(E$35)))-($C$17))/Model!$C$7)^2)/2)/SQRT(2*PI())))-((((Model!$C$5*(($C$10)+Model!$C$6*($C$11)))-($C$16))*NORMSDIST(((Model!$C$5*(($C$10)+Model!$C$6*($C$11)))-($C$16))/Model!$C$7)+Model!$C$7*EXP(-((((Model!$C$5*(($C$10)+Model!$C$6*($C$11)))-($C$16))/Model!$C$7)^2)/2)/SQRT(2*PI()))-(((Model!$C$5*(($C$10)+Model!$C$6*($C$11)))-($C$17))*NORMSDIST(((Model!$C$5*(($C$10)+Model!$C$6*($C$11)))-($C$17))/Model!$C$7)+Model!$C$7*EXP(-((((Model!$C$5*(($C$10)+Model!$C$6*($C$11)))-($C$17))/Model!$C$7)^2)/2)/SQRT(2*PI()))))) -> 1009.7243 | F41: =$C$12+$C$14*((Model!$C$5*(($B41)+Model!$C$6*(F$35)))-(Model!$C$5*(($C$10)+Model!$C$6*($C$11)))-$C$15*(((((Model!$C$5*(($B41)+Model!$C$6*(F$35)))-($C$16))*NORMSDIST(((Model!$C$5*(($B41)+Model!$C$6*(F$35)))-($C$16))/Model!$C$7)+Model!$C$7*EXP(-((((Model!$C$5*(($B41)+Model!$C$6*(F$35)))-($C$16))/Model!$C$7)^2)/2)/SQRT(2*PI()))-(((Model!$C$5*(($B41)+Model!$C$6*(F$35)))-($C$17))*NORMSDIST(((Model!$C$5*(($B41)+Model!$C$6*(F$35)))-($C$17))/Model!$C$7)+Model!$C$7*EXP(-((((Model!$C$5*(($B41)+Model!$C$6*(F$35)))-($C$17))/Model!$C$7)^2)/2)/SQRT(2*PI())))-((((Model!$C$5*(($C$10)+Model!$C$6*($C$11)))-($C$16))*NORMSDIST(((Model!$C$5*(($C$10)+Model!$C$6*($C$11)))-($C$16))/Model!$C$7)+Model!$C$7*EXP(-((((Model!$C$5*(($C$10)+Model!$C$6*($C$11)))-($C$16))/Model!$C$7)^2)/2)/SQRT(2*PI()))-(((Model!$C$5*(($C$10)+Model!$C$6*($C$11)))-($C$17))*NORMSDIST(((Model!$C$5*(($C$10)+Model!$C$6*($C$11)))-($C$17))/Model!$C$7)+Model!$C$7*EXP(-((((Model!$C$5*(($C$10)+Model!$C$6*($C$11)))-($C$17))/Model!$C$7)^2)/2)/SQRT(2*PI()))))) -> 1023.2283 | G41: =$C$12+$C$14*((Model!$C$5*(($B41)+Model!$C$6*(G$35)))-(Model!$C$5*(($C$10)+Model!$C$6*($C$11)))-$C$15*(((((Model!$C$5*(($B41)+Model!$C$6*(G$35)))-($C$16))*NORMSDIST(((Model!$C$5*(($B41)+Model!$C$6*(G$35)))-($C$16))/Model!$C$7)+Model!$C$7*EXP(-((((Model!$C$5*(($B41)+Model!$C$6*(G$35)))-($C$16))/Model!$C$7)^2)/2)/SQRT(2*PI()))-(((Model!$C$5*(($B41)+Model!$C$6*(G$35)))-($C$17))*NORMSDIST(((Model!$C$5*(($B41)+Model!$C$6*(G$35)))-($C$17))/Model!$C$7)+Model!$C$7*EXP(-((((Model!$C$5*(($B41)+Model!$C$6*(G$35)))-($C$17))/Model!$C$7)^2)/2)/SQRT(2*PI())))-((((Model!$C$5*(($C$10)+Model!$C$6*($C$11)))-($C$16))*NORMSDIST(((Model!$C$5*(($C$10)+Model!$C$6*($C$11)))-($C$16))/Model!$C$7)+Model!$C$7*EXP(-((((Model!$C$5*(($C$10)+Model!$C$6*($C$11)))-($C$16))/Model!$C$7)^2)/2)/SQRT(2*PI()))-(((Model!$C$5*(($C$10)+Model!$C$6*($C$11)))-($C$17))*NORMSDIST(((Model!$C$5*(($C$10)+Model!$C$6*($C$11)))-($C$17))/Model!$C$7)+Model!$C$7*EXP(-((((Model!$C$5*(($C$10)+Model!$C$6*($C$11)))-($C$17))/Model!$C$7)^2)/2)/SQRT(2*PI()))))) -> 1041.5503
B42: =$C$10+(-30) -> 54 | C42: =$C$12+$C$14*((Model!$C$5*(($B42)+Model!$C$6*(C$35)))-(Model!$C$5*(($C$10)+Model!$C$6*($C$11)))-$C$15*(((((Model!$C$5*(($B42)+Model!$C$6*(C$35)))-($C$16))*NORMSDIST(((Model!$C$5*(($B42)+Model!$C$6*(C$35)))-($C$16))/Model!$C$7)+Model!$C$7*EXP(-((((Model!$C$5*(($B42)+Model!$C$6*(C$35)))-($C$16))/Model!$C$7)^2)/2)/SQRT(2*PI()))-(((Model!$C$5*(($B42)+Model!$C$6*(C$35)))-($C$17))*NORMSDIST(((Model!$C$5*(($B42)+Model!$C$6*(C$35)))-($C$17))/Model!$C$7)+Model!$C$7*EXP(-((((Model!$C$5*(($B42)+Model!$C$6*(C$35)))-($C$17))/Model!$C$7)^2)/2)/SQRT(2*PI())))-((((Model!$C$5*(($C$10)+Model!$C$6*($C$11)))-($C$16))*NORMSDIST(((Model!$C$5*(($C$10)+Model!$C$6*($C$11)))-($C$16))/Model!$C$7)+Model!$C$7*EXP(-((((Model!$C$5*(($C$10)+Model!$C$6*($C$11)))-($C$16))/Model!$C$7)^2)/2)/SQRT(2*PI()))-(((Model!$C$5*(($C$10)+Model!$C$6*($C$11)))-($C$17))*NORMSDIST(((Model!$C$5*(($C$10)+Model!$C$6*($C$11)))-($C$17))/Model!$C$7)+Model!$C$7*EXP(-((((Model!$C$5*(($C$10)+Model!$C$6*($C$11)))-($C$17))/Model!$C$7)^2)/2)/SQRT(2*PI()))))) -> 976.17293 | D42: =$C$12+$C$14*((Model!$C$5*(($B42)+Model!$C$6*(D$35)))-(Model!$C$5*(($C$10)+Model!$C$6*($C$11)))-$C$15*(((((Model!$C$5*(($B42)+Model!$C$6*(D$35)))-($C$16))*NORMSDIST(((Model!$C$5*(($B42)+Model!$C$6*(D$35)))-($C$16))/Model!$C$7)+Model!$C$7*EXP(-((((Model!$C$5*(($B42)+Model!$C$6*(D$35)))-($C$16))/Model!$C$7)^2)/2)/SQRT(2*PI()))-(((Model!$C$5*(($B42)+Model!$C$6*(D$35)))-($C$17))*NORMSDIST(((Model!$C$5*(($B42)+Model!$C$6*(D$35)))-($C$17))/Model!$C$7)+Model!$C$7*EXP(-((((Model!$C$5*(($B42)+Model!$C$6*(D$35)))-($C$17))/Model!$C$7)^2)/2)/SQRT(2*PI())))-((((Model!$C$5*(($C$10)+Model!$C$6*($C$11)))-($C$16))*NORMSDIST(((Model!$C$5*(($C$10)+Model!$C$6*($C$11)))-($C$16))/Model!$C$7)+Model!$C$7*EXP(-((((Model!$C$5*(($C$10)+Model!$C$6*($C$11)))-($C$16))/Model!$C$7)^2)/2)/SQRT(2*PI()))-(((Model!$C$5*(($C$10)+Model!$C$6*($C$11)))-($C$17))*NORMSDIST(((Model!$C$5*(($C$10)+Model!$C$6*($C$11)))-($C$17))/Model!$C$7)+Model!$C$7*EXP(-((((Model!$C$5*(($C$10)+Model!$C$6*($C$11)))-($C$17))/Model!$C$7)^2)/2)/SQRT(2*PI()))))) -> 989.3069 | E42: =$C$12+$C$14*((Model!$C$5*(($B42)+Model!$C$6*(E$35)))-(Model!$C$5*(($C$10)+Model!$C$6*($C$11)))-$C$15*(((((Model!$C$5*(($B42)+Model!$C$6*(E$35)))-($C$16))*NORMSDIST(((Model!$C$5*(($B42)+Model!$C$6*(E$35)))-($C$16))/Model!$C$7)+Model!$C$7*EXP(-((((Model!$C$5*(($B42)+Model!$C$6*(E$35)))-($C$16))/Model!$C$7)^2)/2)/SQRT(2*PI()))-(((Model!$C$5*(($B42)+Model!$C$6*(E$35)))-($C$17))*NORMSDIST(((Model!$C$5*(($B42)+Model!$C$6*(E$35)))-($C$17))/Model!$C$7)+Model!$C$7*EXP(-((((Model!$C$5*(($B42)+Model!$C$6*(E$35)))-($C$17))/Model!$C$7)^2)/2)/SQRT(2*PI())))-((((Model!$C$5*(($C$10)+Model!$C$6*($C$11)))-($C$16))*NORMSDIST(((Model!$C$5*(($C$10)+Model!$C$6*($C$11)))-($C$16))/Model!$C$7)+Model!$C$7*EXP(-((((Model!$C$5*(($C$10)+Model!$C$6*($C$11)))-($C$16))/Model!$C$7)^2)/2)/SQRT(2*PI()))-(((Model!$C$5*(($C$10)+Model!$C$6*($C$11)))-($C$17))*NORMSDIST(((Model!$C$5*(($C$10)+Model!$C$6*($C$11)))-($C$17))/Model!$C$7)+Model!$C$7*EXP(-((((Model!$C$5*(($C$10)+Model!$C$6*($C$11)))-($C$17))/Model!$C$7)^2)/2)/SQRT(2*PI()))))) -> 1000.1453 | F42: =$C$12+$C$14*((Model!$C$5*(($B42)+Model!$C$6*(F$35)))-(Model!$C$5*(($C$10)+Model!$C$6*($C$11)))-$C$15*(((((Model!$C$5*(($B42)+Model!$C$6*(F$35)))-($C$16))*NORMSDIST(((Model!$C$5*(($B42)+Model!$C$6*(F$35)))-($C$16))/Model!$C$7)+Model!$C$7*EXP(-((((Model!$C$5*(($B42)+Model!$C$6*(F$35)))-($C$16))/Model!$C$7)^2)/2)/SQRT(2*PI()))-(((Model!$C$5*(($B42)+Model!$C$6*(F$35)))-($C$17))*NORMSDIST(((Model!$C$5*(($B42)+Model!$C$6*(F$35)))-($C$17))/Model!$C$7)+Model!$C$7*EXP(-((((Model!$C$5*(($B42)+Model!$C$6*(F$35)))-($C$17))/Model!$C$7)^2)/2)/SQRT(2*PI())))-((((Model!$C$5*(($C$10)+Model!$C$6*($C$11)))-($C$16))*NORMSDIST(((Model!$C$5*(($C$10)+Model!$C$6*($C$11)))-($C$16))/Model!$C$7)+Model!$C$7*EXP(-((((Model!$C$5*(($C$10)+Model!$C$6*($C$11)))-($C$16))/Model!$C$7)^2)/2)/SQRT(2*PI()))-(((Model!$C$5*(($C$10)+Model!$C$6*($C$11)))-($C$17))*NORMSDIST(((Model!$C$5*(($C$10)+Model!$C$6*($C$11)))-($C$17))/Model!$C$7)+Model!$C$7*EXP(-((((Model!$C$5*(($C$10)+Model!$C$6*($C$11)))-($C$17))/Model!$C$7)^2)/2)/SQRT(2*PI()))))) -> 1011.2873 | G42: =$C$12+$C$14*((Model!$C$5*(($B42)+Model!$C$6*(G$35)))-(Model!$C$5*(($C$10)+Model!$C$6*($C$11)))-$C$15*(((((Model!$C$5*(($B42)+Model!$C$6*(G$35)))-($C$16))*NORMSDIST(((Model!$C$5*(($B42)+Model!$C$6*(G$35)))-($C$16))/Model!$C$7)+Model!$C$7*EXP(-((((Model!$C$5*(($B42)+Model!$C$6*(G$35)))-($C$16))/Model!$C$7)^2)/2)/SQRT(2*PI()))-(((Model!$C$5*(($B42)+Model!$C$6*(G$35)))-($C$17))*NORMSDIST(((Model!$C$5*(($B42)+Model!$C$6*(G$35)))-($C$17))/Model!$C$7)+Model!$C$7*EXP(-((((Model!$C$5*(($B42)+Model!$C$6*(G$35)))-($C$17))/Model!$C$7)^2)/2)/SQRT(2*PI())))-((((Model!$C$5*(($C$10)+Model!$C$6*($C$11)))-($C$16))*NORMSDIST(((Model!$C$5*(($C$10)+Model!$C$6*($C$11)))-($C$16))/Model!$C$7)+Model!$C$7*EXP(-((((Model!$C$5*(($C$10)+Model!$C$6*($C$11)))-($C$16))/Model!$C$7)^2)/2)/SQRT(2*PI()))-(((Model!$C$5*(($C$10)+Model!$C$6*($C$11)))-($C$17))*NORMSDIST(((Model!$C$5*(($C$10)+Model!$C$6*($C$11)))-($C$17))/Model!$C$7)+Model!$C$7*EXP(-((((Model!$C$5*(($C$10)+Model!$C$6*($C$11)))-($C$17))/Model!$C$7)^2)/2)/SQRT(2*PI()))))) -> 1025.304
B45: Hedge-ratio sweep (other inputs as above)
B46: Hedge ratio h | C46: P at base ($/t) | D46: Brent +10 | E46: Brent −10 | F46: Crack +10 | G46: Crack −10 | H46: €m per Brent +10
B47: 0 | C47: =(($K$20+$K$15*$K$21+$K$22*((Model!$C$5*(($C$10)+Model!$C$6*($C$11)))+$K$19-($B47)*((((Model!$C$5*(($C$10)+Model!$C$6*($C$11)))-($C$16))*NORMSDIST(((Model!$C$5*(($C$10)+Model!$C$6*($C$11)))-($C$16))/Model!$C$7)+Model!$C$7*EXP(-((((Model!$C$5*(($C$10)+Model!$C$6*($C$11)))-($C$16))/Model!$C$7)^2)/2)/SQRT(2*PI()))-(((Model!$C$5*(($C$10)+Model!$C$6*($C$11)))-($C$17))*NORMSDIST(((Model!$C$5*(($C$10)+Model!$C$6*($C$11)))-($C$17))/Model!$C$7)+Model!$C$7*EXP(-((((Model!$C$5*(($C$10)+Model!$C$6*($C$11)))-($C$17))/Model!$C$7)^2)/2)/SQRT(2*PI())))))/$C$18) -> 1214.9524 | D47: =(($K$20+$K$15*$K$21+$K$22*((Model!$C$5*(($C$10+10)+Model!$C$6*($C$11+0)))+$K$19-($B47)*((((Model!$C$5*(($C$10+10)+Model!$C$6*($C$11+0)))-($C$16))*NORMSDIST(((Model!$C$5*(($C$10+10)+Model!$C$6*($C$11+0)))-($C$16))/Model!$C$7)+Model!$C$7*EXP(-((((Model!$C$5*(($C$10+10)+Model!$C$6*($C$11+0)))-($C$16))/Model!$C$7)^2)/2)/SQRT(2*PI()))-(((Model!$C$5*(($C$10+10)+Model!$C$6*($C$11+0)))-($C$17))*NORMSDIST(((Model!$C$5*(($C$10+10)+Model!$C$6*($C$11+0)))-($C$17))/Model!$C$7)+Model!$C$7*EXP(-((((Model!$C$5*(($C$10+10)+Model!$C$6*($C$11+0)))-($C$17))/Model!$C$7)^2)/2)/SQRT(2*PI())))))/$C$18)-C47 -> 34.520311 | E47: =(($K$20+$K$15*$K$21+$K$22*((Model!$C$5*(($C$10+-10)+Model!$C$6*($C$11+0)))+$K$19-($B47)*((((Model!$C$5*(($C$10+-10)+Model!$C$6*($C$11+0)))-($C$16))*NORMSDIST(((Model!$C$5*(($C$10+-10)+Model!$C$6*($C$11+0)))-($C$16))/Model!$C$7)+Model!$C$7*EXP(-((((Model!$C$5*(($C$10+-10)+Model!$C$6*($C$11+0)))-($C$16))/Model!$C$7)^2)/2)/SQRT(2*PI()))-(((Model!$C$5*(($C$10+-10)+Model!$C$6*($C$11+0)))-($C$17))*NORMSDIST(((Model!$C$5*(($C$10+-10)+Model!$C$6*($C$11+0)))-($C$17))/Model!$C$7)+Model!$C$7*EXP(-((((Model!$C$5*(($C$10+-10)+Model!$C$6*($C$11+0)))-($C$17))/Model!$C$7)^2)/2)/SQRT(2*PI())))))/$C$18)-C47 -> -34.520311 | F47: =(($K$20+$K$15*$K$21+$K$22*((Model!$C$5*(($C$10+0)+Model!$C$6*($C$11+10)))+$K$19-($B47)*((((Model!$C$5*(($C$10+0)+Model!$C$6*($C$11+10)))-($C$16))*NORMSDIST(((Model!$C$5*(($C$10+0)+Model!$C$6*($C$11+10)))-($C$16))/Model!$C$7)+Model!$C$7*EXP(-((((Model!$C$5*(($C$10+0)+Model!$C$6*($C$11+10)))-($C$16))/Model!$C$7)^2)/2)/SQRT(2*PI()))-(((Model!$C$5*(($C$10+0)+Model!$C$6*($C$11+10)))-($C$17))*NORMSDIST(((Model!$C$5*(($C$10+0)+Model!$C$6*($C$11+10)))-($C$17))/Model!$C$7)+Model!$C$7*EXP(-((((Model!$C$5*(($C$10+0)+Model!$C$6*($C$11+10)))-($C$17))/Model!$C$7)^2)/2)/SQRT(2*PI())))))/$C$18)-C47 -> 39.698358 | G47: =(($K$20+$K$15*$K$21+$K$22*((Model!$C$5*(($C$10+0)+Model!$C$6*($C$11+-10)))+$K$19-($B47)*((((Model!$C$5*(($C$10+0)+Model!$C$6*($C$11+-10)))-($C$16))*NORMSDIST(((Model!$C$5*(($C$10+0)+Model!$C$6*($C$11+-10)))-($C$16))/Model!$C$7)+Model!$C$7*EXP(-((((Model!$C$5*(($C$10+0)+Model!$C$6*($C$11+-10)))-($C$16))/Model!$C$7)^2)/2)/SQRT(2*PI()))-(((Model!$C$5*(($C$10+0)+Model!$C$6*($C$11+-10)))-($C$17))*NORMSDIST(((Model!$C$5*(($C$10+0)+Model!$C$6*($C$11+-10)))-($C$17))/Model!$C$7)+Model!$C$7*EXP(-((((Model!$C$5*(($C$10+0)+Model!$C$6*($C$11+-10)))-($C$17))/Model!$C$7)^2)/2)/SQRT(2*PI())))))/$C$18)-C47 -> -39.698358 | H47: =$C$18*D47/$C$19 -> 282.52071
B48: 0.25 | C48: =(($K$20+$K$15*$K$21+$K$22*((Model!$C$5*(($C$10)+Model!$C$6*($C$11)))+$K$19-($B48)*((((Model!$C$5*(($C$10)+Model!$C$6*($C$11)))-($C$16))*NORMSDIST(((Model!$C$5*(($C$10)+Model!$C$6*($C$11)))-($C$16))/Model!$C$7)+Model!$C$7*EXP(-((((Model!$C$5*(($C$10)+Model!$C$6*($C$11)))-($C$16))/Model!$C$7)^2)/2)/SQRT(2*PI()))-(((Model!$C$5*(($C$10)+Model!$C$6*($C$11)))-($C$17))*NORMSDIST(((Model!$C$5*(($C$10)+Model!$C$6*($C$11)))-($C$17))/Model!$C$7)+Model!$C$7*EXP(-((((Model!$C$5*(($C$10)+Model!$C$6*($C$11)))-($C$17))/Model!$C$7)^2)/2)/SQRT(2*PI())))))/$C$18) -> 1159.7846 | D48: =(($K$20+$K$15*$K$21+$K$22*((Model!$C$5*(($C$10+10)+Model!$C$6*($C$11+0)))+$K$19-($B48)*((((Model!$C$5*(($C$10+10)+Model!$C$6*($C$11+0)))-($C$16))*NORMSDIST(((Model!$C$5*(($C$10+10)+Model!$C$6*($C$11+0)))-($C$16))/Model!$C$7)+Model!$C$7*EXP(-((((Model!$C$5*(($C$10+10)+Model!$C$6*($C$11+0)))-($C$16))/Model!$C$7)^2)/2)/SQRT(2*PI()))-(((Model!$C$5*(($C$10+10)+Model!$C$6*($C$11+0)))-($C$17))*NORMSDIST(((Model!$C$5*(($C$10+10)+Model!$C$6*($C$11+0)))-($C$17))/Model!$C$7)+Model!$C$7*EXP(-((((Model!$C$5*(($C$10+10)+Model!$C$6*($C$11+0)))-($C$17))/Model!$C$7)^2)/2)/SQRT(2*PI())))))/$C$18)-C48 -> 29.876758 | E48: =(($K$20+$K$15*$K$21+$K$22*((Model!$C$5*(($C$10+-10)+Model!$C$6*($C$11+0)))+$K$19-($B48)*((((Model!$C$5*(($C$10+-10)+Model!$C$6*($C$11+0)))-($C$16))*NORMSDIST(((Model!$C$5*(($C$10+-10)+Model!$C$6*($C$11+0)))-($C$16))/Model!$C$7)+Model!$C$7*EXP(-((((Model!$C$5*(($C$10+-10)+Model!$C$6*($C$11+0)))-($C$16))/Model!$C$7)^2)/2)/SQRT(2*PI()))-(((Model!$C$5*(($C$10+-10)+Model!$C$6*($C$11+0)))-($C$17))*NORMSDIST(((Model!$C$5*(($C$10+-10)+Model!$C$6*($C$11+0)))-($C$17))/Model!$C$7)+Model!$C$7*EXP(-((((Model!$C$5*(($C$10+-10)+Model!$C$6*($C$11+0)))-($C$17))/Model!$C$7)^2)/2)/SQRT(2*PI())))))/$C$18)-C48 -> -28.487143 | F48: =(($K$20+$K$15*$K$21+$K$22*((Model!$C$5*(($C$10+0)+Model!$C$6*($C$11+10)))+$K$19-($B48)*((((Model!$C$5*(($C$10+0)+Model!$C$6*($C$11+10)))-($C$16))*NORMSDIST(((Model!$C$5*(($C$10+0)+Model!$C$6*($C$11+10)))-($C$16))/Model!$C$7)+Model!$C$7*EXP(-((((Model!$C$5*(($C$10+0)+Model!$C$6*($C$11+10)))-($C$16))/Model!$C$7)^2)/2)/SQRT(2*PI()))-(((Model!$C$5*(($C$10+0)+Model!$C$6*($C$11+10)))-($C$17))*NORMSDIST(((Model!$C$5*(($C$10+0)+Model!$C$6*($C$11+10)))-($C$17))/Model!$C$7)+Model!$C$7*EXP(-((((Model!$C$5*(($C$10+0)+Model!$C$6*($C$11+10)))-($C$17))/Model!$C$7)^2)/2)/SQRT(2*PI())))))/$C$18)-C48 -> 34.486263 | G48: =(($K$20+$K$15*$K$21+$K$22*((Model!$C$5*(($C$10+0)+Model!$C$6*($C$11+-10)))+$K$19-($B48)*((((Model!$C$5*(($C$10+0)+Model!$C$6*($C$11+-10)))-($C$16))*NORMSDIST(((Model!$C$5*(($C$10+0)+Model!$C$6*($C$11+-10)))-($C$16))/Model!$C$7)+Model!$C$7*EXP(-((((Model!$C$5*(($C$10+0)+Model!$C$6*($C$11+-10)))-($C$16))/Model!$C$7)^2)/2)/SQRT(2*PI()))-(((Model!$C$5*(($C$10+0)+Model!$C$6*($C$11+-10)))-($C$17))*NORMSDIST(((Model!$C$5*(($C$10+0)+Model!$C$6*($C$11+-10)))-($C$17))/Model!$C$7)+Model!$C$7*EXP(-((((Model!$C$5*(($C$10+0)+Model!$C$6*($C$11+-10)))-($C$17))/Model!$C$7)^2)/2)/SQRT(2*PI())))))/$C$18)-C48 -> -32.657677 | H48: =$C$18*D48/$C$19 -> 244.51699
B49: 0.5 | C49: =(($K$20+$K$15*$K$21+$K$22*((Model!$C$5*(($C$10)+Model!$C$6*($C$11)))+$K$19-($B49)*((((Model!$C$5*(($C$10)+Model!$C$6*($C$11)))-($C$16))*NORMSDIST(((Model!$C$5*(($C$10)+Model!$C$6*($C$11)))-($C$16))/Model!$C$7)+Model!$C$7*EXP(-((((Model!$C$5*(($C$10)+Model!$C$6*($C$11)))-($C$16))/Model!$C$7)^2)/2)/SQRT(2*PI()))-(((Model!$C$5*(($C$10)+Model!$C$6*($C$11)))-($C$17))*NORMSDIST(((Model!$C$5*(($C$10)+Model!$C$6*($C$11)))-($C$17))/Model!$C$7)+Model!$C$7*EXP(-((((Model!$C$5*(($C$10)+Model!$C$6*($C$11)))-($C$17))/Model!$C$7)^2)/2)/SQRT(2*PI())))))/$C$18) -> 1104.6168 | D49: =(($K$20+$K$15*$K$21+$K$22*((Model!$C$5*(($C$10+10)+Model!$C$6*($C$11+0)))+$K$19-($B49)*((((Model!$C$5*(($C$10+10)+Model!$C$6*($C$11+0)))-($C$16))*NORMSDIST(((Model!$C$5*(($C$10+10)+Model!$C$6*($C$11+0)))-($C$16))/Model!$C$7)+Model!$C$7*EXP(-((((Model!$C$5*(($C$10+10)+Model!$C$6*($C$11+0)))-($C$16))/Model!$C$7)^2)/2)/SQRT(2*PI()))-(((Model!$C$5*(($C$10+10)+Model!$C$6*($C$11+0)))-($C$17))*NORMSDIST(((Model!$C$5*(($C$10+10)+Model!$C$6*($C$11+0)))-($C$17))/Model!$C$7)+Model!$C$7*EXP(-((((Model!$C$5*(($C$10+10)+Model!$C$6*($C$11+0)))-($C$17))/Model!$C$7)^2)/2)/SQRT(2*PI())))))/$C$18)-C49 -> 25.233204 | E49: =(($K$20+$K$15*$K$21+$K$22*((Model!$C$5*(($C$10+-10)+Model!$C$6*($C$11+0)))+$K$19-($B49)*((((Model!$C$5*(($C$10+-10)+Model!$C$6*($C$11+0)))-($C$16))*NORMSDIST(((Model!$C$5*(($C$10+-10)+Model!$C$6*($C$11+0)))-($C$16))/Model!$C$7)+Model!$C$7*EXP(-((((Model!$C$5*(($C$10+-10)+Model!$C$6*($C$11+0)))-($C$16))/Model!$C$7)^2)/2)/SQRT(2*PI()))-(((Model!$C$5*(($C$10+-10)+Model!$C$6*($C$11+0)))-($C$17))*NORMSDIST(((Model!$C$5*(($C$10+-10)+Model!$C$6*($C$11+0)))-($C$17))/Model!$C$7)+Model!$C$7*EXP(-((((Model!$C$5*(($C$10+-10)+Model!$C$6*($C$11+0)))-($C$17))/Model!$C$7)^2)/2)/SQRT(2*PI())))))/$C$18)-C49 -> -22.453975 | F49: =(($K$20+$K$15*$K$21+$K$22*((Model!$C$5*(($C$10+0)+Model!$C$6*($C$11+10)))+$K$19-($B49)*((((Model!$C$5*(($C$10+0)+Model!$C$6*($C$11+10)))-($C$16))*NORMSDIST(((Model!$C$5*(($C$10+0)+Model!$C$6*($C$11+10)))-($C$16))/Model!$C$7)+Model!$C$7*EXP(-((((Model!$C$5*(($C$10+0)+Model!$C$6*($C$11+10)))-($C$16))/Model!$C$7)^2)/2)/SQRT(2*PI()))-(((Model!$C$5*(($C$10+0)+Model!$C$6*($C$11+10)))-($C$17))*NORMSDIST(((Model!$C$5*(($C$10+0)+Model!$C$6*($C$11+10)))-($C$17))/Model!$C$7)+Model!$C$7*EXP(-((((Model!$C$5*(($C$10+0)+Model!$C$6*($C$11+10)))-($C$17))/Model!$C$7)^2)/2)/SQRT(2*PI())))))/$C$18)-C49 -> 29.274168 | G49: =(($K$20+$K$15*$K$21+$K$22*((Model!$C$5*(($C$10+0)+Model!$C$6*($C$11+-10)))+$K$19-($B49)*((((Model!$C$5*(($C$10+0)+Model!$C$6*($C$11+-10)))-($C$16))*NORMSDIST(((Model!$C$5*(($C$10+0)+Model!$C$6*($C$11+-10)))-($C$16))/Model!$C$7)+Model!$C$7*EXP(-((((Model!$C$5*(($C$10+0)+Model!$C$6*($C$11+-10)))-($C$16))/Model!$C$7)^2)/2)/SQRT(2*PI()))-(((Model!$C$5*(($C$10+0)+Model!$C$6*($C$11+-10)))-($C$17))*NORMSDIST(((Model!$C$5*(($C$10+0)+Model!$C$6*($C$11+-10)))-($C$17))/Model!$C$7)+Model!$C$7*EXP(-((((Model!$C$5*(($C$10+0)+Model!$C$6*($C$11+-10)))-($C$17))/Model!$C$7)^2)/2)/SQRT(2*PI())))))/$C$18)-C49 -> -25.616995 | H49: =$C$18*D49/$C$19 -> 206.51328
B50: 0.65 | C50: =(($K$20+$K$15*$K$21+$K$22*((Model!$C$5*(($C$10)+Model!$C$6*($C$11)))+$K$19-($B50)*((((Model!$C$5*(($C$10)+Model!$C$6*($C$11)))-($C$16))*NORMSDIST(((Model!$C$5*(($C$10)+Model!$C$6*($C$11)))-($C$16))/Model!$C$7)+Model!$C$7*EXP(-((((Model!$C$5*(($C$10)+Model!$C$6*($C$11)))-($C$16))/Model!$C$7)^2)/2)/SQRT(2*PI()))-(((Model!$C$5*(($C$10)+Model!$C$6*($C$11)))-($C$17))*NORMSDIST(((Model!$C$5*(($C$10)+Model!$C$6*($C$11)))-($C$17))/Model!$C$7)+Model!$C$7*EXP(-((((Model!$C$5*(($C$10)+Model!$C$6*($C$11)))-($C$17))/Model!$C$7)^2)/2)/SQRT(2*PI())))))/$C$18) -> 1071.5161 | D50: =(($K$20+$K$15*$K$21+$K$22*((Model!$C$5*(($C$10+10)+Model!$C$6*($C$11+0)))+$K$19-($B50)*((((Model!$C$5*(($C$10+10)+Model!$C$6*($C$11+0)))-($C$16))*NORMSDIST(((Model!$C$5*(($C$10+10)+Model!$C$6*($C$11+0)))-($C$16))/Model!$C$7)+Model!$C$7*EXP(-((((Model!$C$5*(($C$10+10)+Model!$C$6*($C$11+0)))-($C$16))/Model!$C$7)^2)/2)/SQRT(2*PI()))-(((Model!$C$5*(($C$10+10)+Model!$C$6*($C$11+0)))-($C$17))*NORMSDIST(((Model!$C$5*(($C$10+10)+Model!$C$6*($C$11+0)))-($C$17))/Model!$C$7)+Model!$C$7*EXP(-((((Model!$C$5*(($C$10+10)+Model!$C$6*($C$11+0)))-($C$17))/Model!$C$7)^2)/2)/SQRT(2*PI())))))/$C$18)-C50 -> 22.447072 | E50: =(($K$20+$K$15*$K$21+$K$22*((Model!$C$5*(($C$10+-10)+Model!$C$6*($C$11+0)))+$K$19-($B50)*((((Model!$C$5*(($C$10+-10)+Model!$C$6*($C$11+0)))-($C$16))*NORMSDIST(((Model!$C$5*(($C$10+-10)+Model!$C$6*($C$11+0)))-($C$16))/Model!$C$7)+Model!$C$7*EXP(-((((Model!$C$5*(($C$10+-10)+Model!$C$6*($C$11+0)))-($C$16))/Model!$C$7)^2)/2)/SQRT(2*PI()))-(((Model!$C$5*(($C$10+-10)+Model!$C$6*($C$11+0)))-($C$17))*NORMSDIST(((Model!$C$5*(($C$10+-10)+Model!$C$6*($C$11+0)))-($C$17))/Model!$C$7)+Model!$C$7*EXP(-((((Model!$C$5*(($C$10+-10)+Model!$C$6*($C$11+0)))-($C$17))/Model!$C$7)^2)/2)/SQRT(2*PI())))))/$C$18)-C50 -> -18.834074 | F50: =(($K$20+$K$15*$K$21+$K$22*((Model!$C$5*(($C$10+0)+Model!$C$6*($C$11+10)))+$K$19-($B50)*((((Model!$C$5*(($C$10+0)+Model!$C$6*($C$11+10)))-($C$16))*NORMSDIST(((Model!$C$5*(($C$10+0)+Model!$C$6*($C$11+10)))-($C$16))/Model!$C$7)+Model!$C$7*EXP(-((((Model!$C$5*(($C$10+0)+Model!$C$6*($C$11+10)))-($C$16))/Model!$C$7)^2)/2)/SQRT(2*PI()))-(((Model!$C$5*(($C$10+0)+Model!$C$6*($C$11+10)))-($C$17))*NORMSDIST(((Model!$C$5*(($C$10+0)+Model!$C$6*($C$11+10)))-($C$17))/Model!$C$7)+Model!$C$7*EXP(-((((Model!$C$5*(($C$10+0)+Model!$C$6*($C$11+10)))-($C$17))/Model!$C$7)^2)/2)/SQRT(2*PI())))))/$C$18)-C50 -> 26.146911 | G50: =(($K$20+$K$15*$K$21+$K$22*((Model!$C$5*(($C$10+0)+Model!$C$6*($C$11+-10)))+$K$19-($B50)*((((Model!$C$5*(($C$10+0)+Model!$C$6*($C$11+-10)))-($C$16))*NORMSDIST(((Model!$C$5*(($C$10+0)+Model!$C$6*($C$11+-10)))-($C$16))/Model!$C$7)+Model!$C$7*EXP(-((((Model!$C$5*(($C$10+0)+Model!$C$6*($C$11+-10)))-($C$16))/Model!$C$7)^2)/2)/SQRT(2*PI()))-(((Model!$C$5*(($C$10+0)+Model!$C$6*($C$11+-10)))-($C$17))*NORMSDIST(((Model!$C$5*(($C$10+0)+Model!$C$6*($C$11+-10)))-($C$17))/Model!$C$7)+Model!$C$7*EXP(-((((Model!$C$5*(($C$10+0)+Model!$C$6*($C$11+-10)))-($C$17))/Model!$C$7)^2)/2)/SQRT(2*PI())))))/$C$18)-C50 -> -21.392587 | H50: =$C$18*D50/$C$19 -> 183.71105
B51: 0.81 | C51: =(($K$20+$K$15*$K$21+$K$22*((Model!$C$5*(($C$10)+Model!$C$6*($C$11)))+$K$19-($B51)*((((Model!$C$5*(($C$10)+Model!$C$6*($C$11)))-($C$16))*NORMSDIST(((Model!$C$5*(($C$10)+Model!$C$6*($C$11)))-($C$16))/Model!$C$7)+Model!$C$7*EXP(-((((Model!$C$5*(($C$10)+Model!$C$6*($C$11)))-($C$16))/Model!$C$7)^2)/2)/SQRT(2*PI()))-(((Model!$C$5*(($C$10)+Model!$C$6*($C$11)))-($C$17))*NORMSDIST(((Model!$C$5*(($C$10)+Model!$C$6*($C$11)))-($C$17))/Model!$C$7)+Model!$C$7*EXP(-((((Model!$C$5*(($C$10)+Model!$C$6*($C$11)))-($C$17))/Model!$C$7)^2)/2)/SQRT(2*PI())))))/$C$18) -> 1036.2086 | D51: =(($K$20+$K$15*$K$21+$K$22*((Model!$C$5*(($C$10+10)+Model!$C$6*($C$11+0)))+$K$19-($B51)*((((Model!$C$5*(($C$10+10)+Model!$C$6*($C$11+0)))-($C$16))*NORMSDIST(((Model!$C$5*(($C$10+10)+Model!$C$6*($C$11+0)))-($C$16))/Model!$C$7)+Model!$C$7*EXP(-((((Model!$C$5*(($C$10+10)+Model!$C$6*($C$11+0)))-($C$16))/Model!$C$7)^2)/2)/SQRT(2*PI()))-(((Model!$C$5*(($C$10+10)+Model!$C$6*($C$11+0)))-($C$17))*NORMSDIST(((Model!$C$5*(($C$10+10)+Model!$C$6*($C$11+0)))-($C$17))/Model!$C$7)+Model!$C$7*EXP(-((((Model!$C$5*(($C$10+10)+Model!$C$6*($C$11+0)))-($C$17))/Model!$C$7)^2)/2)/SQRT(2*PI())))))/$C$18)-C51 -> 19.475197 | E51: =(($K$20+$K$15*$K$21+$K$22*((Model!$C$5*(($C$10+-10)+Model!$C$6*($C$11+0)))+$K$19-($B51)*((((Model!$C$5*(($C$10+-10)+Model!$C$6*($C$11+0)))-($C$16))*NORMSDIST(((Model!$C$5*(($C$10+-10)+Model!$C$6*($C$11+0)))-($C$16))/Model!$C$7)+Model!$C$7*EXP(-((((Model!$C$5*(($C$10+-10)+Model!$C$6*($C$11+0)))-($C$16))/Model!$C$7)^2)/2)/SQRT(2*PI()))-(((Model!$C$5*(($C$10+-10)+Model!$C$6*($C$11+0)))-($C$17))*NORMSDIST(((Model!$C$5*(($C$10+-10)+Model!$C$6*($C$11+0)))-($C$17))/Model!$C$7)+Model!$C$7*EXP(-((((Model!$C$5*(($C$10+-10)+Model!$C$6*($C$11+0)))-($C$17))/Model!$C$7)^2)/2)/SQRT(2*PI())))))/$C$18)-C51 -> -14.972846 | F51: =(($K$20+$K$15*$K$21+$K$22*((Model!$C$5*(($C$10+0)+Model!$C$6*($C$11+10)))+$K$19-($B51)*((((Model!$C$5*(($C$10+0)+Model!$C$6*($C$11+10)))-($C$16))*NORMSDIST(((Model!$C$5*(($C$10+0)+Model!$C$6*($C$11+10)))-($C$16))/Model!$C$7)+Model!$C$7*EXP(-((((Model!$C$5*(($C$10+0)+Model!$C$6*($C$11+10)))-($C$16))/Model!$C$7)^2)/2)/SQRT(2*PI()))-(((Model!$C$5*(($C$10+0)+Model!$C$6*($C$11+10)))-($C$17))*NORMSDIST(((Model!$C$5*(($C$10+0)+Model!$C$6*($C$11+10)))-($C$17))/Model!$C$7)+Model!$C$7*EXP(-((((Model!$C$5*(($C$10+0)+Model!$C$6*($C$11+10)))-($C$17))/Model!$C$7)^2)/2)/SQRT(2*PI())))))/$C$18)-C51 -> 22.811171 | G51: =(($K$20+$K$15*$K$21+$K$22*((Model!$C$5*(($C$10+0)+Model!$C$6*($C$11+-10)))+$K$19-($B51)*((((Model!$C$5*(($C$10+0)+Model!$C$6*($C$11+-10)))-($C$16))*NORMSDIST(((Model!$C$5*(($C$10+0)+Model!$C$6*($C$11+-10)))-($C$16))/Model!$C$7)+Model!$C$7*EXP(-((((Model!$C$5*(($C$10+0)+Model!$C$6*($C$11+-10)))-($C$16))/Model!$C$7)^2)/2)/SQRT(2*PI()))-(((Model!$C$5*(($C$10+0)+Model!$C$6*($C$11+-10)))-($C$17))*NORMSDIST(((Model!$C$5*(($C$10+0)+Model!$C$6*($C$11+-10)))-($C$17))/Model!$C$7)+Model!$C$7*EXP(-((((Model!$C$5*(($C$10+0)+Model!$C$6*($C$11+-10)))-($C$17))/Model!$C$7)^2)/2)/SQRT(2*PI())))))/$C$18)-C51 -> -16.88655 | H51: =$C$18*D51/$C$19 -> 159.38867
B52: 0.9 | C52: =(($K$20+$K$15*$K$21+$K$22*((Model!$C$5*(($C$10)+Model!$C$6*($C$11)))+$K$19-($B52)*((((Model!$C$5*(($C$10)+Model!$C$6*($C$11)))-($C$16))*NORMSDIST(((Model!$C$5*(($C$10)+Model!$C$6*($C$11)))-($C$16))/Model!$C$7)+Model!$C$7*EXP(-((((Model!$C$5*(($C$10)+Model!$C$6*($C$11)))-($C$16))/Model!$C$7)^2)/2)/SQRT(2*PI()))-(((Model!$C$5*(($C$10)+Model!$C$6*($C$11)))-($C$17))*NORMSDIST(((Model!$C$5*(($C$10)+Model!$C$6*($C$11)))-($C$17))/Model!$C$7)+Model!$C$7*EXP(-((((Model!$C$5*(($C$10)+Model!$C$6*($C$11)))-($C$17))/Model!$C$7)^2)/2)/SQRT(2*PI())))))/$C$18) -> 1016.3482 | D52: =(($K$20+$K$15*$K$21+$K$22*((Model!$C$5*(($C$10+10)+Model!$C$6*($C$11+0)))+$K$19-($B52)*((((Model!$C$5*(($C$10+10)+Model!$C$6*($C$11+0)))-($C$16))*NORMSDIST(((Model!$C$5*(($C$10+10)+Model!$C$6*($C$11+0)))-($C$16))/Model!$C$7)+Model!$C$7*EXP(-((((Model!$C$5*(($C$10+10)+Model!$C$6*($C$11+0)))-($C$16))/Model!$C$7)^2)/2)/SQRT(2*PI()))-(((Model!$C$5*(($C$10+10)+Model!$C$6*($C$11+0)))-($C$17))*NORMSDIST(((Model!$C$5*(($C$10+10)+Model!$C$6*($C$11+0)))-($C$17))/Model!$C$7)+Model!$C$7*EXP(-((((Model!$C$5*(($C$10+10)+Model!$C$6*($C$11+0)))-($C$17))/Model!$C$7)^2)/2)/SQRT(2*PI())))))/$C$18)-C52 -> 17.803518 | E52: =(($K$20+$K$15*$K$21+$K$22*((Model!$C$5*(($C$10+-10)+Model!$C$6*($C$11+0)))+$K$19-($B52)*((((Model!$C$5*(($C$10+-10)+Model!$C$6*($C$11+0)))-($C$16))*NORMSDIST(((Model!$C$5*(($C$10+-10)+Model!$C$6*($C$11+0)))-($C$16))/Model!$C$7)+Model!$C$7*EXP(-((((Model!$C$5*(($C$10+-10)+Model!$C$6*($C$11+0)))-($C$16))/Model!$C$7)^2)/2)/SQRT(2*PI()))-(((Model!$C$5*(($C$10+-10)+Model!$C$6*($C$11+0)))-($C$17))*NORMSDIST(((Model!$C$5*(($C$10+-10)+Model!$C$6*($C$11+0)))-($C$17))/Model!$C$7)+Model!$C$7*EXP(-((((Model!$C$5*(($C$10+-10)+Model!$C$6*($C$11+0)))-($C$17))/Model!$C$7)^2)/2)/SQRT(2*PI())))))/$C$18)-C52 -> -12.800905 | F52: =(($K$20+$K$15*$K$21+$K$22*((Model!$C$5*(($C$10+0)+Model!$C$6*($C$11+10)))+$K$19-($B52)*((((Model!$C$5*(($C$10+0)+Model!$C$6*($C$11+10)))-($C$16))*NORMSDIST(((Model!$C$5*(($C$10+0)+Model!$C$6*($C$11+10)))-($C$16))/Model!$C$7)+Model!$C$7*EXP(-((((Model!$C$5*(($C$10+0)+Model!$C$6*($C$11+10)))-($C$16))/Model!$C$7)^2)/2)/SQRT(2*PI()))-(((Model!$C$5*(($C$10+0)+Model!$C$6*($C$11+10)))-($C$17))*NORMSDIST(((Model!$C$5*(($C$10+0)+Model!$C$6*($C$11+10)))-($C$17))/Model!$C$7)+Model!$C$7*EXP(-((((Model!$C$5*(($C$10+0)+Model!$C$6*($C$11+10)))-($C$17))/Model!$C$7)^2)/2)/SQRT(2*PI())))))/$C$18)-C52 -> 20.934816 | G52: =(($K$20+$K$15*$K$21+$K$22*((Model!$C$5*(($C$10+0)+Model!$C$6*($C$11+-10)))+$K$19-($B52)*((((Model!$C$5*(($C$10+0)+Model!$C$6*($C$11+-10)))-($C$16))*NORMSDIST(((Model!$C$5*(($C$10+0)+Model!$C$6*($C$11+-10)))-($C$16))/Model!$C$7)+Model!$C$7*EXP(-((((Model!$C$5*(($C$10+0)+Model!$C$6*($C$11+-10)))-($C$16))/Model!$C$7)^2)/2)/SQRT(2*PI()))-(((Model!$C$5*(($C$10+0)+Model!$C$6*($C$11+-10)))-($C$17))*NORMSDIST(((Model!$C$5*(($C$10+0)+Model!$C$6*($C$11+-10)))-($C$17))/Model!$C$7)+Model!$C$7*EXP(-((((Model!$C$5*(($C$10+0)+Model!$C$6*($C$11+-10)))-($C$17))/Model!$C$7)^2)/2)/SQRT(2*PI())))))/$C$18)-C52 -> -14.351905 | H52: =$C$18*D52/$C$19 -> 145.70733
B53: 1 | C53: =(($K$20+$K$15*$K$21+$K$22*((Model!$C$5*(($C$10)+Model!$C$6*($C$11)))+$K$19-($B53)*((((Model!$C$5*(($C$10)+Model!$C$6*($C$11)))-($C$16))*NORMSDIST(((Model!$C$5*(($C$10)+Model!$C$6*($C$11)))-($C$16))/Model!$C$7)+Model!$C$7*EXP(-((((Model!$C$5*(($C$10)+Model!$C$6*($C$11)))-($C$16))/Model!$C$7)^2)/2)/SQRT(2*PI()))-(((Model!$C$5*(($C$10)+Model!$C$6*($C$11)))-($C$17))*NORMSDIST(((Model!$C$5*(($C$10)+Model!$C$6*($C$11)))-($C$17))/Model!$C$7)+Model!$C$7*EXP(-((((Model!$C$5*(($C$10)+Model!$C$6*($C$11)))-($C$17))/Model!$C$7)^2)/2)/SQRT(2*PI())))))/$C$18) -> 994.28109 | D53: =(($K$20+$K$15*$K$21+$K$22*((Model!$C$5*(($C$10+10)+Model!$C$6*($C$11+0)))+$K$19-($B53)*((((Model!$C$5*(($C$10+10)+Model!$C$6*($C$11+0)))-($C$16))*NORMSDIST(((Model!$C$5*(($C$10+10)+Model!$C$6*($C$11+0)))-($C$16))/Model!$C$7)+Model!$C$7*EXP(-((((Model!$C$5*(($C$10+10)+Model!$C$6*($C$11+0)))-($C$16))/Model!$C$7)^2)/2)/SQRT(2*PI()))-(((Model!$C$5*(($C$10+10)+Model!$C$6*($C$11+0)))-($C$17))*NORMSDIST(((Model!$C$5*(($C$10+10)+Model!$C$6*($C$11+0)))-($C$17))/Model!$C$7)+Model!$C$7*EXP(-((((Model!$C$5*(($C$10+10)+Model!$C$6*($C$11+0)))-($C$17))/Model!$C$7)^2)/2)/SQRT(2*PI())))))/$C$18)-C53 -> 15.946096 | E53: =(($K$20+$K$15*$K$21+$K$22*((Model!$C$5*(($C$10+-10)+Model!$C$6*($C$11+0)))+$K$19-($B53)*((((Model!$C$5*(($C$10+-10)+Model!$C$6*($C$11+0)))-($C$16))*NORMSDIST(((Model!$C$5*(($C$10+-10)+Model!$C$6*($C$11+0)))-($C$16))/Model!$C$7)+Model!$C$7*EXP(-((((Model!$C$5*(($C$10+-10)+Model!$C$6*($C$11+0)))-($C$16))/Model!$C$7)^2)/2)/SQRT(2*PI()))-(((Model!$C$5*(($C$10+-10)+Model!$C$6*($C$11+0)))-($C$17))*NORMSDIST(((Model!$C$5*(($C$10+-10)+Model!$C$6*($C$11+0)))-($C$17))/Model!$C$7)+Model!$C$7*EXP(-((((Model!$C$5*(($C$10+-10)+Model!$C$6*($C$11+0)))-($C$17))/Model!$C$7)^2)/2)/SQRT(2*PI())))))/$C$18)-C53 -> -10.387638 | F53: =(($K$20+$K$15*$K$21+$K$22*((Model!$C$5*(($C$10+0)+Model!$C$6*($C$11+10)))+$K$19-($B53)*((((Model!$C$5*(($C$10+0)+Model!$C$6*($C$11+10)))-($C$16))*NORMSDIST(((Model!$C$5*(($C$10+0)+Model!$C$6*($C$11+10)))-($C$16))/Model!$C$7)+Model!$C$7*EXP(-((((Model!$C$5*(($C$10+0)+Model!$C$6*($C$11+10)))-($C$16))/Model!$C$7)^2)/2)/SQRT(2*PI()))-(((Model!$C$5*(($C$10+0)+Model!$C$6*($C$11+10)))-($C$17))*NORMSDIST(((Model!$C$5*(($C$10+0)+Model!$C$6*($C$11+10)))-($C$17))/Model!$C$7)+Model!$C$7*EXP(-((((Model!$C$5*(($C$10+0)+Model!$C$6*($C$11+10)))-($C$17))/Model!$C$7)^2)/2)/SQRT(2*PI())))))/$C$18)-C53 -> 18.849978 | G53: =(($K$20+$K$15*$K$21+$K$22*((Model!$C$5*(($C$10+0)+Model!$C$6*($C$11+-10)))+$K$19-($B53)*((((Model!$C$5*(($C$10+0)+Model!$C$6*($C$11+-10)))-($C$16))*NORMSDIST(((Model!$C$5*(($C$10+0)+Model!$C$6*($C$11+-10)))-($C$16))/Model!$C$7)+Model!$C$7*EXP(-((((Model!$C$5*(($C$10+0)+Model!$C$6*($C$11+-10)))-($C$16))/Model!$C$7)^2)/2)/SQRT(2*PI()))-(((Model!$C$5*(($C$10+0)+Model!$C$6*($C$11+-10)))-($C$17))*NORMSDIST(((Model!$C$5*(($C$10+0)+Model!$C$6*($C$11+-10)))-($C$17))/Model!$C$7)+Model!$C$7*EXP(-((((Model!$C$5*(($C$10+0)+Model!$C$6*($C$11+-10)))-($C$17))/Model!$C$7)^2)/2)/SQRT(2*PI())))))/$C$18)-C53 -> -11.535633 | H53: =$C$18*D53/$C$19 -> 130.50585
B55: Note: h applies to Aug–Dec; the base price now moves with h because hedges are in the money at base forwards. Changing h keeps the calibrated option structure. For a swap-only book set K1 very low and K2 very high (e.g. 0 and 99,999).

Sheet Recon 1H26
B1: Reconciliation with H1 2026 reported fuel figures
B2: Test: start from Lufthansa's own quarterly guidance, move unrealised months from guidance forwards to realised prices with the model, compare with reported fuel expense.
B4: Monthly market prices | C4: Jan | D4: Feb | E4: Mar | F4: Apr | G4: May | H4: Jun
B5: Brent spot, FRED MCOILBRENTEU ($/bbl) | C5: 66.6 | D5: 70.89 | E5: 103.13 | F5: 117.29 | G5: 107.14 | H5: 85.4
B6: Jet fuel USGC, FRED MJFUELUSGULF ($/gal) | C6: 2.031 | D6: 2.262 | E6: 3.697 | F6: 3.928 | G6: 3.943 | H6: 3.042
B7: LH H1 average Brent ($/bbl) | C7: 87.44
B8: LH H1 average kerosene ($/t) | C8: 1133.9
B9: Brent rebased to LH level ($/bbl) | C9: =C5*$C$7/AVERAGE($C$5:$H$5) -> 63.477199 | D9: =D5*$C$7/AVERAGE($C$5:$H$5) -> 67.566045 | E9: =E5*$C$7/AVERAGE($C$5:$H$5) -> 98.294347 | F9: =F5*$C$7/AVERAGE($C$5:$H$5) -> 111.7904 | G9: =G5*$C$7/AVERAGE($C$5:$H$5) -> 102.11632 | H9: =H5*$C$7/AVERAGE($C$5:$H$5) -> 81.395687
B10: Jet rebased to LH level ($/t) | C10: =C6*42*Model!$C$5*$C$8/(AVERAGE($C$6:$H$6)*42*Model!$C$5) -> 730.9795 | D10: =D6*42*Model!$C$5*$C$8/(AVERAGE($C$6:$H$6)*42*Model!$C$5) -> 814.11897 | E10: =E6*42*Model!$C$5*$C$8/(AVERAGE($C$6:$H$6)*42*Model!$C$5) -> 1330.5914 | F10: =F6*42*Model!$C$5*$C$8/(AVERAGE($C$6:$H$6)*42*Model!$C$5) -> 1413.7309 | G10: =G6*42*Model!$C$5*$C$8/(AVERAGE($C$6:$H$6)*42*Model!$C$5) -> 1419.1296 | H10: =H6*42*Model!$C$5*$C$8/(AVERAGE($C$6:$H$6)*42*Model!$C$5) -> 1094.8496
B11: Implied jet crack ($/bbl) | C11: =C10/Model!$C$5-C9 -> 29.286697 | D11: =D10/Model!$C$5-D9 -> 35.748544 | E11: =E10/Model!$C$5-E9 -> 70.562434 | F11: =F10/Model!$C$5-F9 -> 67.617075 | G11: =G10/Model!$C$5-G9 -> 77.976262 | H11: =H10/Model!$C$5-H9 -> 57.544623
B12: Model jet price J = k·(Brent + w·crack) ($/t) | C12: =Model!$C$5*((C9)+Model!$C$6*(C11)) -> 765.59637 | D12: =Model!$C$5*((D9)+Model!$C$6*(D11)) -> 856.37374 | E12: =Model!$C$5*((E9)+Model!$C$6*(E11)) -> 1413.9962 | F12: =Model!$C$5*((F9)+Model!$C$6*(F11)) -> 1493.6543 | G12: =Model!$C$5*((G9)+Model!$C$6*(G11)) -> 1511.2975 | H12: =Model!$C$5*((H9)+Model!$C$6*(H11)) -> 1162.8674
B13: Shape from FRED monthly series, level rebased to Lufthansa's H1 averages (FRED is US Gulf Coast jet and Europe Brent spot).
B15: Quarterly inputs (blue) and test
C16: Q1 2026 | D16: Q2 2026 | E16: H1 2026
B17: Guidance date | C17: 28 Feb 2026 | D17: 30 Apr 2026
B18: Guided post-hedge jet price ($/t) | C18: 853 | D18: 1263
B19: Guided volume (mt) | C19: 2 | D19: 2.4
B20: Guided mandatory SAF (€m) | C20: 40 | D20: 50
B21: Guided FX at guidance (USD/EUR) | C21: 1.18 | D21: 1.17
B22: Hedge ratio for the quarter (h) | C22: 0.82 | D22: 0.83
B23: Forward Brent at guidance, unrealised months ($/bbl) | C23: 70.6 | D23: 97.9
B24: Forward crack at guidance ($/bbl) | C24: 26.3 | D24: 59
B25: Realised FX (USD/EUR) | C25: 1.1664 | D25: 1.1664
B26: Reported fuel expense (€m) | C26: 1570 | D26: 2606 | E26: =C26+D26 -> 4176
B27: Reported hedge result (€m) | C27: 126 | D27: 459 | E27: =C27+D27 -> 585
B29: Guidance fuel cost (€m) | C29: =C19*C18/C21+C20 -> 1485.7627 | D29: =D19*D18/D21+D20 -> 2640.7692 | E29: =C29+D29 -> 4126.5319
B30: Forward model jet price J_fwd ($/t) | C30: =Model!$C$5*((C23)+Model!$C$6*(C24)) -> 794.6586 | D30: =Model!$C$5*((D23)+Model!$C$6*(D24)) -> 1306.11
B31: Unrealised months | C31: Mar | D31: May, Jun
B32: Model ΔP vs guidance ($/t) | C32: =(((E$12-C30)-C22*(((((E$12)-(Model!$C$16))*NORMSDIST(((E$12)-(Model!$C$16))/Model!$C$7)+Model!$C$7*EXP(-((((E$12)-(Model!$C$16))/Model!$C$7)^2)/2)/SQRT(2*PI()))-(((E$12)-(Model!$C$17))*NORMSDIST(((E$12)-(Model!$C$17))/Model!$C$7)+Model!$C$7*EXP(-((((E$12)-(Model!$C$17))/Model!$C$7)^2)/2)/SQRT(2*PI())))-((((C30)-(Model!$C$16))*NORMSDIST(((C30)-(Model!$C$16))/Model!$C$7)+Model!$C$7*EXP(-((((C30)-(Model!$C$16))/Model!$C$7)^2)/2)/SQRT(2*PI()))-(((C30)-(Model!$C$17))*NORMSDIST(((C30)-(Model!$C$17))/Model!$C$7)+Model!$C$7*EXP(-((((C30)-(Model!$C$17))/Model!$C$7)^2)/2)/SQRT(2*PI()))))))/3 -> 85.149734 | D32: =(((G$12-D30)-D22*(((((G$12)-(Model!$C$16))*NORMSDIST(((G$12)-(Model!$C$16))/Model!$C$7)+Model!$C$7*EXP(-((((G$12)-(Model!$C$16))/Model!$C$7)^2)/2)/SQRT(2*PI()))-(((G$12)-(Model!$C$17))*NORMSDIST(((G$12)-(Model!$C$17))/Model!$C$7)+Model!$C$7*EXP(-((((G$12)-(Model!$C$17))/Model!$C$7)^2)/2)/SQRT(2*PI())))-((((D30)-(Model!$C$16))*NORMSDIST(((D30)-(Model!$C$16))/Model!$C$7)+Model!$C$7*EXP(-((((D30)-(Model!$C$16))/Model!$C$7)^2)/2)/SQRT(2*PI()))-(((D30)-(Model!$C$17))*NORMSDIST(((D30)-(Model!$C$17))/Model!$C$7)+Model!$C$7*EXP(-((((D30)-(Model!$C$17))/Model!$C$7)^2)/2)/SQRT(2*PI())))))+((H$12-D30)-D22*(((((H$12)-(Model!$C$16))*NORMSDIST(((H$12)-(Model!$C$16))/Model!$C$7)+Model!$C$7*EXP(-((((H$12)-(Model!$C$16))/Model!$C$7)^2)/2)/SQRT(2*PI()))-(((H$12)-(Model!$C$17))*NORMSDIST(((H$12)-(Model!$C$17))/Model!$C$7)+Model!$C$7*EXP(-((((H$12)-(Model!$C$17))/Model!$C$7)^2)/2)/SQRT(2*PI())))-((((D30)-(Model!$C$16))*NORMSDIST(((D30)-(Model!$C$16))/Model!$C$7)+Model!$C$7*EXP(-((((D30)-(Model!$C$16))/Model!$C$7)^2)/2)/SQRT(2*PI()))-(((D30)-(Model!$C$17))*NORMSDIST(((D30)-(Model!$C$17))/Model!$C$7)+Model!$C$7*EXP(-((((D30)-(Model!$C$17))/Model!$C$7)^2)/2)/SQRT(2*PI()))))))/3 -> 29.743099
B33: MODEL fuel cost at realised prices (€m) | C33: =C19*(C18+C32)/C25+C20 -> 1648.6244 | D33: =D19*(D18+D32)/D25+D20 -> 2709.9652 | E33: =C33+D33 -> 4358.5896
B34: Error vs reported (€m) | C34: =C33-C26 -> 78.624373 | D34: =D33-D26 -> 103.96522 | E34: =E33-E26 -> 182.5896
B35: Error vs reported (%) | C35: =C34/C26 -> 0.050079218 | D35: =D34/D26 -> 0.03989456 | E35: =E34/E26 -> 0.043723563
B36: Model hedge payoff (€m, absolute) | C36: =C22*C19/3*((((C$12)-(Model!$C$16))*NORMSDIST(((C$12)-(Model!$C$16))/Model!$C$7)+Model!$C$7*EXP(-((((C$12)-(Model!$C$16))/Model!$C$7)^2)/2)/SQRT(2*PI()))-(((C$12)-(Model!$C$17))*NORMSDIST(((C$12)-(Model!$C$17))/Model!$C$7)+Model!$C$7*EXP(-((((C$12)-(Model!$C$17))/Model!$C$7)^2)/2)/SQRT(2*PI())))/C25+C22*C19/3*((((D$12)-(Model!$C$16))*NORMSDIST(((D$12)-(Model!$C$16))/Model!$C$7)+Model!$C$7*EXP(-((((D$12)-(Model!$C$16))/Model!$C$7)^2)/2)/SQRT(2*PI()))-(((D$12)-(Model!$C$17))*NORMSDIST(((D$12)-(Model!$C$17))/Model!$C$7)+Model!$C$7*EXP(-((((D$12)-(Model!$C$17))/Model!$C$7)^2)/2)/SQRT(2*PI())))/C25+C22*C19/3*((((E$12)-(Model!$C$16))*NORMSDIST(((E$12)-(Model!$C$16))/Model!$C$7)+Model!$C$7*EXP(-((((E$12)-(Model!$C$16))/Model!$C$7)^2)/2)/SQRT(2*PI()))-(((E$12)-(Model!$C$17))*NORMSDIST(((E$12)-(Model!$C$17))/Model!$C$7)+Model!$C$7*EXP(-((((E$12)-(Model!$C$17))/Model!$C$7)^2)/2)/SQRT(2*PI())))/C25 -> 411.18616 | D36: =D22*D19/3*((((F$12)-(Model!$C$16))*NORMSDIST(((F$12)-(Model!$C$16))/Model!$C$7)+Model!$C$7*EXP(-((((F$12)-(Model!$C$16))/Model!$C$7)^2)/2)/SQRT(2*PI()))-(((F$12)-(Model!$C$17))*NORMSDIST(((F$12)-(Model!$C$17))/Model!$C$7)+Model!$C$7*EXP(-((((F$12)-(Model!$C$17))/Model!$C$7)^2)/2)/SQRT(2*PI())))/D25+D22*D19/3*((((G$12)-(Model!$C$16))*NORMSDIST(((G$12)-(Model!$C$16))/Model!$C$7)+Model!$C$7*EXP(-((((G$12)-(Model!$C$16))/Model!$C$7)^2)/2)/SQRT(2*PI()))-(((G$12)-(Model!$C$17))*NORMSDIST(((G$12)-(Model!$C$17))/Model!$C$7)+Model!$C$7*EXP(-((((G$12)-(Model!$C$17))/Model!$C$7)^2)/2)/SQRT(2*PI())))/D25+D22*D19/3*((((H$12)-(Model!$C$16))*NORMSDIST(((H$12)-(Model!$C$16))/Model!$C$7)+Model!$C$7*EXP(-((((H$12)-(Model!$C$16))/Model!$C$7)^2)/2)/SQRT(2*PI()))-(((H$12)-(Model!$C$17))*NORMSDIST(((H$12)-(Model!$C$17))/Model!$C$7)+Model!$C$7*EXP(-((((H$12)-(Model!$C$17))/Model!$C$7)^2)/2)/SQRT(2*PI())))/D25 -> 934.00913 | E36: =C36+D36 -> 1345.1953
B37: Model hedge gain increase Q1→Q2 (€m) | C37: =D36-C36 -> 522.82297
B38: Reported increase Q1→Q2 (€m) | C38: =D27-C27 -> 333
B40: Reading the test:
B41: • Fuel cost: compare the yellow rows. Within roughly ±5% is as good as the inputs allow: quarterly volumes and FX are not disclosed (guided values used), and FRED is US Gulf Coast jet, rebased to Lufthansa's H1 average.
B42: • Absolute hedge payoff cannot be compared with the reported hedge result: the grid only pins how cost CHANGES with price, and option premiums and layering sit in P0.
B43: • The change in hedge gains between quarters can be compared: it tests whether the model's protection at high prices is right.

Sheet Calibration
B1: Calibration on published Lufthansa sensitivity grids
B2: Strikes are per hedge year (blue = calibrated values you can override). Global parameters live on the Model sheet.
B4: Hedge-year strikes | F4: Fit summary ($/t)
B5: Hedge year | C5: K1 ($/t) | D5: K2 ($/t) | F5: Grid (hedge year @ as-of) | G5: RMSE | H5: Max |error| | I5: Naive RMSE*
B6: 2026 | C6: 691 | D6: 1299 | F6: FY24@2024-10-22 | G6: =SQRT(SUMSQ(R30:V38)/COUNT(R30:V38)) -> 2.54555 | H6: =MAX(MAX(R30:V38),-MIN(R30:V38)) -> 6.9261855 | I6: =SQRT(C39/COUNT(R30:V38)) -> 20.542897
B7: 2025 | C7: 690 | D7: 1005 | F7: FY25@2025-02-28 | G7: =SQRT(SUMSQ(R55:V61)/COUNT(R55:V61)) -> 12.207854 | H7: =MAX(MAX(R55:V61),-MIN(R55:V61)) -> 29.260543 | I7: =SQRT(C62/COUNT(R55:V61)) -> 58.6927
B8: 2024 | C8: 900 | D8: 1345 | F8: FY25@2025-04-24 | G8: =SQRT(SUMSQ(R78:V84)/COUNT(R78:V84)) -> 13.535899 | H8: =MAX(MAX(R78:V84),-MIN(R78:V84)) -> 29.202747 | I8: =SQRT(C85/COUNT(R78:V84)) -> 65.044963
F9: FY25@2025-07-25 | G9: =SQRT(SUMSQ(R101:V107)/COUNT(R101:V107)) -> 7.9906082 | H9: =MAX(MAX(R101:V107),-MIN(R101:V107)) -> 20.156872 | I9: =SQRT(C108/COUNT(R101:V107)) -> 26.741635
F10: FY25@2025-10-24 | G10: =SQRT(SUMSQ(R124:V130)/COUNT(R124:V130)) -> 3.9934182 | H10: =MAX(MAX(R124:V130),-MIN(R124:V130)) -> 9.6726561 | I10: =SQRT(C131/COUNT(R124:V130)) -> 15.893985
F11: FY26@2026-02-28 | G11: =SQRT(SUMSQ(R147:V153)/COUNT(R147:V153)) -> 9.6749682 | H11: =MAX(MAX(R147:V153),-MIN(R147:V153)) -> 23.334455 | I11: =SQRT(C154/COUNT(R147:V153)) -> 43.616475
F12: FY26@2026-04-30 | G12: =SQRT(SUMSQ(R170:V176)/COUNT(R170:V176)) -> 10.57823 | H12: =MAX(MAX(R170:V176),-MIN(R170:V176)) -> 18.968005 | I12: =SQRT(C177/COUNT(R170:V176)) -> 53.543517
F13: FY26@2026-07-27 | G13: =SQRT(SUMSQ(R193:V199)/COUNT(R193:V199)) -> 6.3011204 | H13: =MAX(MAX(R193:V199),-MIN(R193:V199)) -> 13.390299 | I13: =SQRT(C200/COUNT(R193:V199)) -> 35.569146
F14: All grids | G14: =SQRT((SUMSQ(R30:V38)+SUMSQ(R55:V61)+SUMSQ(R78:V84)+SUMSQ(R101:V107)+SUMSQ(R124:V130)+SUMSQ(R147:V153)+SUMSQ(R170:V176)+SUMSQ(R193:V199))/(COUNT(R30:V38)+COUNT(R55:V61)+COUNT(R78:V84)+COUNT(R101:V107)+COUNT(R124:V130)+COUNT(R147:V153)+COUNT(R170:V176)+COUNT(R193:V199))) -> 8.9626823 | H14: =MAX(H6:H13) -> 29.260543 | I14: =SQRT((C39+C62+C85+C108+C131+C154+C177+C200)/(COUNT(R30:V38)+COUNT(R55:V61)+COUNT(R78:V84)+COUNT(R101:V107)+COUNT(R124:V130)+COUNT(R147:V153)+COUNT(R170:V176)+COUNT(R193:V199))) -> 42.859691
F15: *Naive = P0 + s·(1−h)·ΔJ, i.e. treating the hedge ratio as a straight swap hedge.
B17: FY24@2024-10-22 | C17: Source: Q3 2024 results presentation
B18: Hedge year | C18: 2024
B19: Months not yet realised | C19: 2
B20: s | C20: =C19/12 -> 0.16666667
B21: Hedge ratio h | C21: 0.83
B22: Base Brent | C22: 76
B23: Base crack | C23: 15
B24: P0 (centre cell) | C24: =INDEX(D30:H38,MATCH(C22,C30:C38,0),MATCH(C23,D29:H29,0)) -> 888
B25: K1 | C25: =INDEX($C$6:$C$8,MATCH(C18,$B$6:$B$8,0)) -> 900
B26: K2 | C26: =INDEX($D$6:$D$8,MATCH(C18,$B$6:$B$8,0)) -> 1345
C28: Published | J28: Model | Q28: Model − published
C29: Brent \ crack | D29: 5 | E29: 10 | F29: 15 | G29: 20 | H29: 25 | J29: Brent \ crack | K29: =D29 -> 5 | L29: =E29 -> 10 | M29: =F29 -> 15 | N29: =G29 -> 20 | O29: =H29 -> 25 | Q29: Brent \ crack | R29: =D29 -> 5 | S29: =E29 -> 10 | T29: =F29 -> 15 | U29: =G29 -> 20 | V29: =H29 -> 25
C30: 126 | D30: 916 | E30: 920 | F30: 923 | G30: 928 | H30: 933 | J30: =C30 -> 126 | K30: =$C$24+$C$20*((Model!$C$5*(($C30)+Model!$C$6*(D$29)))-(Model!$C$5*(($C$22)+Model!$C$6*($C$23)))-$C$21*(((((Model!$C$5*(($C30)+Model!$C$6*(D$29)))-($C$25))*NORMSDIST(((Model!$C$5*(($C30)+Model!$C$6*(D$29)))-($C$25))/Model!$C$7)+Model!$C$7*EXP(-((((Model!$C$5*(($C30)+Model!$C$6*(D$29)))-($C$25))/Model!$C$7)^2)/2)/SQRT(2*PI()))-(((Model!$C$5*(($C30)+Model!$C$6*(D$29)))-($C$26))*NORMSDIST(((Model!$C$5*(($C30)+Model!$C$6*(D$29)))-($C$26))/Model!$C$7)+Model!$C$7*EXP(-((((Model!$C$5*(($C30)+Model!$C$6*(D$29)))-($C$26))/Model!$C$7)^2)/2)/SQRT(2*PI())))-((((Model!$C$5*(($C$22)+Model!$C$6*($C$23)))-($C$25))*NORMSDIST(((Model!$C$5*(($C$22)+Model!$C$6*($C$23)))-($C$25))/Model!$C$7)+Model!$C$7*EXP(-((((Model!$C$5*(($C$22)+Model!$C$6*($C$23)))-($C$25))/Model!$C$7)^2)/2)/SQRT(2*PI()))-(((Model!$C$5*(($C$22)+Model!$C$6*($C$23)))-($C$26))*NORMSDIST(((Model!$C$5*(($C$22)+Model!$C$6*($C$23)))-($C$26))/Model!$C$7)+Model!$C$7*EXP(-((((Model!$C$5*(($C$22)+Model!$C$6*($C$23)))-($C$26))/Model!$C$7)^2)/2)/SQRT(2*PI()))))) -> 919.1565 | L30: =$C$24+$C$20*((Model!$C$5*(($C30)+Model!$C$6*(E$29)))-(Model!$C$5*(($C$22)+Model!$C$6*($C$23)))-$C$21*(((((Model!$C$5*(($C30)+Model!$C$6*(E$29)))-($C$25))*NORMSDIST(((Model!$C$5*(($C30)+Model!$C$6*(E$29)))-($C$25))/Model!$C$7)+Model!$C$7*EXP(-((((Model!$C$5*(($C30)+Model!$C$6*(E$29)))-($C$25))/Model!$C$7)^2)/2)/SQRT(2*PI()))-(((Model!$C$5*(($C30)+Model!$C$6*(E$29)))-($C$26))*NORMSDIST(((Model!$C$5*(($C30)+Model!$C$6*(E$29)))-($C$26))/Model!$C$7)+Model!$C$7*EXP(-((((Model!$C$5*(($C30)+Model!$C$6*(E$29)))-($C$26))/Model!$C$7)^2)/2)/SQRT(2*PI())))-((((Model!$C$5*(($C$22)+Model!$C$6*($C$23)))-($C$25))*NORMSDIST(((Model!$C$5*(($C$22)+Model!$C$6*($C$23)))-($C$25))/Model!$C$7)+Model!$C$7*EXP(-((((Model!$C$5*(($C$22)+Model!$C$6*($C$23)))-($C$25))/Model!$C$7)^2)/2)/SQRT(2*PI()))-(((Model!$C$5*(($C$22)+Model!$C$6*($C$23)))-($C$26))*NORMSDIST(((Model!$C$5*(($C$22)+Model!$C$6*($C$23)))-($C$26))/Model!$C$7)+Model!$C$7*EXP(-((((Model!$C$5*(($C$22)+Model!$C$6*($C$23)))-($C$26))/Model!$C$7)^2)/2)/SQRT(2*PI()))))) -> 921.98477 | M30: =$C$24+$C$20*((Model!$C$5*(($C30)+Model!$C$6*(F$29)))-(Model!$C$5*(($C$22)+Model!$C$6*($C$23)))-$C$21*(((((Model!$C$5*(($C30)+Model!$C$6*(F$29)))-($C$25))*NORMSDIST(((Model!$C$5*(($C30)+Model!$C$6*(F$29)))-($C$25))/Model!$C$7)+Model!$C$7*EXP(-((((Model!$C$5*(($C30)+Model!$C$6*(F$29)))-($C$25))/Model!$C$7)^2)/2)/SQRT(2*PI()))-(((Model!$C$5*(($C30)+Model!$C$6*(F$29)))-($C$26))*NORMSDIST(((Model!$C$5*(($C30)+Model!$C$6*(F$29)))-($C$26))/Model!$C$7)+Model!$C$7*EXP(-((((Model!$C$5*(($C30)+Model!$C$6*(F$29)))-($C$26))/Model!$C$7)^2)/2)/SQRT(2*PI())))-((((Model!$C$5*(($C$22)+Model!$C$6*($C$23)))-($C$25))*NORMSDIST(((Model!$C$5*(($C$22)+Model!$C$6*($C$23)))-($C$25))/Model!$C$7)+Model!$C$7*EXP(-((((Model!$C$5*(($C$22)+Model!$C$6*($C$23)))-($C$25))/Model!$C$7)^2)/2)/SQRT(2*PI()))-(((Model!$C$5*(($C$22)+Model!$C$6*($C$23)))-($C$26))*NORMSDIST(((Model!$C$5*(($C$22)+Model!$C$6*($C$23)))-($C$26))/Model!$C$7)+Model!$C$7*EXP(-((((Model!$C$5*(($C$22)+Model!$C$6*($C$23)))-($C$26))/Model!$C$7)^2)/2)/SQRT(2*PI()))))) -> 924.66026 | N30: =$C$24+$C$20*((Model!$C$5*(($C30)+Model!$C$6*(G$29)))-(Model!$C$5*(($C$22)+Model!$C$6*($C$23)))-$C$21*(((((Model!$C$5*(($C30)+Model!$C$6*(G$29)))-($C$25))*NORMSDIST(((Model!$C$5*(($C30)+Model!$C$6*(G$29)))-($C$25))/Model!$C$7)+Model!$C$7*EXP(-((((Model!$C$5*(($C30)+Model!$C$6*(G$29)))-($C$25))/Model!$C$7)^2)/2)/SQRT(2*PI()))-(((Model!$C$5*(($C30)+Model!$C$6*(G$29)))-($C$26))*NORMSDIST(((Model!$C$5*(($C30)+Model!$C$6*(G$29)))-($C$26))/Model!$C$7)+Model!$C$7*EXP(-((((Model!$C$5*(($C30)+Model!$C$6*(G$29)))-($C$26))/Model!$C$7)^2)/2)/SQRT(2*PI())))-((((Model!$C$5*(($C$22)+Model!$C$6*($C$23)))-($C$25))*NORMSDIST(((Model!$C$5*(($C$22)+Model!$C$6*($C$23)))-($C$25))/Model!$C$7)+Model!$C$7*EXP(-((((Model!$C$5*(($C$22)+Model!$C$6*($C$23)))-($C$25))/Model!$C$7)^2)/2)/SQRT(2*PI()))-(((Model!$C$5*(($C$22)+Model!$C$6*($C$23)))-($C$26))*NORMSDIST(((Model!$C$5*(($C$22)+Model!$C$6*($C$23)))-($C$26))/Model!$C$7)+Model!$C$7*EXP(-((((Model!$C$5*(($C$22)+Model!$C$6*($C$23)))-($C$26))/Model!$C$7)^2)/2)/SQRT(2*PI()))))) -> 927.36074 | O30: =$C$24+$C$20*((Model!$C$5*(($C30)+Model!$C$6*(H$29)))-(Model!$C$5*(($C$22)+Model!$C$6*($C$23)))-$C$21*(((((Model!$C$5*(($C30)+Model!$C$6*(H$29)))-($C$25))*NORMSDIST(((Model!$C$5*(($C30)+Model!$C$6*(H$29)))-($C$25))/Model!$C$7)+Model!$C$7*EXP(-((((Model!$C$5*(($C30)+Model!$C$6*(H$29)))-($C$25))/Model!$C$7)^2)/2)/SQRT(2*PI()))-(((Model!$C$5*(($C30)+Model!$C$6*(H$29)))-($C$26))*NORMSDIST(((Model!$C$5*(($C30)+Model!$C$6*(H$29)))-($C$26))/Model!$C$7)+Model!$C$7*EXP(-((((Model!$C$5*(($C30)+Model!$C$6*(H$29)))-($C$26))/Model!$C$7)^2)/2)/SQRT(2*PI())))-((((Model!$C$5*(($C$22)+Model!$C$6*($C$23)))-($C$25))*NORMSDIST(((Model!$C$5*(($C$22)+Model!$C$6*($C$23)))-($C$25))/Model!$C$7)+Model!$C$7*EXP(-((((Model!$C$5*(($C$22)+Model!$C$6*($C$23)))-($C$25))/Model!$C$7)^2)/2)/SQRT(2*PI()))-(((Model!$C$5*(($C$22)+Model!$C$6*($C$23)))-($C$26))*NORMSDIST(((Model!$C$5*(($C$22)+Model!$C$6*($C$23)))-($C$26))/Model!$C$7)+Model!$C$7*EXP(-((((Model!$C$5*(($C$22)+Model!$C$6*($C$23)))-($C$26))/Model!$C$7)^2)/2)/SQRT(2*PI()))))) -> 930.2617 | Q30: =C30 -> 126 | R30: =K30-D30 -> 3.156498 | S30: =L30-E30 -> 1.9847698 | T30: =M30-F30 -> 1.6602565 | U30: =N30-G30 -> -0.63925738 | V30: =O30-H30 -> -2.7383016
C31: 116 | D31: 910 | E31: 913 | F31: 917 | G31: 921 | H31: 925 | J31: =C31 -> 116 | K31: =$C$24+$C$20*((Model!$C$5*(($C31)+Model!$C$6*(D$29)))-(Model!$C$5*(($C$22)+Model!$C$6*($C$23)))-$C$21*(((((Model!$C$5*(($C31)+Model!$C$6*(D$29)))-($C$25))*NORMSDIST(((Model!$C$5*(($C31)+Model!$C$6*(D$29)))-($C$25))/Model!$C$7)+Model!$C$7*EXP(-((((Model!$C$5*(($C31)+Model!$C$6*(D$29)))-($C$25))/Model!$C$7)^2)/2)/SQRT(2*PI()))-(((Model!$C$5*(($C31)+Model!$C$6*(D$29)))-($C$26))*NORMSDIST(((Model!$C$5*(($C31)+Model!$C$6*(D$29)))-($C$26))/Model!$C$7)+Model!$C$7*EXP(-((((Model!$C$5*(($C31)+Model!$C$6*(D$29)))-($C$26))/Model!$C$7)^2)/2)/SQRT(2*PI())))-((((Model!$C$5*(($C$22)+Model!$C$6*($C$23)))-($C$25))*NORMSDIST(((Model!$C$5*(($C$22)+Model!$C$6*($C$23)))-($C$25))/Model!$C$7)+Model!$C$7*EXP(-((((Model!$C$5*(($C$22)+Model!$C$6*($C$23)))-($C$25))/Model!$C$7)^2)/2)/SQRT(2*PI()))-(((Model!$C$5*(($C$22)+Model!$C$6*($C$23)))-($C$26))*NORMSDIST(((Model!$C$5*(($C$22)+Model!$C$6*($C$23)))-($C$26))/Model!$C$7)+Model!$C$7*EXP(-((((Model!$C$5*(($C$22)+Model!$C$6*($C$23)))-($C$26))/Model!$C$7)^2)/2)/SQRT(2*PI()))))) -> 913.40366 | L31: =$C$24+$C$20*((Model!$C$5*(($C31)+Model!$C$6*(E$29)))-(Model!$C$5*(($C$22)+Model!$C$6*($C$23)))-$C$21*(((((Model!$C$5*(($C31)+Model!$C$6*(E$29)))-($C$25))*NORMSDIST(((Model!$C$5*(($C31)+Model!$C$6*(E$29)))-($C$25))/Model!$C$7)+Model!$C$7*EXP(-((((Model!$C$5*(($C31)+Model!$C$6*(E$29)))-($C$25))/Model!$C$7)^2)/2)/SQRT(2*PI()))-(((Model!$C$5*(($C31)+Model!$C$6*(E$29)))-($C$26))*NORMSDIST(((Model!$C$5*(($C31)+Model!$C$6*(E$29)))-($C$26))/Model!$C$7)+Model!$C$7*EXP(-((((Model!$C$5*(($C31)+Model!$C$6*(E$29)))-($C$26))/Model!$C$7)^2)/2)/SQRT(2*PI())))-((((Model!$C$5*(($C$22)+Model!$C$6*($C$23)))-($C$25))*NORMSDIST(((Model!$C$5*(($C$22)+Model!$C$6*($C$23)))-($C$25))/Model!$C$7)+Model!$C$7*EXP(-((((Model!$C$5*(($C$22)+Model!$C$6*($C$23)))-($C$25))/Model!$C$7)^2)/2)/SQRT(2*PI()))-(((Model!$C$5*(($C$22)+Model!$C$6*($C$23)))-($C$26))*NORMSDIST(((Model!$C$5*(($C$22)+Model!$C$6*($C$23)))-($C$26))/Model!$C$7)+Model!$C$7*EXP(-((((Model!$C$5*(($C$22)+Model!$C$6*($C$23)))-($C$26))/Model!$C$7)^2)/2)/SQRT(2*PI()))))) -> 916.87082 | M31: =$C$24+$C$20*((Model!$C$5*(($C31)+Model!$C$6*(F$29)))-(Model!$C$5*(($C$22)+Model!$C$6*($C$23)))-$C$21*(((((Model!$C$5*(($C31)+Model!$C$6*(F$29)))-($C$25))*NORMSDIST(((Model!$C$5*(($C31)+Model!$C$6*(F$29)))-($C$25))/Model!$C$7)+Model!$C$7*EXP(-((((Model!$C$5*(($C31)+Model!$C$6*(F$29)))-($C$25))/Model!$C$7)^2)/2)/SQRT(2*PI()))-(((Model!$C$5*(($C31)+Model!$C$6*(F$29)))-($C$26))*NORMSDIST(((Model!$C$5*(($C31)+Model!$C$6*(F$29)))-($C$26))/Model!$C$7)+Model!$C$7*EXP(-((((Model!$C$5*(($C31)+Model!$C$6*(F$29)))-($C$26))/Model!$C$7)^2)/2)/SQRT(2*PI())))-((((Model!$C$5*(($C$22)+Model!$C$6*($C$23)))-($C$25))*NORMSDIST(((Model!$C$5*(($C$22)+Model!$C$6*($C$23)))-($C$25))/Model!$C$7)+Model!$C$7*EXP(-((((Model!$C$5*(($C$22)+Model!$C$6*($C$23)))-($C$25))/Model!$C$7)^2)/2)/SQRT(2*PI()))-(((Model!$C$5*(($C$22)+Model!$C$6*($C$23)))-($C$26))*NORMSDIST(((Model!$C$5*(($C$22)+Model!$C$6*($C$23)))-($C$26))/Model!$C$7)+Model!$C$7*EXP(-((((Model!$C$5*(($C$22)+Model!$C$6*($C$23)))-($C$26))/Model!$C$7)^2)/2)/SQRT(2*PI()))))) -> 919.91859 | N31: =$C$24+$C$20*((Model!$C$5*(($C31)+Model!$C$6*(G$29)))-(Model!$C$5*(($C$22)+Model!$C$6*($C$23)))-$C$21*(((((Model!$C$5*(($C31)+Model!$C$6*(G$29)))-($C$25))*NORMSDIST(((Model!$C$5*(($C31)+Model!$C$6*(G$29)))-($C$25))/Model!$C$7)+Model!$C$7*EXP(-((((Model!$C$5*(($C31)+Model!$C$6*(G$29)))-($C$25))/Model!$C$7)^2)/2)/SQRT(2*PI()))-(((Model!$C$5*(($C31)+Model!$C$6*(G$29)))-($C$26))*NORMSDIST(((Model!$C$5*(($C31)+Model!$C$6*(G$29)))-($C$26))/Model!$C$7)+Model!$C$7*EXP(-((((Model!$C$5*(($C31)+Model!$C$6*(G$29)))-($C$26))/Model!$C$7)^2)/2)/SQRT(2*PI())))-((((Model!$C$5*(($C$22)+Model!$C$6*($C$23)))-($C$25))*NORMSDIST(((Model!$C$5*(($C$22)+Model!$C$6*($C$23)))-($C$25))/Model!$C$7)+Model!$C$7*EXP(-((((Model!$C$5*(($C$22)+Model!$C$6*($C$23)))-($C$25))/Model!$C$7)^2)/2)/SQRT(2*PI()))-(((Model!$C$5*(($C$22)+Model!$C$6*($C$23)))-($C$26))*NORMSDIST(((Model!$C$5*(($C$22)+Model!$C$6*($C$23)))-($C$26))/Model!$C$7)+Model!$C$7*EXP(-((((Model!$C$5*(($C$22)+Model!$C$6*($C$23)))-($C$26))/Model!$C$7)^2)/2)/SQRT(2*PI()))))) -> 922.69037 | O31: =$C$24+$C$20*((Model!$C$5*(($C31)+Model!$C$6*(H$29)))-(Model!$C$5*(($C$22)+Model!$C$6*($C$23)))-$C$21*(((((Model!$C$5*(($C31)+Model!$C$6*(H$29)))-($C$25))*NORMSDIST(((Model!$C$5*(($C31)+Model!$C$6*(H$29)))-($C$25))/Model!$C$7)+Model!$C$7*EXP(-((((Model!$C$5*(($C31)+Model!$C$6*(H$29)))-($C$25))/Model!$C$7)^2)/2)/SQRT(2*PI()))-(((Model!$C$5*(($C31)+Model!$C$6*(H$29)))-($C$26))*NORMSDIST(((Model!$C$5*(($C31)+Model!$C$6*(H$29)))-($C$26))/Model!$C$7)+Model!$C$7*EXP(-((((Model!$C$5*(($C31)+Model!$C$6*(H$29)))-($C$26))/Model!$C$7)^2)/2)/SQRT(2*PI())))-((((Model!$C$5*(($C$22)+Model!$C$6*($C$23)))-($C$25))*NORMSDIST(((Model!$C$5*(($C$22)+Model!$C$6*($C$23)))-($C$25))/Model!$C$7)+Model!$C$7*EXP(-((((Model!$C$5*(($C$22)+Model!$C$6*($C$23)))-($C$25))/Model!$C$7)^2)/2)/SQRT(2*PI()))-(((Model!$C$5*(($C$22)+Model!$C$6*($C$23)))-($C$26))*NORMSDIST(((Model!$C$5*(($C$22)+Model!$C$6*($C$23)))-($C$26))/Model!$C$7)+Model!$C$7*EXP(-((((Model!$C$5*(($C$22)+Model!$C$6*($C$23)))-($C$26))/Model!$C$7)^2)/2)/SQRT(2*PI()))))) -> 925.35504 | Q31: =C31 -> 116 | R31: =K31-D31 -> 3.4036615 | S31: =L31-E31 -> 3.8708168 | T31: =M31-F31 -> 2.9185865 | U31: =N31-G31 -> 1.6903692 | V31: =O31-H31 -> 0.35503747
C32: 106 | D32: 905 | E32: 910 | F32: 914 | G32: 918 | H32: 921 | J32: =C32 -> 106 | K32: =$C$24+$C$20*((Model!$C$5*(($C32)+Model!$C$6*(D$29)))-(Model!$C$5*(($C$22)+Model!$C$6*($C$23)))-$C$21*(((((Model!$C$5*(($C32)+Model!$C$6*(D$29)))-($C$25))*NORMSDIST(((Model!$C$5*(($C32)+Model!$C$6*(D$29)))-($C$25))/Model!$C$7)+Model!$C$7*EXP(-((((Model!$C$5*(($C32)+Model!$C$6*(D$29)))-($C$25))/Model!$C$7)^2)/2)/SQRT(2*PI()))-(((Model!$C$5*(($C32)+Model!$C$6*(D$29)))-($C$26))*NORMSDIST(((Model!$C$5*(($C32)+Model!$C$6*(D$29)))-($C$26))/Model!$C$7)+Model!$C$7*EXP(-((((Model!$C$5*(($C32)+Model!$C$6*(D$29)))-($C$26))/Model!$C$7)^2)/2)/SQRT(2*PI())))-((((Model!$C$5*(($C$22)+Model!$C$6*($C$23)))-($C$25))*NORMSDIST(((Model!$C$5*(($C$22)+Model!$C$6*($C$23)))-($C$25))/Model!$C$7)+Model!$C$7*EXP(-((((Model!$C$5*(($C$22)+Model!$C$6*($C$23)))-($C$25))/Model!$C$7)^2)/2)/SQRT(2*PI()))-(((Model!$C$5*(($C$22)+Model!$C$6*($C$23)))-($C$26))*NORMSDIST(((Model!$C$5*(($C$22)+Model!$C$6*($C$23)))-($C$26))/Model!$C$7)+Model!$C$7*EXP(-((((Model!$C$5*(($C$22)+Model!$C$6*($C$23)))-($C$26))/Model!$C$7)^2)/2)/SQRT(2*PI()))))) -> 906.08824 | L32: =$C$24+$C$20*((Model!$C$5*(($C32)+Model!$C$6*(E$29)))-(Model!$C$5*(($C$22)+Model!$C$6*($C$23)))-$C$21*(((((Model!$C$5*(($C32)+Model!$C$6*(E$29)))-($C$25))*NORMSDIST(((Model!$C$5*(($C32)+Model!$C$6*(E$29)))-($C$25))/Model!$C$7)+Model!$C$7*EXP(-((((Model!$C$5*(($C32)+Model!$C$6*(E$29)))-($C$25))/Model!$C$7)^2)/2)/SQRT(2*PI()))-(((Model!$C$5*(($C32)+Model!$C$6*(E$29)))-($C$26))*NORMSDIST(((Model!$C$5*(($C32)+Model!$C$6*(E$29)))-($C$26))/Model!$C$7)+Model!$C$7*EXP(-((((Model!$C$5*(($C32)+Model!$C$6*(E$29)))-($C$26))/Model!$C$7)^2)/2)/SQRT(2*PI())))-((((Model!$C$5*(($C$22)+Model!$C$6*($C$23)))-($C$25))*NORMSDIST(((Model!$C$5*(($C$22)+Model!$C$6*($C$23)))-($C$25))/Model!$C$7)+Model!$C$7*EXP(-((((Model!$C$5*(($C$22)+Model!$C$6*($C$23)))-($C$25))/Model!$C$7)^2)/2)/SQRT(2*PI()))-(((Model!$C$5*(($C$22)+Model!$C$6*($C$23)))-($C$26))*NORMSDIST(((Model!$C$5*(($C$22)+Model!$C$6*($C$23)))-($C$26))/Model!$C$7)+Model!$C$7*EXP(-((((Model!$C$5*(($C$22)+Model!$C$6*($C$23)))-($C$26))/Model!$C$7)^2)/2)/SQRT(2*PI()))))) -> 910.50801 | M32: =$C$24+$C$20*((Model!$C$5*(($C32)+Model!$C$6*(F$29)))-(Model!$C$5*(($C$22)+Model!$C$6*($C$23)))-$C$21*(((((Model!$C$5*(($C32)+Model!$C$6*(F$29)))-($C$25))*NORMSDIST(((Model!$C$5*(($C32)+Model!$C$6*(F$29)))-($C$25))/Model!$C$7)+Model!$C$7*EXP(-((((Model!$C$5*(($C32)+Model!$C$6*(F$29)))-($C$25))/Model!$C$7)^2)/2)/SQRT(2*PI()))-(((Model!$C$5*(($C32)+Model!$C$6*(F$29)))-($C$26))*NORMSDIST(((Model!$C$5*(($C32)+Model!$C$6*(F$29)))-($C$26))/Model!$C$7)+Model!$C$7*EXP(-((((Model!$C$5*(($C32)+Model!$C$6*(F$29)))-($C$26))/Model!$C$7)^2)/2)/SQRT(2*PI())))-((((Model!$C$5*(($C$22)+Model!$C$6*($C$23)))-($C$25))*NORMSDIST(((Model!$C$5*(($C$22)+Model!$C$6*($C$23)))-($C$25))/Model!$C$7)+Model!$C$7*EXP(-((((Model!$C$5*(($C$22)+Model!$C$6*($C$23)))-($C$25))/Model!$C$7)^2)/2)/SQRT(2*PI()))-(((Model!$C$5*(($C$22)+Model!$C$6*($C$23)))-($C$26))*NORMSDIST(((Model!$C$5*(($C$22)+Model!$C$6*($C$23)))-($C$26))/Model!$C$7)+Model!$C$7*EXP(-((((Model!$C$5*(($C$22)+Model!$C$6*($C$23)))-($C$26))/Model!$C$7)^2)/2)/SQRT(2*PI()))))) -> 914.35522 | N32: =$C$24+$C$20*((Model!$C$5*(($C32)+Model!$C$6*(G$29)))-(Model!$C$5*(($C$22)+Model!$C$6*($C$23)))-$C$21*(((((Model!$C$5*(($C32)+Model!$C$6*(G$29)))-($C$25))*NORMSDIST(((Model!$C$5*(($C32)+Model!$C$6*(G$29)))-($C$25))/Model!$C$7)+Model!$C$7*EXP(-((((Model!$C$5*(($C32)+Model!$C$6*(G$29)))-($C$25))/Model!$C$7)^2)/2)/SQRT(2*PI()))-(((Model!$C$5*(($C32)+Model!$C$6*(G$29)))-($C$26))*NORMSDIST(((Model!$C$5*(($C32)+Model!$C$6*(G$29)))-($C$26))/Model!$C$7)+Model!$C$7*EXP(-((((Model!$C$5*(($C32)+Model!$C$6*(G$29)))-($C$26))/Model!$C$7)^2)/2)/SQRT(2*PI())))-((((Model!$C$5*(($C$22)+Model!$C$6*($C$23)))-($C$25))*NORMSDIST(((Model!$C$5*(($C$22)+Model!$C$6*($C$23)))-($C$25))/Model!$C$7)+Model!$C$7*EXP(-((((Model!$C$5*(($C$22)+Model!$C$6*($C$23)))-($C$25))/Model!$C$7)^2)/2)/SQRT(2*PI()))-(((Model!$C$5*(($C$22)+Model!$C$6*($C$23)))-($C$26))*NORMSDIST(((Model!$C$5*(($C$22)+Model!$C$6*($C$23)))-($C$26))/Model!$C$7)+Model!$C$7*EXP(-((((Model!$C$5*(($C$22)+Model!$C$6*($C$23)))-($C$26))/Model!$C$7)^2)/2)/SQRT(2*PI()))))) -> 917.7011 | O32: =$C$24+$C$20*((Model!$C$5*(($C32)+Model!$C$6*(H$29)))-(Model!$C$5*(($C$22)+Model!$C$6*($C$23)))-$C$21*(((((Model!$C$5*(($C32)+Model!$C$6*(H$29)))-($C$25))*NORMSDIST(((Model!$C$5*(($C32)+Model!$C$6*(H$29)))-($C$25))/Model!$C$7)+Model!$C$7*EXP(-((((Model!$C$5*(($C32)+Model!$C$6*(H$29)))-($C$25))/Model!$C$7)^2)/2)/SQRT(2*PI()))-(((Model!$C$5*(($C32)+Model!$C$6*(H$29)))-($C$26))*NORMSDIST(((Model!$C$5*(($C32)+Model!$C$6*(H$29)))-($C$26))/Model!$C$7)+Model!$C$7*EXP(-((((Model!$C$5*(($C32)+Model!$C$6*(H$29)))-($C$26))/Model!$C$7)^2)/2)/SQRT(2*PI())))-((((Model!$C$5*(($C$22)+Model!$C$6*($C$23)))-($C$25))*NORMSDIST(((Model!$C$5*(($C$22)+Model!$C$6*($C$23)))-($C$25))/Model!$C$7)+Model!$C$7*EXP(-((((Model!$C$5*(($C$22)+Model!$C$6*($C$23)))-($C$25))/Model!$C$7)^2)/2)/SQRT(2*PI()))-(((Model!$C$5*(($C$22)+Model!$C$6*($C$23)))-($C$26))*NORMSDIST(((Model!$C$5*(($C$22)+Model!$C$6*($C$23)))-($C$26))/Model!$C$7)+Model!$C$7*EXP(-((((Model!$C$5*(($C$22)+Model!$C$6*($C$23)))-($C$26))/Model!$C$7)^2)/2)/SQRT(2*PI()))))) -> 920.66176 | Q32: =C32 -> 106 | R32: =K32-D32 -> 1.0882372 | S32: =L32-E32 -> 0.50801231 | T32: =M32-F32 -> 0.3552177 | U32: =N32-G32 -> -0.29890493 | V32: =O32-H32 -> -0.33824325
C33: 96 | D33: 897 | E33: 904 | F33: 910 | G33: 914 | H33: 918 | J33: =C33 -> 96 | K33: =$C$24+$C$20*((Model!$C$5*(($C33)+Model!$C$6*(D$29)))-(Model!$C$5*(($C$22)+Model!$C$6*($C$23)))-$C$21*(((((Model!$C$5*(($C33)+Model!$C$6*(D$29)))-($C$25))*NORMSDIST(((Model!$C$5*(($C33)+Model!$C$6*(D$29)))-($C$25))/Model!$C$7)+Model!$C$7*EXP(-((((Model!$C$5*(($C33)+Model!$C$6*(D$29)))-($C$25))/Model!$C$7)^2)/2)/SQRT(2*PI()))-(((Model!$C$5*(($C33)+Model!$C$6*(D$29)))-($C$26))*NORMSDIST(((Model!$C$5*(($C33)+Model!$C$6*(D$29)))-($C$26))/Model!$C$7)+Model!$C$7*EXP(-((((Model!$C$5*(($C33)+Model!$C$6*(D$29)))-($C$26))/Model!$C$7)^2)/2)/SQRT(2*PI())))-((((Model!$C$5*(($C$22)+Model!$C$6*($C$23)))-($C$25))*NORMSDIST(((Model!$C$5*(($C$22)+Model!$C$6*($C$23)))-($C$25))/Model!$C$7)+Model!$C$7*EXP(-((((Model!$C$5*(($C$22)+Model!$C$6*($C$23)))-($C$25))/Model!$C$7)^2)/2)/SQRT(2*PI()))-(((Model!$C$5*(($C$22)+Model!$C$6*($C$23)))-($C$26))*NORMSDIST(((Model!$C$5*(($C$22)+Model!$C$6*($C$23)))-($C$26))/Model!$C$7)+Model!$C$7*EXP(-((((Model!$C$5*(($C$22)+Model!$C$6*($C$23)))-($C$26))/Model!$C$7)^2)/2)/SQRT(2*PI()))))) -> 896.99592 | L33: =$C$24+$C$20*((Model!$C$5*(($C33)+Model!$C$6*(E$29)))-(Model!$C$5*(($C$22)+Model!$C$6*($C$23)))-$C$21*(((((Model!$C$5*(($C33)+Model!$C$6*(E$29)))-($C$25))*NORMSDIST(((Model!$C$5*(($C33)+Model!$C$6*(E$29)))-($C$25))/Model!$C$7)+Model!$C$7*EXP(-((((Model!$C$5*(($C33)+Model!$C$6*(E$29)))-($C$25))/Model!$C$7)^2)/2)/SQRT(2*PI()))-(((Model!$C$5*(($C33)+Model!$C$6*(E$29)))-($C$26))*NORMSDIST(((Model!$C$5*(($C33)+Model!$C$6*(E$29)))-($C$26))/Model!$C$7)+Model!$C$7*EXP(-((((Model!$C$5*(($C33)+Model!$C$6*(E$29)))-($C$26))/Model!$C$7)^2)/2)/SQRT(2*PI())))-((((Model!$C$5*(($C$22)+Model!$C$6*($C$23)))-($C$25))*NORMSDIST(((Model!$C$5*(($C$22)+Model!$C$6*($C$23)))-($C$25))/Model!$C$7)+Model!$C$7*EXP(-((((Model!$C$5*(($C$22)+Model!$C$6*($C$23)))-($C$25))/Model!$C$7)^2)/2)/SQRT(2*PI()))-(((Model!$C$5*(($C$22)+Model!$C$6*($C$23)))-($C$26))*NORMSDIST(((Model!$C$5*(($C$22)+Model!$C$6*($C$23)))-($C$26))/Model!$C$7)+Model!$C$7*EXP(-((((Model!$C$5*(($C$22)+Model!$C$6*($C$23)))-($C$26))/Model!$C$7)^2)/2)/SQRT(2*PI()))))) -> 902.43834 | M33: =$C$24+$C$20*((Model!$C$5*(($C33)+Model!$C$6*(F$29)))-(Model!$C$5*(($C$22)+Model!$C$6*($C$23)))-$C$21*(((((Model!$C$5*(($C33)+Model!$C$6*(F$29)))-($C$25))*NORMSDIST(((Model!$C$5*(($C33)+Model!$C$6*(F$29)))-($C$25))/Model!$C$7)+Model!$C$7*EXP(-((((Model!$C$5*(($C33)+Model!$C$6*(F$29)))-($C$25))/Model!$C$7)^2)/2)/SQRT(2*PI()))-(((Model!$C$5*(($C33)+Model!$C$6*(F$29)))-($C$26))*NORMSDIST(((Model!$C$5*(($C33)+Model!$C$6*(F$29)))-($C$26))/Model!$C$7)+Model!$C$7*EXP(-((((Model!$C$5*(($C33)+Model!$C$6*(F$29)))-($C$26))/Model!$C$7)^2)/2)/SQRT(2*PI())))-((((Model!$C$5*(($C$22)+Model!$C$6*($C$23)))-($C$25))*NORMSDIST(((Model!$C$5*(($C$22)+Model!$C$6*($C$23)))-($C$25))/Model!$C$7)+Model!$C$7*EXP(-((((Model!$C$5*(($C$22)+Model!$C$6*($C$23)))-($C$25))/Model!$C$7)^2)/2)/SQRT(2*PI()))-(((Model!$C$5*(($C$22)+Model!$C$6*($C$23)))-($C$26))*NORMSDIST(((Model!$C$5*(($C$22)+Model!$C$6*($C$23)))-($C$26))/Model!$C$7)+Model!$C$7*EXP(-((((Model!$C$5*(($C$22)+Model!$C$6*($C$23)))-($C$26))/Model!$C$7)^2)/2)/SQRT(2*PI()))))) -> 907.29854 | N33: =$C$24+$C$20*((Model!$C$5*(($C33)+Model!$C$6*(G$29)))-(Model!$C$5*(($C$22)+Model!$C$6*($C$23)))-$C$21*(((((Model!$C$5*(($C33)+Model!$C$6*(G$29)))-($C$25))*NORMSDIST(((Model!$C$5*(($C33)+Model!$C$6*(G$29)))-($C$25))/Model!$C$7)+Model!$C$7*EXP(-((((Model!$C$5*(($C33)+Model!$C$6*(G$29)))-($C$25))/Model!$C$7)^2)/2)/SQRT(2*PI()))-(((Model!$C$5*(($C33)+Model!$C$6*(G$29)))-($C$26))*NORMSDIST(((Model!$C$5*(($C33)+Model!$C$6*(G$29)))-($C$26))/Model!$C$7)+Model!$C$7*EXP(-((((Model!$C$5*(($C33)+Model!$C$6*(G$29)))-($C$26))/Model!$C$7)^2)/2)/SQRT(2*PI())))-((((Model!$C$5*(($C$22)+Model!$C$6*($C$23)))-($C$25))*NORMSDIST(((Model!$C$5*(($C$22)+Model!$C$6*($C$23)))-($C$25))/Model!$C$7)+Model!$C$7*EXP(-((((Model!$C$5*(($C$22)+Model!$C$6*($C$23)))-($C$25))/Model!$C$7)^2)/2)/SQRT(2*PI()))-(((Model!$C$5*(($C$22)+Model!$C$6*($C$23)))-($C$26))*NORMSDIST(((Model!$C$5*(($C$22)+Model!$C$6*($C$23)))-($C$26))/Model!$C$7)+Model!$C$7*EXP(-((((Model!$C$5*(($C$22)+Model!$C$6*($C$23)))-($C$26))/Model!$C$7)^2)/2)/SQRT(2*PI()))))) -> 911.5648 | O33: =$C$24+$C$20*((Model!$C$5*(($C33)+Model!$C$6*(H$29)))-(Model!$C$5*(($C$22)+Model!$C$6*($C$23)))-$C$21*(((((Model!$C$5*(($C33)+Model!$C$6*(H$29)))-($C$25))*NORMSDIST(((Model!$C$5*(($C33)+Model!$C$6*(H$29)))-($C$25))/Model!$C$7)+Model!$C$7*EXP(-((((Model!$C$5*(($C33)+Model!$C$6*(H$29)))-($C$25))/Model!$C$7)^2)/2)/SQRT(2*PI()))-(((Model!$C$5*(($C33)+Model!$C$6*(H$29)))-($C$26))*NORMSDIST(((Model!$C$5*(($C33)+Model!$C$6*(H$29)))-($C$26))/Model!$C$7)+Model!$C$7*EXP(-((((Model!$C$5*(($C33)+Model!$C$6*(H$29)))-($C$26))/Model!$C$7)^2)/2)/SQRT(2*PI())))-((((Model!$C$5*(($C$22)+Model!$C$6*($C$23)))-($C$25))*NORMSDIST(((Model!$C$5*(($C$22)+Model!$C$6*($C$23)))-($C$25))/Model!$C$7)+Model!$C$7*EXP(-((((Model!$C$5*(($C$22)+Model!$C$6*($C$23)))-($C$25))/Model!$C$7)^2)/2)/SQRT(2*PI()))-(((Model!$C$5*(($C$22)+Model!$C$6*($C$23)))-($C$26))*NORMSDIST(((Model!$C$5*(($C$22)+Model!$C$6*($C$23)))-($C$26))/Model!$C$7)+Model!$C$7*EXP(-((((Model!$C$5*(($C$22)+Model!$C$6*($C$23)))-($C$26))/Model!$C$7)^2)/2)/SQRT(2*PI()))))) -> 915.27242 | Q33: =C33 -> 96 | R33: =K33-D33 -> -0.0040760263 | S33: =L33-E33 -> -1.5616611 | T33: =M33-F33 -> -2.7014598 | U33: =N33-G33 -> -2.4352048 | V33: =O33-H33 -> -2.7275842
C34: 86 | D34: 887 | E34: 894 | F34: 902 | G34: 909 | H34: 914 | J34: =C34 -> 86 | K34: =$C$24+$C$20*((Model!$C$5*(($C34)+Model!$C$6*(D$29)))-(Model!$C$5*(($C$22)+Model!$C$6*($C$23)))-$C$21*(((((Model!$C$5*(($C34)+Model!$C$6*(D$29)))-($C$25))*NORMSDIST(((Model!$C$5*(($C34)+Model!$C$6*(D$29)))-($C$25))/Model!$C$7)+Model!$C$7*EXP(-((((Model!$C$5*(($C34)+Model!$C$6*(D$29)))-($C$25))/Model!$C$7)^2)/2)/SQRT(2*PI()))-(((Model!$C$5*(($C34)+Model!$C$6*(D$29)))-($C$26))*NORMSDIST(((Model!$C$5*(($C34)+Model!$C$6*(D$29)))-($C$26))/Model!$C$7)+Model!$C$7*EXP(-((((Model!$C$5*(($C34)+Model!$C$6*(D$29)))-($C$26))/Model!$C$7)^2)/2)/SQRT(2*PI())))-((((Model!$C$5*(($C$22)+Model!$C$6*($C$23)))-($C$25))*NORMSDIST(((Model!$C$5*(($C$22)+Model!$C$6*($C$23)))-($C$25))/Model!$C$7)+Model!$C$7*EXP(-((((Model!$C$5*(($C$22)+Model!$C$6*($C$23)))-($C$25))/Model!$C$7)^2)/2)/SQRT(2*PI()))-(((Model!$C$5*(($C$22)+Model!$C$6*($C$23)))-($C$26))*NORMSDIST(((Model!$C$5*(($C$22)+Model!$C$6*($C$23)))-($C$26))/Model!$C$7)+Model!$C$7*EXP(-((((Model!$C$5*(($C$22)+Model!$C$6*($C$23)))-($C$26))/Model!$C$7)^2)/2)/SQRT(2*PI()))))) -> 886.31117 | L34: =$C$24+$C$20*((Model!$C$5*(($C34)+Model!$C$6*(E$29)))-(Model!$C$5*(($C$22)+Model!$C$6*($C$23)))-$C$21*(((((Model!$C$5*(($C34)+Model!$C$6*(E$29)))-($C$25))*NORMSDIST(((Model!$C$5*(($C34)+Model!$C$6*(E$29)))-($C$25))/Model!$C$7)+Model!$C$7*EXP(-((((Model!$C$5*(($C34)+Model!$C$6*(E$29)))-($C$25))/Model!$C$7)^2)/2)/SQRT(2*PI()))-(((Model!$C$5*(($C34)+Model!$C$6*(E$29)))-($C$26))*NORMSDIST(((Model!$C$5*(($C34)+Model!$C$6*(E$29)))-($C$26))/Model!$C$7)+Model!$C$7*EXP(-((((Model!$C$5*(($C34)+Model!$C$6*(E$29)))-($C$26))/Model!$C$7)^2)/2)/SQRT(2*PI())))-((((Model!$C$5*(($C$22)+Model!$C$6*($C$23)))-($C$25))*NORMSDIST(((Model!$C$5*(($C$22)+Model!$C$6*($C$23)))-($C$25))/Model!$C$7)+Model!$C$7*EXP(-((((Model!$C$5*(($C$22)+Model!$C$6*($C$23)))-($C$25))/Model!$C$7)^2)/2)/SQRT(2*PI()))-(((Model!$C$5*(($C$22)+Model!$C$6*($C$23)))-($C$26))*NORMSDIST(((Model!$C$5*(($C$22)+Model!$C$6*($C$23)))-($C$26))/Model!$C$7)+Model!$C$7*EXP(-((((Model!$C$5*(($C$22)+Model!$C$6*($C$23)))-($C$26))/Model!$C$7)^2)/2)/SQRT(2*PI()))))) -> 892.62791 | M34: =$C$24+$C$20*((Model!$C$5*(($C34)+Model!$C$6*(F$29)))-(Model!$C$5*(($C$22)+Model!$C$6*($C$23)))-$C$21*(((((Model!$C$5*(($C34)+Model!$C$6*(F$29)))-($C$25))*NORMSDIST(((Model!$C$5*(($C34)+Model!$C$6*(F$29)))-($C$25))/Model!$C$7)+Model!$C$7*EXP(-((((Model!$C$5*(($C34)+Model!$C$6*(F$29)))-($C$25))/Model!$C$7)^2)/2)/SQRT(2*PI()))-(((Model!$C$5*(($C34)+Model!$C$6*(F$29)))-($C$26))*NORMSDIST(((Model!$C$5*(($C34)+Model!$C$6*(F$29)))-($C$26))/Model!$C$7)+Model!$C$7*EXP(-((((Model!$C$5*(($C34)+Model!$C$6*(F$29)))-($C$26))/Model!$C$7)^2)/2)/SQRT(2*PI())))-((((Model!$C$5*(($C$22)+Model!$C$6*($C$23)))-($C$25))*NORMSDIST(((Model!$C$5*(($C$22)+Model!$C$6*($C$23)))-($C$25))/Model!$C$7)+Model!$C$7*EXP(-((((Model!$C$5*(($C$22)+Model!$C$6*($C$23)))-($C$25))/Model!$C$7)^2)/2)/SQRT(2*PI()))-(((Model!$C$5*(($C$22)+Model!$C$6*($C$23)))-($C$26))*NORMSDIST(((Model!$C$5*(($C$22)+Model!$C$6*($C$23)))-($C$26))/Model!$C$7)+Model!$C$7*EXP(-((((Model!$C$5*(($C$22)+Model!$C$6*($C$23)))-($C$26))/Model!$C$7)^2)/2)/SQRT(2*PI()))))) -> 898.46954 | N34: =$C$24+$C$20*((Model!$C$5*(($C34)+Model!$C$6*(G$29)))-(Model!$C$5*(($C$22)+Model!$C$6*($C$23)))-$C$21*(((((Model!$C$5*(($C34)+Model!$C$6*(G$29)))-($C$25))*NORMSDIST(((Model!$C$5*(($C34)+Model!$C$6*(G$29)))-($C$25))/Model!$C$7)+Model!$C$7*EXP(-((((Model!$C$5*(($C34)+Model!$C$6*(G$29)))-($C$25))/Model!$C$7)^2)/2)/SQRT(2*PI()))-(((Model!$C$5*(($C34)+Model!$C$6*(G$29)))-($C$26))*NORMSDIST(((Model!$C$5*(($C34)+Model!$C$6*(G$29)))-($C$26))/Model!$C$7)+Model!$C$7*EXP(-((((Model!$C$5*(($C34)+Model!$C$6*(G$29)))-($C$26))/Model!$C$7)^2)/2)/SQRT(2*PI())))-((((Model!$C$5*(($C$22)+Model!$C$6*($C$23)))-($C$25))*NORMSDIST(((Model!$C$5*(($C$22)+Model!$C$6*($C$23)))-($C$25))/Model!$C$7)+Model!$C$7*EXP(-((((Model!$C$5*(($C$22)+Model!$C$6*($C$23)))-($C$25))/Model!$C$7)^2)/2)/SQRT(2*PI()))-(((Model!$C$5*(($C$22)+Model!$C$6*($C$23)))-($C$26))*NORMSDIST(((Model!$C$5*(($C$22)+Model!$C$6*($C$23)))-($C$26))/Model!$C$7)+Model!$C$7*EXP(-((((Model!$C$5*(($C$22)+Model!$C$6*($C$23)))-($C$26))/Model!$C$7)^2)/2)/SQRT(2*PI()))))) -> 903.7636 | O34: =$C$24+$C$20*((Model!$C$5*(($C34)+Model!$C$6*(H$29)))-(Model!$C$5*(($C$22)+Model!$C$6*($C$23)))-$C$21*(((((Model!$C$5*(($C34)+Model!$C$6*(H$29)))-($C$25))*NORMSDIST(((Model!$C$5*(($C34)+Model!$C$6*(H$29)))-($C$25))/Model!$C$7)+Model!$C$7*EXP(-((((Model!$C$5*(($C34)+Model!$C$6*(H$29)))-($C$25))/Model!$C$7)^2)/2)/SQRT(2*PI()))-(((Model!$C$5*(($C34)+Model!$C$6*(H$29)))-($C$26))*NORMSDIST(((Model!$C$5*(($C34)+Model!$C$6*(H$29)))-($C$26))/Model!$C$7)+Model!$C$7*EXP(-((((Model!$C$5*(($C34)+Model!$C$6*(H$29)))-($C$26))/Model!$C$7)^2)/2)/SQRT(2*PI())))-((((Model!$C$5*(($C$22)+Model!$C$6*($C$23)))-($C$25))*NORMSDIST(((Model!$C$5*(($C$22)+Model!$C$6*($C$23)))-($C$25))/Model!$C$7)+Model!$C$7*EXP(-((((Model!$C$5*(($C$22)+Model!$C$6*($C$23)))-($C$25))/Model!$C$7)^2)/2)/SQRT(2*PI()))-(((Model!$C$5*(($C$22)+Model!$C$6*($C$23)))-($C$26))*NORMSDIST(((Model!$C$5*(($C$22)+Model!$C$6*($C$23)))-($C$26))/Model!$C$7)+Model!$C$7*EXP(-((((Model!$C$5*(($C$22)+Model!$C$6*($C$23)))-($C$26))/Model!$C$7)^2)/2)/SQRT(2*PI()))))) -> 908.46817 | Q34: =C34 -> 86 | R34: =K34-D34 -> -0.68882524 | S34: =L34-E34 -> -1.3720922 | T34: =M34-F34 -> -3.5304564 | U34: =N34-G34 -> -5.2364005 | V34: =O34-H34 -> -5.5318298
C35: 76 | D35: 877 | E35: 882 | F35: 888 | G35: 896 | H35: 904 | J35: =C35 -> 76 | K35: =$C$24+$C$20*((Model!$C$5*(($C35)+Model!$C$6*(D$29)))-(Model!$C$5*(($C$22)+Model!$C$6*($C$23)))-$C$21*(((((Model!$C$5*(($C35)+Model!$C$6*(D$29)))-($C$25))*NORMSDIST(((Model!$C$5*(($C35)+Model!$C$6*(D$29)))-($C$25))/Model!$C$7)+Model!$C$7*EXP(-((((Model!$C$5*(($C35)+Model!$C$6*(D$29)))-($C$25))/Model!$C$7)^2)/2)/SQRT(2*PI()))-(((Model!$C$5*(($C35)+Model!$C$6*(D$29)))-($C$26))*NORMSDIST(((Model!$C$5*(($C35)+Model!$C$6*(D$29)))-($C$26))/Model!$C$7)+Model!$C$7*EXP(-((((Model!$C$5*(($C35)+Model!$C$6*(D$29)))-($C$26))/Model!$C$7)^2)/2)/SQRT(2*PI())))-((((Model!$C$5*(($C$22)+Model!$C$6*($C$23)))-($C$25))*NORMSDIST(((Model!$C$5*(($C$22)+Model!$C$6*($C$23)))-($C$25))/Model!$C$7)+Model!$C$7*EXP(-((((Model!$C$5*(($C$22)+Model!$C$6*($C$23)))-($C$25))/Model!$C$7)^2)/2)/SQRT(2*PI()))-(((Model!$C$5*(($C$22)+Model!$C$6*($C$23)))-($C$26))*NORMSDIST(((Model!$C$5*(($C$22)+Model!$C$6*($C$23)))-($C$26))/Model!$C$7)+Model!$C$7*EXP(-((((Model!$C$5*(($C$22)+Model!$C$6*($C$23)))-($C$26))/Model!$C$7)^2)/2)/SQRT(2*PI()))))) -> 874.45989 | L35: =$C$24+$C$20*((Model!$C$5*(($C35)+Model!$C$6*(E$29)))-(Model!$C$5*(($C$22)+Model!$C$6*($C$23)))-$C$21*(((((Model!$C$5*(($C35)+Model!$C$6*(E$29)))-($C$25))*NORMSDIST(((Model!$C$5*(($C35)+Model!$C$6*(E$29)))-($C$25))/Model!$C$7)+Model!$C$7*EXP(-((((Model!$C$5*(($C35)+Model!$C$6*(E$29)))-($C$25))/Model!$C$7)^2)/2)/SQRT(2*PI()))-(((Model!$C$5*(($C35)+Model!$C$6*(E$29)))-($C$26))*NORMSDIST(((Model!$C$5*(($C35)+Model!$C$6*(E$29)))-($C$26))/Model!$C$7)+Model!$C$7*EXP(-((((Model!$C$5*(($C35)+Model!$C$6*(E$29)))-($C$26))/Model!$C$7)^2)/2)/SQRT(2*PI())))-((((Model!$C$5*(($C$22)+Model!$C$6*($C$23)))-($C$25))*NORMSDIST(((Model!$C$5*(($C$22)+Model!$C$6*($C$23)))-($C$25))/Model!$C$7)+Model!$C$7*EXP(-((((Model!$C$5*(($C$22)+Model!$C$6*($C$23)))-($C$25))/Model!$C$7)^2)/2)/SQRT(2*PI()))-(((Model!$C$5*(($C$22)+Model!$C$6*($C$23)))-($C$26))*NORMSDIST(((Model!$C$5*(($C$22)+Model!$C$6*($C$23)))-($C$26))/Model!$C$7)+Model!$C$7*EXP(-((((Model!$C$5*(($C$22)+Model!$C$6*($C$23)))-($C$26))/Model!$C$7)^2)/2)/SQRT(2*PI()))))) -> 881.38891 | M35: =$C$24+$C$20*((Model!$C$5*(($C35)+Model!$C$6*(F$29)))-(Model!$C$5*(($C$22)+Model!$C$6*($C$23)))-$C$21*(((((Model!$C$5*(($C35)+Model!$C$6*(F$29)))-($C$25))*NORMSDIST(((Model!$C$5*(($C35)+Model!$C$6*(F$29)))-($C$25))/Model!$C$7)+Model!$C$7*EXP(-((((Model!$C$5*(($C35)+Model!$C$6*(F$29)))-($C$25))/Model!$C$7)^2)/2)/SQRT(2*PI()))-(((Model!$C$5*(($C35)+Model!$C$6*(F$29)))-($C$26))*NORMSDIST(((Model!$C$5*(($C35)+Model!$C$6*(F$29)))-($C$26))/Model!$C$7)+Model!$C$7*EXP(-((((Model!$C$5*(($C35)+Model!$C$6*(F$29)))-($C$26))/Model!$C$7)^2)/2)/SQRT(2*PI())))-((((Model!$C$5*(($C$22)+Model!$C$6*($C$23)))-($C$25))*NORMSDIST(((Model!$C$5*(($C$22)+Model!$C$6*($C$23)))-($C$25))/Model!$C$7)+Model!$C$7*EXP(-((((Model!$C$5*(($C$22)+Model!$C$6*($C$23)))-($C$25))/Model!$C$7)^2)/2)/SQRT(2*PI()))-(((Model!$C$5*(($C$22)+Model!$C$6*($C$23)))-($C$26))*NORMSDIST(((Model!$C$5*(($C$22)+Model!$C$6*($C$23)))-($C$26))/Model!$C$7)+Model!$C$7*EXP(-((((Model!$C$5*(($C$22)+Model!$C$6*($C$23)))-($C$26))/Model!$C$7)^2)/2)/SQRT(2*PI()))))) -> 888 | N35: =$C$24+$C$20*((Model!$C$5*(($C35)+Model!$C$6*(G$29)))-(Model!$C$5*(($C$22)+Model!$C$6*($C$23)))-$C$21*(((((Model!$C$5*(($C35)+Model!$C$6*(G$29)))-($C$25))*NORMSDIST(((Model!$C$5*(($C35)+Model!$C$6*(G$29)))-($C$25))/Model!$C$7)+Model!$C$7*EXP(-((((Model!$C$5*(($C35)+Model!$C$6*(G$29)))-($C$25))/Model!$C$7)^2)/2)/SQRT(2*PI()))-(((Model!$C$5*(($C35)+Model!$C$6*(G$29)))-($C$26))*NORMSDIST(((Model!$C$5*(($C35)+Model!$C$6*(G$29)))-($C$26))/Model!$C$7)+Model!$C$7*EXP(-((((Model!$C$5*(($C35)+Model!$C$6*(G$29)))-($C$26))/Model!$C$7)^2)/2)/SQRT(2*PI())))-((((Model!$C$5*(($C$22)+Model!$C$6*($C$23)))-($C$25))*NORMSDIST(((Model!$C$5*(($C$22)+Model!$C$6*($C$23)))-($C$25))/Model!$C$7)+Model!$C$7*EXP(-((((Model!$C$5*(($C$22)+Model!$C$6*($C$23)))-($C$25))/Model!$C$7)^2)/2)/SQRT(2*PI()))-(((Model!$C$5*(($C$22)+Model!$C$6*($C$23)))-($C$26))*NORMSDIST(((Model!$C$5*(($C$22)+Model!$C$6*($C$23)))-($C$26))/Model!$C$7)+Model!$C$7*EXP(-((((Model!$C$5*(($C$22)+Model!$C$6*($C$23)))-($C$26))/Model!$C$7)^2)/2)/SQRT(2*PI()))))) -> 894.20096 | O35: =$C$24+$C$20*((Model!$C$5*(($C35)+Model!$C$6*(H$29)))-(Model!$C$5*(($C$22)+Model!$C$6*($C$23)))-$C$21*(((((Model!$C$5*(($C35)+Model!$C$6*(H$29)))-($C$25))*NORMSDIST(((Model!$C$5*(($C35)+Model!$C$6*(H$29)))-($C$25))/Model!$C$7)+Model!$C$7*EXP(-((((Model!$C$5*(($C35)+Model!$C$6*(H$29)))-($C$25))/Model!$C$7)^2)/2)/SQRT(2*PI()))-(((Model!$C$5*(($C35)+Model!$C$6*(H$29)))-($C$26))*NORMSDIST(((Model!$C$5*(($C35)+Model!$C$6*(H$29)))-($C$26))/Model!$C$7)+Model!$C$7*EXP(-((((Model!$C$5*(($C35)+Model!$C$6*(H$29)))-($C$26))/Model!$C$7)^2)/2)/SQRT(2*PI())))-((((Model!$C$5*(($C$22)+Model!$C$6*($C$23)))-($C$25))*NORMSDIST(((Model!$C$5*(($C$22)+Model!$C$6*($C$23)))-($C$25))/Model!$C$7)+Model!$C$7*EXP(-((((Model!$C$5*(($C$22)+Model!$C$6*($C$23)))-($C$25))/Model!$C$7)^2)/2)/SQRT(2*PI()))-(((Model!$C$5*(($C$22)+Model!$C$6*($C$23)))-($C$26))*NORMSDIST(((Model!$C$5*(($C$22)+Model!$C$6*($C$23)))-($C$26))/Model!$C$7)+Model!$C$7*EXP(-((((Model!$C$5*(($C$22)+Model!$C$6*($C$23)))-($C$26))/Model!$C$7)^2)/2)/SQRT(2*PI()))))) -> 899.90574 | Q35: =C35 -> 76 | R35: =K35-D35 -> -2.5401101 | S35: =L35-E35 -> -0.61108615 | T35: =M35-F35 -> 0 | U35: =N35-G35 -> -1.7990404 | V35: =O35-H35 -> -4.0942648
C36: 66 | D36: 862 | E36: 870 | F36: 876 | G36: 881 | H36: 888 | J36: =C36 -> 66 | K36: =$C$24+$C$20*((Model!$C$5*(($C36)+Model!$C$6*(D$29)))-(Model!$C$5*(($C$22)+Model!$C$6*($C$23)))-$C$21*(((((Model!$C$5*(($C36)+Model!$C$6*(D$29)))-($C$25))*NORMSDIST(((Model!$C$5*(($C36)+Model!$C$6*(D$29)))-($C$25))/Model!$C$7)+Model!$C$7*EXP(-((((Model!$C$5*(($C36)+Model!$C$6*(D$29)))-($C$25))/Model!$C$7)^2)/2)/SQRT(2*PI()))-(((Model!$C$5*(($C36)+Model!$C$6*(D$29)))-($C$26))*NORMSDIST(((Model!$C$5*(($C36)+Model!$C$6*(D$29)))-($C$26))/Model!$C$7)+Model!$C$7*EXP(-((((Model!$C$5*(($C36)+Model!$C$6*(D$29)))-($C$26))/Model!$C$7)^2)/2)/SQRT(2*PI())))-((((Model!$C$5*(($C$22)+Model!$C$6*($C$23)))-($C$25))*NORMSDIST(((Model!$C$5*(($C$22)+Model!$C$6*($C$23)))-($C$25))/Model!$C$7)+Model!$C$7*EXP(-((((Model!$C$5*(($C$22)+Model!$C$6*($C$23)))-($C$25))/Model!$C$7)^2)/2)/SQRT(2*PI()))-(((Model!$C$5*(($C$22)+Model!$C$6*($C$23)))-($C$26))*NORMSDIST(((Model!$C$5*(($C$22)+Model!$C$6*($C$23)))-($C$26))/Model!$C$7)+Model!$C$7*EXP(-((((Model!$C$5*(($C$22)+Model!$C$6*($C$23)))-($C$26))/Model!$C$7)^2)/2)/SQRT(2*PI()))))) -> 861.90188 | L36: =$C$24+$C$20*((Model!$C$5*(($C36)+Model!$C$6*(E$29)))-(Model!$C$5*(($C$22)+Model!$C$6*($C$23)))-$C$21*(((((Model!$C$5*(($C36)+Model!$C$6*(E$29)))-($C$25))*NORMSDIST(((Model!$C$5*(($C36)+Model!$C$6*(E$29)))-($C$25))/Model!$C$7)+Model!$C$7*EXP(-((((Model!$C$5*(($C36)+Model!$C$6*(E$29)))-($C$25))/Model!$C$7)^2)/2)/SQRT(2*PI()))-(((Model!$C$5*(($C36)+Model!$C$6*(E$29)))-($C$26))*NORMSDIST(((Model!$C$5*(($C36)+Model!$C$6*(E$29)))-($C$26))/Model!$C$7)+Model!$C$7*EXP(-((((Model!$C$5*(($C36)+Model!$C$6*(E$29)))-($C$26))/Model!$C$7)^2)/2)/SQRT(2*PI())))-((((Model!$C$5*(($C$22)+Model!$C$6*($C$23)))-($C$25))*NORMSDIST(((Model!$C$5*(($C$22)+Model!$C$6*($C$23)))-($C$25))/Model!$C$7)+Model!$C$7*EXP(-((((Model!$C$5*(($C$22)+Model!$C$6*($C$23)))-($C$25))/Model!$C$7)^2)/2)/SQRT(2*PI()))-(((Model!$C$5*(($C$22)+Model!$C$6*($C$23)))-($C$26))*NORMSDIST(((Model!$C$5*(($C$22)+Model!$C$6*($C$23)))-($C$26))/Model!$C$7)+Model!$C$7*EXP(-((((Model!$C$5*(($C$22)+Model!$C$6*($C$23)))-($C$26))/Model!$C$7)^2)/2)/SQRT(2*PI()))))) -> 869.18535 | M36: =$C$24+$C$20*((Model!$C$5*(($C36)+Model!$C$6*(F$29)))-(Model!$C$5*(($C$22)+Model!$C$6*($C$23)))-$C$21*(((((Model!$C$5*(($C36)+Model!$C$6*(F$29)))-($C$25))*NORMSDIST(((Model!$C$5*(($C36)+Model!$C$6*(F$29)))-($C$25))/Model!$C$7)+Model!$C$7*EXP(-((((Model!$C$5*(($C36)+Model!$C$6*(F$29)))-($C$25))/Model!$C$7)^2)/2)/SQRT(2*PI()))-(((Model!$C$5*(($C36)+Model!$C$6*(F$29)))-($C$26))*NORMSDIST(((Model!$C$5*(($C36)+Model!$C$6*(F$29)))-($C$26))/Model!$C$7)+Model!$C$7*EXP(-((((Model!$C$5*(($C36)+Model!$C$6*(F$29)))-($C$26))/Model!$C$7)^2)/2)/SQRT(2*PI())))-((((Model!$C$5*(($C$22)+Model!$C$6*($C$23)))-($C$25))*NORMSDIST(((Model!$C$5*(($C$22)+Model!$C$6*($C$23)))-($C$25))/Model!$C$7)+Model!$C$7*EXP(-((((Model!$C$5*(($C$22)+Model!$C$6*($C$23)))-($C$25))/Model!$C$7)^2)/2)/SQRT(2*PI()))-(((Model!$C$5*(($C$22)+Model!$C$6*($C$23)))-($C$26))*NORMSDIST(((Model!$C$5*(($C$22)+Model!$C$6*($C$23)))-($C$26))/Model!$C$7)+Model!$C$7*EXP(-((((Model!$C$5*(($C$22)+Model!$C$6*($C$23)))-($C$26))/Model!$C$7)^2)/2)/SQRT(2*PI()))))) -> 876.29309 | N36: =$C$24+$C$20*((Model!$C$5*(($C36)+Model!$C$6*(G$29)))-(Model!$C$5*(($C$22)+Model!$C$6*($C$23)))-$C$21*(((((Model!$C$5*(($C36)+Model!$C$6*(G$29)))-($C$25))*NORMSDIST(((Model!$C$5*(($C36)+Model!$C$6*(G$29)))-($C$25))/Model!$C$7)+Model!$C$7*EXP(-((((Model!$C$5*(($C36)+Model!$C$6*(G$29)))-($C$25))/Model!$C$7)^2)/2)/SQRT(2*PI()))-(((Model!$C$5*(($C36)+Model!$C$6*(G$29)))-($C$26))*NORMSDIST(((Model!$C$5*(($C36)+Model!$C$6*(G$29)))-($C$26))/Model!$C$7)+Model!$C$7*EXP(-((((Model!$C$5*(($C36)+Model!$C$6*(G$29)))-($C$26))/Model!$C$7)^2)/2)/SQRT(2*PI())))-((((Model!$C$5*(($C$22)+Model!$C$6*($C$23)))-($C$25))*NORMSDIST(((Model!$C$5*(($C$22)+Model!$C$6*($C$23)))-($C$25))/Model!$C$7)+Model!$C$7*EXP(-((((Model!$C$5*(($C$22)+Model!$C$6*($C$23)))-($C$25))/Model!$C$7)^2)/2)/SQRT(2*PI()))-(((Model!$C$5*(($C$22)+Model!$C$6*($C$23)))-($C$26))*NORMSDIST(((Model!$C$5*(($C$22)+Model!$C$6*($C$23)))-($C$26))/Model!$C$7)+Model!$C$7*EXP(-((((Model!$C$5*(($C$22)+Model!$C$6*($C$23)))-($C$26))/Model!$C$7)^2)/2)/SQRT(2*PI()))))) -> 883.14791 | O36: =$C$24+$C$20*((Model!$C$5*(($C36)+Model!$C$6*(H$29)))-(Model!$C$5*(($C$22)+Model!$C$6*($C$23)))-$C$21*(((((Model!$C$5*(($C36)+Model!$C$6*(H$29)))-($C$25))*NORMSDIST(((Model!$C$5*(($C36)+Model!$C$6*(H$29)))-($C$25))/Model!$C$7)+Model!$C$7*EXP(-((((Model!$C$5*(($C36)+Model!$C$6*(H$29)))-($C$25))/Model!$C$7)^2)/2)/SQRT(2*PI()))-(((Model!$C$5*(($C36)+Model!$C$6*(H$29)))-($C$26))*NORMSDIST(((Model!$C$5*(($C36)+Model!$C$6*(H$29)))-($C$26))/Model!$C$7)+Model!$C$7*EXP(-((((Model!$C$5*(($C36)+Model!$C$6*(H$29)))-($C$26))/Model!$C$7)^2)/2)/SQRT(2*PI())))-((((Model!$C$5*(($C$22)+Model!$C$6*($C$23)))-($C$25))*NORMSDIST(((Model!$C$5*(($C$22)+Model!$C$6*($C$23)))-($C$25))/Model!$C$7)+Model!$C$7*EXP(-((((Model!$C$5*(($C$22)+Model!$C$6*($C$23)))-($C$25))/Model!$C$7)^2)/2)/SQRT(2*PI()))-(((Model!$C$5*(($C$22)+Model!$C$6*($C$23)))-($C$26))*NORMSDIST(((Model!$C$5*(($C$22)+Model!$C$6*($C$23)))-($C$26))/Model!$C$7)+Model!$C$7*EXP(-((((Model!$C$5*(($C$22)+Model!$C$6*($C$23)))-($C$26))/Model!$C$7)^2)/2)/SQRT(2*PI()))))) -> 889.66088 | Q36: =C36 -> 66 | R36: =K36-D36 -> -0.098118577 | S36: =L36-E36 -> -0.81465286 | T36: =M36-F36 -> 0.29308577 | U36: =N36-G36 -> 2.1479138 | V36: =O36-H36 -> 1.6608843
C37: 56 | D37: 848 | E37: 858 | F37: 867 | G37: 874 | H37: 879 | J37: =C37 -> 56 | K37: =$C$24+$C$20*((Model!$C$5*(($C37)+Model!$C$6*(D$29)))-(Model!$C$5*(($C$22)+Model!$C$6*($C$23)))-$C$21*(((((Model!$C$5*(($C37)+Model!$C$6*(D$29)))-($C$25))*NORMSDIST(((Model!$C$5*(($C37)+Model!$C$6*(D$29)))-($C$25))/Model!$C$7)+Model!$C$7*EXP(-((((Model!$C$5*(($C37)+Model!$C$6*(D$29)))-($C$25))/Model!$C$7)^2)/2)/SQRT(2*PI()))-(((Model!$C$5*(($C37)+Model!$C$6*(D$29)))-($C$26))*NORMSDIST(((Model!$C$5*(($C37)+Model!$C$6*(D$29)))-($C$26))/Model!$C$7)+Model!$C$7*EXP(-((((Model!$C$5*(($C37)+Model!$C$6*(D$29)))-($C$26))/Model!$C$7)^2)/2)/SQRT(2*PI())))-((((Model!$C$5*(($C$22)+Model!$C$6*($C$23)))-($C$25))*NORMSDIST(((Model!$C$5*(($C$22)+Model!$C$6*($C$23)))-($C$25))/Model!$C$7)+Model!$C$7*EXP(-((((Model!$C$5*(($C$22)+Model!$C$6*($C$23)))-($C$25))/Model!$C$7)^2)/2)/SQRT(2*PI()))-(((Model!$C$5*(($C$22)+Model!$C$6*($C$23)))-($C$26))*NORMSDIST(((Model!$C$5*(($C$22)+Model!$C$6*($C$23)))-($C$26))/Model!$C$7)+Model!$C$7*EXP(-((((Model!$C$5*(($C$22)+Model!$C$6*($C$23)))-($C$26))/Model!$C$7)^2)/2)/SQRT(2*PI()))))) -> 848.98837 | L37: =$C$24+$C$20*((Model!$C$5*(($C37)+Model!$C$6*(E$29)))-(Model!$C$5*(($C$22)+Model!$C$6*($C$23)))-$C$21*(((((Model!$C$5*(($C37)+Model!$C$6*(E$29)))-($C$25))*NORMSDIST(((Model!$C$5*(($C37)+Model!$C$6*(E$29)))-($C$25))/Model!$C$7)+Model!$C$7*EXP(-((((Model!$C$5*(($C37)+Model!$C$6*(E$29)))-($C$25))/Model!$C$7)^2)/2)/SQRT(2*PI()))-(((Model!$C$5*(($C37)+Model!$C$6*(E$29)))-($C$26))*NORMSDIST(((Model!$C$5*(($C37)+Model!$C$6*(E$29)))-($C$26))/Model!$C$7)+Model!$C$7*EXP(-((((Model!$C$5*(($C37)+Model!$C$6*(E$29)))-($C$26))/Model!$C$7)^2)/2)/SQRT(2*PI())))-((((Model!$C$5*(($C$22)+Model!$C$6*($C$23)))-($C$25))*NORMSDIST(((Model!$C$5*(($C$22)+Model!$C$6*($C$23)))-($C$25))/Model!$C$7)+Model!$C$7*EXP(-((((Model!$C$5*(($C$22)+Model!$C$6*($C$23)))-($C$25))/Model!$C$7)^2)/2)/SQRT(2*PI()))-(((Model!$C$5*(($C$22)+Model!$C$6*($C$23)))-($C$26))*NORMSDIST(((Model!$C$5*(($C$22)+Model!$C$6*($C$23)))-($C$26))/Model!$C$7)+Model!$C$7*EXP(-((((Model!$C$5*(($C$22)+Model!$C$6*($C$23)))-($C$26))/Model!$C$7)^2)/2)/SQRT(2*PI()))))) -> 856.44196 | M37: =$C$24+$C$20*((Model!$C$5*(($C37)+Model!$C$6*(F$29)))-(Model!$C$5*(($C$22)+Model!$C$6*($C$23)))-$C$21*(((((Model!$C$5*(($C37)+Model!$C$6*(F$29)))-($C$25))*NORMSDIST(((Model!$C$5*(($C37)+Model!$C$6*(F$29)))-($C$25))/Model!$C$7)+Model!$C$7*EXP(-((((Model!$C$5*(($C37)+Model!$C$6*(F$29)))-($C$25))/Model!$C$7)^2)/2)/SQRT(2*PI()))-(((Model!$C$5*(($C37)+Model!$C$6*(F$29)))-($C$26))*NORMSDIST(((Model!$C$5*(($C37)+Model!$C$6*(F$29)))-($C$26))/Model!$C$7)+Model!$C$7*EXP(-((((Model!$C$5*(($C37)+Model!$C$6*(F$29)))-($C$26))/Model!$C$7)^2)/2)/SQRT(2*PI())))-((((Model!$C$5*(($C$22)+Model!$C$6*($C$23)))-($C$25))*NORMSDIST(((Model!$C$5*(($C$22)+Model!$C$6*($C$23)))-($C$25))/Model!$C$7)+Model!$C$7*EXP(-((((Model!$C$5*(($C$22)+Model!$C$6*($C$23)))-($C$25))/Model!$C$7)^2)/2)/SQRT(2*PI()))-(((Model!$C$5*(($C$22)+Model!$C$6*($C$23)))-($C$26))*NORMSDIST(((Model!$C$5*(($C$22)+Model!$C$6*($C$23)))-($C$26))/Model!$C$7)+Model!$C$7*EXP(-((((Model!$C$5*(($C$22)+Model!$C$6*($C$23)))-($C$26))/Model!$C$7)^2)/2)/SQRT(2*PI()))))) -> 863.81515 | N37: =$C$24+$C$20*((Model!$C$5*(($C37)+Model!$C$6*(G$29)))-(Model!$C$5*(($C$22)+Model!$C$6*($C$23)))-$C$21*(((((Model!$C$5*(($C37)+Model!$C$6*(G$29)))-($C$25))*NORMSDIST(((Model!$C$5*(($C37)+Model!$C$6*(G$29)))-($C$25))/Model!$C$7)+Model!$C$7*EXP(-((((Model!$C$5*(($C37)+Model!$C$6*(G$29)))-($C$25))/Model!$C$7)^2)/2)/SQRT(2*PI()))-(((Model!$C$5*(($C37)+Model!$C$6*(G$29)))-($C$26))*NORMSDIST(((Model!$C$5*(($C37)+Model!$C$6*(G$29)))-($C$26))/Model!$C$7)+Model!$C$7*EXP(-((((Model!$C$5*(($C37)+Model!$C$6*(G$29)))-($C$26))/Model!$C$7)^2)/2)/SQRT(2*PI())))-((((Model!$C$5*(($C$22)+Model!$C$6*($C$23)))-($C$25))*NORMSDIST(((Model!$C$5*(($C$22)+Model!$C$6*($C$23)))-($C$25))/Model!$C$7)+Model!$C$7*EXP(-((((Model!$C$5*(($C$22)+Model!$C$6*($C$23)))-($C$25))/Model!$C$7)^2)/2)/SQRT(2*PI()))-(((Model!$C$5*(($C$22)+Model!$C$6*($C$23)))-($C$26))*NORMSDIST(((Model!$C$5*(($C$22)+Model!$C$6*($C$23)))-($C$26))/Model!$C$7)+Model!$C$7*EXP(-((((Model!$C$5*(($C$22)+Model!$C$6*($C$23)))-($C$26))/Model!$C$7)^2)/2)/SQRT(2*PI()))))) -> 871.05934 | O37: =$C$24+$C$20*((Model!$C$5*(($C37)+Model!$C$6*(H$29)))-(Model!$C$5*(($C$22)+Model!$C$6*($C$23)))-$C$21*(((((Model!$C$5*(($C37)+Model!$C$6*(H$29)))-($C$25))*NORMSDIST(((Model!$C$5*(($C37)+Model!$C$6*(H$29)))-($C$25))/Model!$C$7)+Model!$C$7*EXP(-((((Model!$C$5*(($C37)+Model!$C$6*(H$29)))-($C$25))/Model!$C$7)^2)/2)/SQRT(2*PI()))-(((Model!$C$5*(($C37)+Model!$C$6*(H$29)))-($C$26))*NORMSDIST(((Model!$C$5*(($C37)+Model!$C$6*(H$29)))-($C$26))/Model!$C$7)+Model!$C$7*EXP(-((((Model!$C$5*(($C37)+Model!$C$6*(H$29)))-($C$26))/Model!$C$7)^2)/2)/SQRT(2*PI())))-((((Model!$C$5*(($C$22)+Model!$C$6*($C$23)))-($C$25))*NORMSDIST(((Model!$C$5*(($C$22)+Model!$C$6*($C$23)))-($C$25))/Model!$C$7)+Model!$C$7*EXP(-((((Model!$C$5*(($C$22)+Model!$C$6*($C$23)))-($C$25))/Model!$C$7)^2)/2)/SQRT(2*PI()))-(((Model!$C$5*(($C$22)+Model!$C$6*($C$23)))-($C$26))*NORMSDIST(((Model!$C$5*(($C$22)+Model!$C$6*($C$23)))-($C$26))/Model!$C$7)+Model!$C$7*EXP(-((((Model!$C$5*(($C$22)+Model!$C$6*($C$23)))-($C$26))/Model!$C$7)^2)/2)/SQRT(2*PI()))))) -> 878.10914 | Q37: =C37 -> 56 | R37: =K37-D37 -> 0.98837279 | S37: =L37-E37 -> -1.5580352 | T37: =M37-F37 -> -3.1848543 | U37: =N37-G37 -> -2.9406569 | V37: =O37-H37 -> -0.8908643
C38: 46 | D38: 829 | E38: 839 | F38: 849 | G38: 858 | H38: 867 | J38: =C38 -> 46 | K38: =$C$24+$C$20*((Model!$C$5*(($C38)+Model!$C$6*(D$29)))-(Model!$C$5*(($C$22)+Model!$C$6*($C$23)))-$C$21*(((((Model!$C$5*(($C38)+Model!$C$6*(D$29)))-($C$25))*NORMSDIST(((Model!$C$5*(($C38)+Model!$C$6*(D$29)))-($C$25))/Model!$C$7)+Model!$C$7*EXP(-((((Model!$C$5*(($C38)+Model!$C$6*(D$29)))-($C$25))/Model!$C$7)^2)/2)/SQRT(2*PI()))-(((Model!$C$5*(($C38)+Model!$C$6*(D$29)))-($C$26))*NORMSDIST(((Model!$C$5*(($C38)+Model!$C$6*(D$29)))-($C$26))/Model!$C$7)+Model!$C$7*EXP(-((((Model!$C$5*(($C38)+Model!$C$6*(D$29)))-($C$26))/Model!$C$7)^2)/2)/SQRT(2*PI())))-((((Model!$C$5*(($C$22)+Model!$C$6*($C$23)))-($C$25))*NORMSDIST(((Model!$C$5*(($C$22)+Model!$C$6*($C$23)))-($C$25))/Model!$C$7)+Model!$C$7*EXP(-((((Model!$C$5*(($C$22)+Model!$C$6*($C$23)))-($C$25))/Model!$C$7)^2)/2)/SQRT(2*PI()))-(((Model!$C$5*(($C$22)+Model!$C$6*($C$23)))-($C$26))*NORMSDIST(((Model!$C$5*(($C$22)+Model!$C$6*($C$23)))-($C$26))/Model!$C$7)+Model!$C$7*EXP(-((((Model!$C$5*(($C$22)+Model!$C$6*($C$23)))-($C$26))/Model!$C$7)^2)/2)/SQRT(2*PI()))))) -> 835.92619 | L38: =$C$24+$C$20*((Model!$C$5*(($C38)+Model!$C$6*(E$29)))-(Model!$C$5*(($C$22)+Model!$C$6*($C$23)))-$C$21*(((((Model!$C$5*(($C38)+Model!$C$6*(E$29)))-($C$25))*NORMSDIST(((Model!$C$5*(($C38)+Model!$C$6*(E$29)))-($C$25))/Model!$C$7)+Model!$C$7*EXP(-((((Model!$C$5*(($C38)+Model!$C$6*(E$29)))-($C$25))/Model!$C$7)^2)/2)/SQRT(2*PI()))-(((Model!$C$5*(($C38)+Model!$C$6*(E$29)))-($C$26))*NORMSDIST(((Model!$C$5*(($C38)+Model!$C$6*(E$29)))-($C$26))/Model!$C$7)+Model!$C$7*EXP(-((((Model!$C$5*(($C38)+Model!$C$6*(E$29)))-($C$26))/Model!$C$7)^2)/2)/SQRT(2*PI())))-((((Model!$C$5*(($C$22)+Model!$C$6*($C$23)))-($C$25))*NORMSDIST(((Model!$C$5*(($C$22)+Model!$C$6*($C$23)))-($C$25))/Model!$C$7)+Model!$C$7*EXP(-((((Model!$C$5*(($C$22)+Model!$C$6*($C$23)))-($C$25))/Model!$C$7)^2)/2)/SQRT(2*PI()))-(((Model!$C$5*(($C$22)+Model!$C$6*($C$23)))-($C$26))*NORMSDIST(((Model!$C$5*(($C$22)+Model!$C$6*($C$23)))-($C$26))/Model!$C$7)+Model!$C$7*EXP(-((((Model!$C$5*(($C$22)+Model!$C$6*($C$23)))-($C$26))/Model!$C$7)^2)/2)/SQRT(2*PI()))))) -> 843.44756 | M38: =$C$24+$C$20*((Model!$C$5*(($C38)+Model!$C$6*(F$29)))-(Model!$C$5*(($C$22)+Model!$C$6*($C$23)))-$C$21*(((((Model!$C$5*(($C38)+Model!$C$6*(F$29)))-($C$25))*NORMSDIST(((Model!$C$5*(($C38)+Model!$C$6*(F$29)))-($C$25))/Model!$C$7)+Model!$C$7*EXP(-((((Model!$C$5*(($C38)+Model!$C$6*(F$29)))-($C$25))/Model!$C$7)^2)/2)/SQRT(2*PI()))-(((Model!$C$5*(($C38)+Model!$C$6*(F$29)))-($C$26))*NORMSDIST(((Model!$C$5*(($C38)+Model!$C$6*(F$29)))-($C$26))/Model!$C$7)+Model!$C$7*EXP(-((((Model!$C$5*(($C38)+Model!$C$6*(F$29)))-($C$26))/Model!$C$7)^2)/2)/SQRT(2*PI())))-((((Model!$C$5*(($C$22)+Model!$C$6*($C$23)))-($C$25))*NORMSDIST(((Model!$C$5*(($C$22)+Model!$C$6*($C$23)))-($C$25))/Model!$C$7)+Model!$C$7*EXP(-((((Model!$C$5*(($C$22)+Model!$C$6*($C$23)))-($C$25))/Model!$C$7)^2)/2)/SQRT(2*PI()))-(((Model!$C$5*(($C$22)+Model!$C$6*($C$23)))-($C$26))*NORMSDIST(((Model!$C$5*(($C$22)+Model!$C$6*($C$23)))-($C$26))/Model!$C$7)+Model!$C$7*EXP(-((((Model!$C$5*(($C$22)+Model!$C$6*($C$23)))-($C$26))/Model!$C$7)^2)/2)/SQRT(2*PI()))))) -> 850.93844 | N38: =$C$24+$C$20*((Model!$C$5*(($C38)+Model!$C$6*(G$29)))-(Model!$C$5*(($C$22)+Model!$C$6*($C$23)))-$C$21*(((((Model!$C$5*(($C38)+Model!$C$6*(G$29)))-($C$25))*NORMSDIST(((Model!$C$5*(($C38)+Model!$C$6*(G$29)))-($C$25))/Model!$C$7)+Model!$C$7*EXP(-((((Model!$C$5*(($C38)+Model!$C$6*(G$29)))-($C$25))/Model!$C$7)^2)/2)/SQRT(2*PI()))-(((Model!$C$5*(($C38)+Model!$C$6*(G$29)))-($C$26))*NORMSDIST(((Model!$C$5*(($C38)+Model!$C$6*(G$29)))-($C$26))/Model!$C$7)+Model!$C$7*EXP(-((((Model!$C$5*(($C38)+Model!$C$6*(G$29)))-($C$26))/Model!$C$7)^2)/2)/SQRT(2*PI())))-((((Model!$C$5*(($C$22)+Model!$C$6*($C$23)))-($C$25))*NORMSDIST(((Model!$C$5*(($C$22)+Model!$C$6*($C$23)))-($C$25))/Model!$C$7)+Model!$C$7*EXP(-((((Model!$C$5*(($C$22)+Model!$C$6*($C$23)))-($C$25))/Model!$C$7)^2)/2)/SQRT(2*PI()))-(((Model!$C$5*(($C$22)+Model!$C$6*($C$23)))-($C$26))*NORMSDIST(((Model!$C$5*(($C$22)+Model!$C$6*($C$23)))-($C$26))/Model!$C$7)+Model!$C$7*EXP(-((((Model!$C$5*(($C$22)+Model!$C$6*($C$23)))-($C$26))/Model!$C$7)^2)/2)/SQRT(2*PI()))))) -> 858.37483 | O38: =$C$24+$C$20*((Model!$C$5*(($C38)+Model!$C$6*(H$29)))-(Model!$C$5*(($C$22)+Model!$C$6*($C$23)))-$C$21*(((((Model!$C$5*(($C38)+Model!$C$6*(H$29)))-($C$25))*NORMSDIST(((Model!$C$5*(($C38)+Model!$C$6*(H$29)))-($C$25))/Model!$C$7)+Model!$C$7*EXP(-((((Model!$C$5*(($C38)+Model!$C$6*(H$29)))-($C$25))/Model!$C$7)^2)/2)/SQRT(2*PI()))-(((Model!$C$5*(($C38)+Model!$C$6*(H$29)))-($C$26))*NORMSDIST(((Model!$C$5*(($C38)+Model!$C$6*(H$29)))-($C$26))/Model!$C$7)+Model!$C$7*EXP(-((((Model!$C$5*(($C38)+Model!$C$6*(H$29)))-($C$26))/Model!$C$7)^2)/2)/SQRT(2*PI())))-((((Model!$C$5*(($C$22)+Model!$C$6*($C$23)))-($C$25))*NORMSDIST(((Model!$C$5*(($C$22)+Model!$C$6*($C$23)))-($C$25))/Model!$C$7)+Model!$C$7*EXP(-((((Model!$C$5*(($C$22)+Model!$C$6*($C$23)))-($C$25))/Model!$C$7)^2)/2)/SQRT(2*PI()))-(((Model!$C$5*(($C$22)+Model!$C$6*($C$23)))-($C$26))*NORMSDIST(((Model!$C$5*(($C$22)+Model!$C$6*($C$23)))-($C$26))/Model!$C$7)+Model!$C$7*EXP(-((((Model!$C$5*(($C$22)+Model!$C$6*($C$23)))-($C$26))/Model!$C$7)^2)/2)/SQRT(2*PI()))))) -> 865.71972 | Q38: =C38 -> 46 | R38: =K38-D38 -> 6.9261855 | S38: =L38-E38 -> 4.4475555 | T38: =M38-F38 -> 1.9384375 | U38: =N38-G38 -> 0.37483401 | V38: =O38-H38 -> -1.2802766
B39: Naive model SSE | C39: =($C$24+$C$20*(1-$C$21)*Model!$C$5*((C30-$C$22)+(D29-$C$23))-D30)^2+($C$24+$C$20*(1-$C$21)*Model!$C$5*((C30-$C$22)+(E29-$C$23))-E30)^2+($C$24+$C$20*(1-$C$21)*Model!$C$5*((C30-$C$22)+(F29-$C$23))-F30)^2+($C$24+$C$20*(1-$C$21)*Model!$C$5*((C30-$C$22)+(G29-$C$23))-G30)^2+($C$24+$C$20*(1-$C$21)*Model!$C$5*((C30-$C$22)+(H29-$C$23))-H30)^2+($C$24+$C$20*(1-$C$21)*Model!$C$5*((C31-$C$22)+(D29-$C$23))-D31)^2+($C$24+$C$20*(1-$C$21)*Model!$C$5*((C31-$C$22)+(E29-$C$23))-E31)^2+($C$24+$C$20*(1-$C$21)*Model!$C$5*((C31-$C$22)+(F29-$C$23))-F31)^2+($C$24+$C$20*(1-$C$21)*Model!$C$5*((C31-$C$22)+(G29-$C$23))-G31)^2+($C$24+$C$20*(1-$C$21)*Model!$C$5*((C31-$C$22)+(H29-$C$23))-H31)^2+($C$24+$C$20*(1-$C$21)*Model!$C$5*((C32-$C$22)+(D29-$C$23))-D32)^2+($C$24+$C$20*(1-$C$21)*Model!$C$5*((C32-$C$22)+(E29-$C$23))-E32)^2+($C$24+$C$20*(1-$C$21)*Model!$C$5*((C32-$C$22)+(F29-$C$23))-F32)^2+($C$24+$C$20*(1-$C$21)*Model!$C$5*((C32-$C$22)+(G29-$C$23))-G32)^2+($C$24+$C$20*(1-$C$21)*Model!$C$5*((C32-$C$22)+(H29-$C$23))-H32)^2+($C$24+$C$20*(1-$C$21)*Model!$C$5*((C33-$C$22)+(D29-$C$23))-D33)^2+($C$24+$C$20*(1-$C$21)*Model!$C$5*((C33-$C$22)+(E29-$C$23))-E33)^2+($C$24+$C$20*(1-$C$21)*Model!$C$5*((C33-$C$22)+(F29-$C$23))-F33)^2+($C$24+$C$20*(1-$C$21)*Model!$C$5*((C33-$C$22)+(G29-$C$23))-G33)^2+($C$24+$C$20*(1-$C$21)*Model!$C$5*((C33-$C$22)+(H29-$C$23))-H33)^2+($C$24+$C$20*(1-$C$21)*Model!$C$5*((C34-$C$22)+(D29-$C$23))-D34)^2+($C$24+$C$20*(1-$C$21)*Model!$C$5*((C34-$C$22)+(E29-$C$23))-E34)^2+($C$24+$C$20*(1-$C$21)*Model!$C$5*((C34-$C$22)+(F29-$C$23))-F34)^2+($C$24+$C$20*(1-$C$21)*Model!$C$5*((C34-$C$22)+(G29-$C$23))-G34)^2+($C$24+$C$20*(1-$C$21)*Model!$C$5*((C34-$C$22)+(H29-$C$23))-H34)^2+($C$24+$C$20*(1-$C$21)*Model!$C$5*((C35-$C$22)+(D29-$C$23))-D35)^2+($C$24+$C$20*(1-$C$21)*Model!$C$5*((C35-$C$22)+(E29-$C$23))-E35)^2+($C$24+$C$20*(1-$C$21)*Model!$C$5*((C35-$C$22)+(F29-$C$23))-F35)^2+($C$24+$C$20*(1-$C$21)*Model!$C$5*((C35-$C$22)+(G29-$C$23))-G35)^2+($C$24+$C$20*(1-$C$21)*Model!$C$5*((C35-$C$22)+(H29-$C$23))-H35)^2+($C$24+$C$20*(1-$C$21)*Model!$C$5*((C36-$C$22)+(D29-$C$23))-D36)^2+($C$24+$C$20*(1-$C$21)*Model!$C$5*((C36-$C$22)+(E29-$C$23))-E36)^2+($C$24+$C$20*(1-$C$21)*Model!$C$5*((C36-$C$22)+(F29-$C$23))-F36)^2+($C$24+$C$20*(1-$C$21)*Model!$C$5*((C36-$C$22)+(G29-$C$23))-G36)^2+($C$24+$C$20*(1-$C$21)*Model!$C$5*((C36-$C$22)+(H29-$C$23))-H36)^2+($C$24+$C$20*(1-$C$21)*Model!$C$5*((C37-$C$22)+(D29-$C$23))-D37)^2+($C$24+$C$20*(1-$C$21)*Model!$C$5*((C37-$C$22)+(E29-$C$23))-E37)^2+($C$24+$C$20*(1-$C$21)*Model!$C$5*((C37-$C$22)+(F29-$C$23))-F37)^2+($C$24+$C$20*(1-$C$21)*Model!$C$5*((C37-$C$22)+(G29-$C$23))-G37)^2+($C$24+$C$20*(1-$C$21)*Model!$C$5*((C37-$C$22)+(H29-$C$23))-H37)^2+($C$24+$C$20*(1-$C$21)*Model!$C$5*((C38-$C$22)+(D29-$C$23))-D38)^2+($C$24+$C$20*(1-$C$21)*Model!$C$5*((C38-$C$22)+(E29-$C$23))-E38)^2+($C$24+$C$20*(1-$C$21)*Model!$C$5*((C38-$C$22)+(F29-$C$23))-F38)^2+($C$24+$C$20*(1-$C$21)*Model!$C$5*((C38-$C$22)+(G29-$C$23))-G38)^2+($C$24+$C$20*(1-$C$21)*Model!$C$5*((C38-$C$22)+(H29-$C$23))-H38)^2 -> 18990.477
B42: FY25@2025-02-28 | C42: Source: FY 2024 results presentation (Mar 2025)
B43: Hedge year | C43: 2025
B44: Months not yet realised | C44: 10
B45: s | C45: =C44/12 -> 0.83333333
B46: Hedge ratio h | C46: 0.79
B47: Base Brent | C47: 71
B48: Base crack | C48: 19
B49: P0 (centre cell) | C49: =INDEX(D55:H61,MATCH(C47,C55:C61,0),MATCH(C48,D54:H54,0)) -> 825
B50: K1 | C50: =INDEX($C$6:$C$8,MATCH(C43,$B$6:$B$8,0)) -> 690
B51: K2 | C51: =INDEX($D$6:$D$8,MATCH(C43,$B$6:$B$8,0)) -> 1005
C53: Published | J53: Model | Q53: Model − published
C54: Brent \ crack | D54: 9 | E54: 14 | F54: 19 | G54: 24 | H54: 29 | J54: Brent \ crack | K54: =D54 -> 9 | L54: =E54 -> 14 | M54: =F54 -> 19 | N54: =G54 -> 24 | O54: =H54 -> 29 | Q54: Brent \ crack | R54: =D54 -> 9 | S54: =E54 -> 14 | T54: =F54 -> 19 | U54: =G54 -> 24 | V54: =H54 -> 29
C55: 101 | D55: 889 | E55: 905 | F55: 921 | G55: 935 | H55: 951 | J55: =C55 -> 101 | K55: =$C$49+$C$45*((Model!$C$5*(($C55)+Model!$C$6*(D$54)))-(Model!$C$5*(($C$47)+Model!$C$6*($C$48)))-$C$46*(((((Model!$C$5*(($C55)+Model!$C$6*(D$54)))-($C$50))*NORMSDIST(((Model!$C$5*(($C55)+Model!$C$6*(D$54)))-($C$50))/Model!$C$7)+Model!$C$7*EXP(-((((Model!$C$5*(($C55)+Model!$C$6*(D$54)))-($C$50))/Model!$C$7)^2)/2)/SQRT(2*PI()))-(((Model!$C$5*(($C55)+Model!$C$6*(D$54)))-($C$51))*NORMSDIST(((Model!$C$5*(($C55)+Model!$C$6*(D$54)))-($C$51))/Model!$C$7)+Model!$C$7*EXP(-((((Model!$C$5*(($C55)+Model!$C$6*(D$54)))-($C$51))/Model!$C$7)^2)/2)/SQRT(2*PI())))-((((Model!$C$5*(($C$47)+Model!$C$6*($C$48)))-($C$50))*NORMSDIST(((Model!$C$5*(($C$47)+Model!$C$6*($C$48)))-($C$50))/Model!$C$7)+Model!$C$7*EXP(-((((Model!$C$5*(($C$47)+Model!$C$6*($C$48)))-($C$50))/Model!$C$7)^2)/2)/SQRT(2*PI()))-(((Model!$C$5*(($C$47)+Model!$C$6*($C$48)))-($C$51))*NORMSDIST(((Model!$C$5*(($C$47)+Model!$C$6*($C$48)))-($C$51))/Model!$C$7)+Model!$C$7*EXP(-((((Model!$C$5*(($C$47)+Model!$C$6*($C$48)))-($C$51))/Model!$C$7)^2)/2)/SQRT(2*PI()))))) -> 889.79303 | L55: =$C$49+$C$45*((Model!$C$5*(($C55)+Model!$C$6*(E$54)))-(Model!$C$5*(($C$47)+Model!$C$6*($C$48)))-$C$46*(((((Model!$C$5*(($C55)+Model!$C$6*(E$54)))-($C$50))*NORMSDIST(((Model!$C$5*(($C55)+Model!$C$6*(E$54)))-($C$50))/Model!$C$7)+Model!$C$7*EXP(-((((Model!$C$5*(($C55)+Model!$C$6*(E$54)))-($C$50))/Model!$C$7)^2)/2)/SQRT(2*PI()))-(((Model!$C$5*(($C55)+Model!$C$6*(E$54)))-($C$51))*NORMSDIST(((Model!$C$5*(($C55)+Model!$C$6*(E$54)))-($C$51))/Model!$C$7)+Model!$C$7*EXP(-((((Model!$C$5*(($C55)+Model!$C$6*(E$54)))-($C$51))/Model!$C$7)^2)/2)/SQRT(2*PI())))-((((Model!$C$5*(($C$47)+Model!$C$6*($C$48)))-($C$50))*NORMSDIST(((Model!$C$5*(($C$47)+Model!$C$6*($C$48)))-($C$50))/Model!$C$7)+Model!$C$7*EXP(-((((Model!$C$5*(($C$47)+Model!$C$6*($C$48)))-($C$50))/Model!$C$7)^2)/2)/SQRT(2*PI()))-(((Model!$C$5*(($C$47)+Model!$C$6*($C$48)))-($C$51))*NORMSDIST(((Model!$C$5*(($C$47)+Model!$C$6*($C$48)))-($C$51))/Model!$C$7)+Model!$C$7*EXP(-((((Model!$C$5*(($C$47)+Model!$C$6*($C$48)))-($C$51))/Model!$C$7)^2)/2)/SQRT(2*PI()))))) -> 909.80584 | M55: =$C$49+$C$45*((Model!$C$5*(($C55)+Model!$C$6*(F$54)))-(Model!$C$5*(($C$47)+Model!$C$6*($C$48)))-$C$46*(((((Model!$C$5*(($C55)+Model!$C$6*(F$54)))-($C$50))*NORMSDIST(((Model!$C$5*(($C55)+Model!$C$6*(F$54)))-($C$50))/Model!$C$7)+Model!$C$7*EXP(-((((Model!$C$5*(($C55)+Model!$C$6*(F$54)))-($C$50))/Model!$C$7)^2)/2)/SQRT(2*PI()))-(((Model!$C$5*(($C55)+Model!$C$6*(F$54)))-($C$51))*NORMSDIST(((Model!$C$5*(($C55)+Model!$C$6*(F$54)))-($C$51))/Model!$C$7)+Model!$C$7*EXP(-((((Model!$C$5*(($C55)+Model!$C$6*(F$54)))-($C$51))/Model!$C$7)^2)/2)/SQRT(2*PI())))-((((Model!$C$5*(($C$47)+Model!$C$6*($C$48)))-($C$50))*NORMSDIST(((Model!$C$5*(($C$47)+Model!$C$6*($C$48)))-($C$50))/Model!$C$7)+Model!$C$7*EXP(-((((Model!$C$5*(($C$47)+Model!$C$6*($C$48)))-($C$50))/Model!$C$7)^2)/2)/SQRT(2*PI()))-(((Model!$C$5*(($C$47)+Model!$C$6*($C$48)))-($C$51))*NORMSDIST(((Model!$C$5*(($C$47)+Model!$C$6*($C$48)))-($C$51))/Model!$C$7)+Model!$C$7*EXP(-((((Model!$C$5*(($C$47)+Model!$C$6*($C$48)))-($C$51))/Model!$C$7)^2)/2)/SQRT(2*PI()))))) -> 931.18672 | N55: =$C$49+$C$45*((Model!$C$5*(($C55)+Model!$C$6*(G$54)))-(Model!$C$5*(($C$47)+Model!$C$6*($C$48)))-$C$46*(((((Model!$C$5*(($C55)+Model!$C$6*(G$54)))-($C$50))*NORMSDIST(((Model!$C$5*(($C55)+Model!$C$6*(G$54)))-($C$50))/Model!$C$7)+Model!$C$7*EXP(-((((Model!$C$5*(($C55)+Model!$C$6*(G$54)))-($C$50))/Model!$C$7)^2)/2)/SQRT(2*PI()))-(((Model!$C$5*(($C55)+Model!$C$6*(G$54)))-($C$51))*NORMSDIST(((Model!$C$5*(($C55)+Model!$C$6*(G$54)))-($C$51))/Model!$C$7)+Model!$C$7*EXP(-((((Model!$C$5*(($C55)+Model!$C$6*(G$54)))-($C$51))/Model!$C$7)^2)/2)/SQRT(2*PI())))-((((Model!$C$5*(($C$47)+Model!$C$6*($C$48)))-($C$50))*NORMSDIST(((Model!$C$5*(($C$47)+Model!$C$6*($C$48)))-($C$50))/Model!$C$7)+Model!$C$7*EXP(-((((Model!$C$5*(($C$47)+Model!$C$6*($C$48)))-($C$50))/Model!$C$7)^2)/2)/SQRT(2*PI()))-(((Model!$C$5*(($C$47)+Model!$C$6*($C$48)))-($C$51))*NORMSDIST(((Model!$C$5*(($C$47)+Model!$C$6*($C$48)))-($C$51))/Model!$C$7)+Model!$C$7*EXP(-((((Model!$C$5*(($C$47)+Model!$C$6*($C$48)))-($C$51))/Model!$C$7)^2)/2)/SQRT(2*PI()))))) -> 954.54884 | O55: =$C$49+$C$45*((Model!$C$5*(($C55)+Model!$C$6*(H$54)))-(Model!$C$5*(($C$47)+Model!$C$6*($C$48)))-$C$46*(((((Model!$C$5*(($C55)+Model!$C$6*(H$54)))-($C$50))*NORMSDIST(((Model!$C$5*(($C55)+Model!$C$6*(H$54)))-($C$50))/Model!$C$7)+Model!$C$7*EXP(-((((Model!$C$5*(($C55)+Model!$C$6*(H$54)))-($C$50))/Model!$C$7)^2)/2)/SQRT(2*PI()))-(((Model!$C$5*(($C55)+Model!$C$6*(H$54)))-($C$51))*NORMSDIST(((Model!$C$5*(($C55)+Model!$C$6*(H$54)))-($C$51))/Model!$C$7)+Model!$C$7*EXP(-((((Model!$C$5*(($C55)+Model!$C$6*(H$54)))-($C$51))/Model!$C$7)^2)/2)/SQRT(2*PI())))-((((Model!$C$5*(($C$47)+Model!$C$6*($C$48)))-($C$50))*NORMSDIST(((Model!$C$5*(($C$47)+Model!$C$6*($C$48)))-($C$50))/Model!$C$7)+Model!$C$7*EXP(-((((Model!$C$5*(($C$47)+Model!$C$6*($C$48)))-($C$50))/Model!$C$7)^2)/2)/SQRT(2*PI()))-(((Model!$C$5*(($C$47)+Model!$C$6*($C$48)))-($C$51))*NORMSDIST(((Model!$C$5*(($C$47)+Model!$C$6*($C$48)))-($C$51))/Model!$C$7)+Model!$C$7*EXP(-((((Model!$C$5*(($C$47)+Model!$C$6*($C$48)))-($C$51))/Model!$C$7)^2)/2)/SQRT(2*PI()))))) -> 980.26054 | Q55: =C55 -> 101 | R55: =K55-D55 -> 0.79302773 | S55: =L55-E55 -> 4.8058361 | T55: =M55-F55 -> 10.186721 | U55: =N55-G55 -> 19.548837 | V55: =O55-H55 -> 29.260543
C56: 91 | D56: 861 | E56: 886 | F56: 905 | G56: 920 | H56: 935 | J56: =C56 -> 91 | K56: =$C$49+$C$45*((Model!$C$5*(($C56)+Model!$C$6*(D$54)))-(Model!$C$5*(($C$47)+Model!$C$6*($C$48)))-$C$46*(((((Model!$C$5*(($C56)+Model!$C$6*(D$54)))-($C$50))*NORMSDIST(((Model!$C$5*(($C56)+Model!$C$6*(D$54)))-($C$50))/Model!$C$7)+Model!$C$7*EXP(-((((Model!$C$5*(($C56)+Model!$C$6*(D$54)))-($C$50))/Model!$C$7)^2)/2)/SQRT(2*PI()))-(((Model!$C$5*(($C56)+Model!$C$6*(D$54)))-($C$51))*NORMSDIST(((Model!$C$5*(($C56)+Model!$C$6*(D$54)))-($C$51))/Model!$C$7)+Model!$C$7*EXP(-((((Model!$C$5*(($C56)+Model!$C$6*(D$54)))-($C$51))/Model!$C$7)^2)/2)/SQRT(2*PI())))-((((Model!$C$5*(($C$47)+Model!$C$6*($C$48)))-($C$50))*NORMSDIST(((Model!$C$5*(($C$47)+Model!$C$6*($C$48)))-($C$50))/Model!$C$7)+Model!$C$7*EXP(-((((Model!$C$5*(($C$47)+Model!$C$6*($C$48)))-($C$50))/Model!$C$7)^2)/2)/SQRT(2*PI()))-(((Model!$C$5*(($C$47)+Model!$C$6*($C$48)))-($C$51))*NORMSDIST(((Model!$C$5*(($C$47)+Model!$C$6*($C$48)))-($C$51))/Model!$C$7)+Model!$C$7*EXP(-((((Model!$C$5*(($C$47)+Model!$C$6*($C$48)))-($C$51))/Model!$C$7)^2)/2)/SQRT(2*PI()))))) -> 855.84464 | L56: =$C$49+$C$45*((Model!$C$5*(($C56)+Model!$C$6*(E$54)))-(Model!$C$5*(($C$47)+Model!$C$6*($C$48)))-$C$46*(((((Model!$C$5*(($C56)+Model!$C$6*(E$54)))-($C$50))*NORMSDIST(((Model!$C$5*(($C56)+Model!$C$6*(E$54)))-($C$50))/Model!$C$7)+Model!$C$7*EXP(-((((Model!$C$5*(($C56)+Model!$C$6*(E$54)))-($C$50))/Model!$C$7)^2)/2)/SQRT(2*PI()))-(((Model!$C$5*(($C56)+Model!$C$6*(E$54)))-($C$51))*NORMSDIST(((Model!$C$5*(($C56)+Model!$C$6*(E$54)))-($C$51))/Model!$C$7)+Model!$C$7*EXP(-((((Model!$C$5*(($C56)+Model!$C$6*(E$54)))-($C$51))/Model!$C$7)^2)/2)/SQRT(2*PI())))-((((Model!$C$5*(($C$47)+Model!$C$6*($C$48)))-($C$50))*NORMSDIST(((Model!$C$5*(($C$47)+Model!$C$6*($C$48)))-($C$50))/Model!$C$7)+Model!$C$7*EXP(-((((Model!$C$5*(($C$47)+Model!$C$6*($C$48)))-($C$50))/Model!$C$7)^2)/2)/SQRT(2*PI()))-(((Model!$C$5*(($C$47)+Model!$C$6*($C$48)))-($C$51))*NORMSDIST(((Model!$C$5*(($C$47)+Model!$C$6*($C$48)))-($C$51))/Model!$C$7)+Model!$C$7*EXP(-((((Model!$C$5*(($C$47)+Model!$C$6*($C$48)))-($C$51))/Model!$C$7)^2)/2)/SQRT(2*PI()))))) -> 875.41871 | M56: =$C$49+$C$45*((Model!$C$5*(($C56)+Model!$C$6*(F$54)))-(Model!$C$5*(($C$47)+Model!$C$6*($C$48)))-$C$46*(((((Model!$C$5*(($C56)+Model!$C$6*(F$54)))-($C$50))*NORMSDIST(((Model!$C$5*(($C56)+Model!$C$6*(F$54)))-($C$50))/Model!$C$7)+Model!$C$7*EXP(-((((Model!$C$5*(($C56)+Model!$C$6*(F$54)))-($C$50))/Model!$C$7)^2)/2)/SQRT(2*PI()))-(((Model!$C$5*(($C56)+Model!$C$6*(F$54)))-($C$51))*NORMSDIST(((Model!$C$5*(($C56)+Model!$C$6*(F$54)))-($C$51))/Model!$C$7)+Model!$C$7*EXP(-((((Model!$C$5*(($C56)+Model!$C$6*(F$54)))-($C$51))/Model!$C$7)^2)/2)/SQRT(2*PI())))-((((Model!$C$5*(($C$47)+Model!$C$6*($C$48)))-($C$50))*NORMSDIST(((Model!$C$5*(($C$47)+Model!$C$6*($C$48)))-($C$50))/Model!$C$7)+Model!$C$7*EXP(-((((Model!$C$5*(($C$47)+Model!$C$6*($C$48)))-($C$50))/Model!$C$7)^2)/2)/SQRT(2*PI()))-(((Model!$C$5*(($C$47)+Model!$C$6*($C$48)))-($C$51))*NORMSDIST(((Model!$C$5*(($C$47)+Model!$C$6*($C$48)))-($C$51))/Model!$C$7)+Model!$C$7*EXP(-((((Model!$C$5*(($C$47)+Model!$C$6*($C$48)))-($C$51))/Model!$C$7)^2)/2)/SQRT(2*PI()))))) -> 894.92392 | N56: =$C$49+$C$45*((Model!$C$5*(($C56)+Model!$C$6*(G$54)))-(Model!$C$5*(($C$47)+Model!$C$6*($C$48)))-$C$46*(((((Model!$C$5*(($C56)+Model!$C$6*(G$54)))-($C$50))*NORMSDIST(((Model!$C$5*(($C56)+Model!$C$6*(G$54)))-($C$50))/Model!$C$7)+Model!$C$7*EXP(-((((Model!$C$5*(($C56)+Model!$C$6*(G$54)))-($C$50))/Model!$C$7)^2)/2)/SQRT(2*PI()))-(((Model!$C$5*(($C56)+Model!$C$6*(G$54)))-($C$51))*NORMSDIST(((Model!$C$5*(($C56)+Model!$C$6*(G$54)))-($C$51))/Model!$C$7)+Model!$C$7*EXP(-((((Model!$C$5*(($C56)+Model!$C$6*(G$54)))-($C$51))/Model!$C$7)^2)/2)/SQRT(2*PI())))-((((Model!$C$5*(($C$47)+Model!$C$6*($C$48)))-($C$50))*NORMSDIST(((Model!$C$5*(($C$47)+Model!$C$6*($C$48)))-($C$50))/Model!$C$7)+Model!$C$7*EXP(-((((Model!$C$5*(($C$47)+Model!$C$6*($C$48)))-($C$50))/Model!$C$7)^2)/2)/SQRT(2*PI()))-(((Model!$C$5*(($C$47)+Model!$C$6*($C$48)))-($C$51))*NORMSDIST(((Model!$C$5*(($C$47)+Model!$C$6*($C$48)))-($C$51))/Model!$C$7)+Model!$C$7*EXP(-((((Model!$C$5*(($C$47)+Model!$C$6*($C$48)))-($C$51))/Model!$C$7)^2)/2)/SQRT(2*PI()))))) -> 915.22286 | O56: =$C$49+$C$45*((Model!$C$5*(($C56)+Model!$C$6*(H$54)))-(Model!$C$5*(($C$47)+Model!$C$6*($C$48)))-$C$46*(((((Model!$C$5*(($C56)+Model!$C$6*(H$54)))-($C$50))*NORMSDIST(((Model!$C$5*(($C56)+Model!$C$6*(H$54)))-($C$50))/Model!$C$7)+Model!$C$7*EXP(-((((Model!$C$5*(($C56)+Model!$C$6*(H$54)))-($C$50))/Model!$C$7)^2)/2)/SQRT(2*PI()))-(((Model!$C$5*(($C56)+Model!$C$6*(H$54)))-($C$51))*NORMSDIST(((Model!$C$5*(($C56)+Model!$C$6*(H$54)))-($C$51))/Model!$C$7)+Model!$C$7*EXP(-((((Model!$C$5*(($C56)+Model!$C$6*(H$54)))-($C$51))/Model!$C$7)^2)/2)/SQRT(2*PI())))-((((Model!$C$5*(($C$47)+Model!$C$6*($C$48)))-($C$50))*NORMSDIST(((Model!$C$5*(($C$47)+Model!$C$6*($C$48)))-($C$50))/Model!$C$7)+Model!$C$7*EXP(-((((Model!$C$5*(($C$47)+Model!$C$6*($C$48)))-($C$50))/Model!$C$7)^2)/2)/SQRT(2*PI()))-(((Model!$C$5*(($C$47)+Model!$C$6*($C$48)))-($C$51))*NORMSDIST(((Model!$C$5*(($C$47)+Model!$C$6*($C$48)))-($C$51))/Model!$C$7)+Model!$C$7*EXP(-((((Model!$C$5*(($C$47)+Model!$C$6*($C$48)))-($C$51))/Model!$C$7)^2)/2)/SQRT(2*PI()))))) -> 937.07063 | Q56: =C56 -> 91 | R56: =K56-D56 -> -5.1553558 | S56: =L56-E56 -> -10.581291 | T56: =M56-F56 -> -10.076079 | U56: =N56-G56 -> -4.7771359 | V56: =O56-H56 -> 2.0706295
C57: 81 | D57: 822 | E57: 850 | F57: 880 | G57: 903 | H57: 919 | J57: =C57 -> 81 | K57: =$C$49+$C$45*((Model!$C$5*(($C57)+Model!$C$6*(D$54)))-(Model!$C$5*(($C$47)+Model!$C$6*($C$48)))-$C$46*(((((Model!$C$5*(($C57)+Model!$C$6*(D$54)))-($C$50))*NORMSDIST(((Model!$C$5*(($C57)+Model!$C$6*(D$54)))-($C$50))/Model!$C$7)+Model!$C$7*EXP(-((((Model!$C$5*(($C57)+Model!$C$6*(D$54)))-($C$50))/Model!$C$7)^2)/2)/SQRT(2*PI()))-(((Model!$C$5*(($C57)+Model!$C$6*(D$54)))-($C$51))*NORMSDIST(((Model!$C$5*(($C57)+Model!$C$6*(D$54)))-($C$51))/Model!$C$7)+Model!$C$7*EXP(-((((Model!$C$5*(($C57)+Model!$C$6*(D$54)))-($C$51))/Model!$C$7)^2)/2)/SQRT(2*PI())))-((((Model!$C$5*(($C$47)+Model!$C$6*($C$48)))-($C$50))*NORMSDIST(((Model!$C$5*(($C$47)+Model!$C$6*($C$48)))-($C$50))/Model!$C$7)+Model!$C$7*EXP(-((((Model!$C$5*(($C$47)+Model!$C$6*($C$48)))-($C$50))/Model!$C$7)^2)/2)/SQRT(2*PI()))-(((Model!$C$5*(($C$47)+Model!$C$6*($C$48)))-($C$51))*NORMSDIST(((Model!$C$5*(($C$47)+Model!$C$6*($C$48)))-($C$51))/Model!$C$7)+Model!$C$7*EXP(-((((Model!$C$5*(($C$47)+Model!$C$6*($C$48)))-($C$51))/Model!$C$7)^2)/2)/SQRT(2*PI()))))) -> 819.17148 | L57: =$C$49+$C$45*((Model!$C$5*(($C57)+Model!$C$6*(E$54)))-(Model!$C$5*(($C$47)+Model!$C$6*($C$48)))-$C$46*(((((Model!$C$5*(($C57)+Model!$C$6*(E$54)))-($C$50))*NORMSDIST(((Model!$C$5*(($C57)+Model!$C$6*(E$54)))-($C$50))/Model!$C$7)+Model!$C$7*EXP(-((((Model!$C$5*(($C57)+Model!$C$6*(E$54)))-($C$50))/Model!$C$7)^2)/2)/SQRT(2*PI()))-(((Model!$C$5*(($C57)+Model!$C$6*(E$54)))-($C$51))*NORMSDIST(((Model!$C$5*(($C57)+Model!$C$6*(E$54)))-($C$51))/Model!$C$7)+Model!$C$7*EXP(-((((Model!$C$5*(($C57)+Model!$C$6*(E$54)))-($C$51))/Model!$C$7)^2)/2)/SQRT(2*PI())))-((((Model!$C$5*(($C$47)+Model!$C$6*($C$48)))-($C$50))*NORMSDIST(((Model!$C$5*(($C$47)+Model!$C$6*($C$48)))-($C$50))/Model!$C$7)+Model!$C$7*EXP(-((((Model!$C$5*(($C$47)+Model!$C$6*($C$48)))-($C$50))/Model!$C$7)^2)/2)/SQRT(2*PI()))-(((Model!$C$5*(($C$47)+Model!$C$6*($C$48)))-($C$51))*NORMSDIST(((Model!$C$5*(($C$47)+Model!$C$6*($C$48)))-($C$51))/Model!$C$7)+Model!$C$7*EXP(-((((Model!$C$5*(($C$47)+Model!$C$6*($C$48)))-($C$51))/Model!$C$7)^2)/2)/SQRT(2*PI()))))) -> 840.82818 | M57: =$C$49+$C$45*((Model!$C$5*(($C57)+Model!$C$6*(F$54)))-(Model!$C$5*(($C$47)+Model!$C$6*($C$48)))-$C$46*(((((Model!$C$5*(($C57)+Model!$C$6*(F$54)))-($C$50))*NORMSDIST(((Model!$C$5*(($C57)+Model!$C$6*(F$54)))-($C$50))/Model!$C$7)+Model!$C$7*EXP(-((((Model!$C$5*(($C57)+Model!$C$6*(F$54)))-($C$50))/Model!$C$7)^2)/2)/SQRT(2*PI()))-(((Model!$C$5*(($C57)+Model!$C$6*(F$54)))-($C$51))*NORMSDIST(((Model!$C$5*(($C57)+Model!$C$6*(F$54)))-($C$51))/Model!$C$7)+Model!$C$7*EXP(-((((Model!$C$5*(($C57)+Model!$C$6*(F$54)))-($C$51))/Model!$C$7)^2)/2)/SQRT(2*PI())))-((((Model!$C$5*(($C$47)+Model!$C$6*($C$48)))-($C$50))*NORMSDIST(((Model!$C$5*(($C$47)+Model!$C$6*($C$48)))-($C$50))/Model!$C$7)+Model!$C$7*EXP(-((((Model!$C$5*(($C$47)+Model!$C$6*($C$48)))-($C$50))/Model!$C$7)^2)/2)/SQRT(2*PI()))-(((Model!$C$5*(($C$47)+Model!$C$6*($C$48)))-($C$51))*NORMSDIST(((Model!$C$5*(($C$47)+Model!$C$6*($C$48)))-($C$51))/Model!$C$7)+Model!$C$7*EXP(-((((Model!$C$5*(($C$47)+Model!$C$6*($C$48)))-($C$51))/Model!$C$7)^2)/2)/SQRT(2*PI()))))) -> 861.00658 | N57: =$C$49+$C$45*((Model!$C$5*(($C57)+Model!$C$6*(G$54)))-(Model!$C$5*(($C$47)+Model!$C$6*($C$48)))-$C$46*(((((Model!$C$5*(($C57)+Model!$C$6*(G$54)))-($C$50))*NORMSDIST(((Model!$C$5*(($C57)+Model!$C$6*(G$54)))-($C$50))/Model!$C$7)+Model!$C$7*EXP(-((((Model!$C$5*(($C57)+Model!$C$6*(G$54)))-($C$50))/Model!$C$7)^2)/2)/SQRT(2*PI()))-(((Model!$C$5*(($C57)+Model!$C$6*(G$54)))-($C$51))*NORMSDIST(((Model!$C$5*(($C57)+Model!$C$6*(G$54)))-($C$51))/Model!$C$7)+Model!$C$7*EXP(-((((Model!$C$5*(($C57)+Model!$C$6*(G$54)))-($C$51))/Model!$C$7)^2)/2)/SQRT(2*PI())))-((((Model!$C$5*(($C$47)+Model!$C$6*($C$48)))-($C$50))*NORMSDIST(((Model!$C$5*(($C$47)+Model!$C$6*($C$48)))-($C$50))/Model!$C$7)+Model!$C$7*EXP(-((((Model!$C$5*(($C$47)+Model!$C$6*($C$48)))-($C$50))/Model!$C$7)^2)/2)/SQRT(2*PI()))-(((Model!$C$5*(($C$47)+Model!$C$6*($C$48)))-($C$51))*NORMSDIST(((Model!$C$5*(($C$47)+Model!$C$6*($C$48)))-($C$51))/Model!$C$7)+Model!$C$7*EXP(-((((Model!$C$5*(($C$47)+Model!$C$6*($C$48)))-($C$51))/Model!$C$7)^2)/2)/SQRT(2*PI()))))) -> 880.47791 | O57: =$C$49+$C$45*((Model!$C$5*(($C57)+Model!$C$6*(H$54)))-(Model!$C$5*(($C$47)+Model!$C$6*($C$48)))-$C$46*(((((Model!$C$5*(($C57)+Model!$C$6*(H$54)))-($C$50))*NORMSDIST(((Model!$C$5*(($C57)+Model!$C$6*(H$54)))-($C$50))/Model!$C$7)+Model!$C$7*EXP(-((((Model!$C$5*(($C57)+Model!$C$6*(H$54)))-($C$50))/Model!$C$7)^2)/2)/SQRT(2*PI()))-(((Model!$C$5*(($C57)+Model!$C$6*(H$54)))-($C$51))*NORMSDIST(((Model!$C$5*(($C57)+Model!$C$6*(H$54)))-($C$51))/Model!$C$7)+Model!$C$7*EXP(-((((Model!$C$5*(($C57)+Model!$C$6*(H$54)))-($C$51))/Model!$C$7)^2)/2)/SQRT(2*PI())))-((((Model!$C$5*(($C$47)+Model!$C$6*($C$48)))-($C$50))*NORMSDIST(((Model!$C$5*(($C$47)+Model!$C$6*($C$48)))-($C$50))/Model!$C$7)+Model!$C$7*EXP(-((((Model!$C$5*(($C$47)+Model!$C$6*($C$48)))-($C$50))/Model!$C$7)^2)/2)/SQRT(2*PI()))-(((Model!$C$5*(($C$47)+Model!$C$6*($C$48)))-($C$51))*NORMSDIST(((Model!$C$5*(($C$47)+Model!$C$6*($C$48)))-($C$51))/Model!$C$7)+Model!$C$7*EXP(-((((Model!$C$5*(($C$47)+Model!$C$6*($C$48)))-($C$51))/Model!$C$7)^2)/2)/SQRT(2*PI()))))) -> 900.10941 | Q57: =C57 -> 81 | R57: =K57-D57 -> -2.8285225 | S57: =L57-E57 -> -9.171823 | T57: =M57-F57 -> -18.993425 | U57: =N57-G57 -> -22.522091 | V57: =O57-H57 -> -18.890586
C58: 71 | D58: 785 | E58: 802 | F58: 825 | G58: 855 | H58: 883 | J58: =C58 -> 71 | K58: =$C$49+$C$45*((Model!$C$5*(($C58)+Model!$C$6*(D$54)))-(Model!$C$5*(($C$47)+Model!$C$6*($C$48)))-$C$46*(((((Model!$C$5*(($C58)+Model!$C$6*(D$54)))-($C$50))*NORMSDIST(((Model!$C$5*(($C58)+Model!$C$6*(D$54)))-($C$50))/Model!$C$7)+Model!$C$7*EXP(-((((Model!$C$5*(($C58)+Model!$C$6*(D$54)))-($C$50))/Model!$C$7)^2)/2)/SQRT(2*PI()))-(((Model!$C$5*(($C58)+Model!$C$6*(D$54)))-($C$51))*NORMSDIST(((Model!$C$5*(($C58)+Model!$C$6*(D$54)))-($C$51))/Model!$C$7)+Model!$C$7*EXP(-((((Model!$C$5*(($C58)+Model!$C$6*(D$54)))-($C$51))/Model!$C$7)^2)/2)/SQRT(2*PI())))-((((Model!$C$5*(($C$47)+Model!$C$6*($C$48)))-($C$50))*NORMSDIST(((Model!$C$5*(($C$47)+Model!$C$6*($C$48)))-($C$50))/Model!$C$7)+Model!$C$7*EXP(-((((Model!$C$5*(($C$47)+Model!$C$6*($C$48)))-($C$50))/Model!$C$7)^2)/2)/SQRT(2*PI()))-(((Model!$C$5*(($C$47)+Model!$C$6*($C$48)))-($C$51))*NORMSDIST(((Model!$C$5*(($C$47)+Model!$C$6*($C$48)))-($C$51))/Model!$C$7)+Model!$C$7*EXP(-((((Model!$C$5*(($C$47)+Model!$C$6*($C$48)))-($C$51))/Model!$C$7)^2)/2)/SQRT(2*PI()))))) -> 776.408 | L58: =$C$49+$C$45*((Model!$C$5*(($C58)+Model!$C$6*(E$54)))-(Model!$C$5*(($C$47)+Model!$C$6*($C$48)))-$C$46*(((((Model!$C$5*(($C58)+Model!$C$6*(E$54)))-($C$50))*NORMSDIST(((Model!$C$5*(($C58)+Model!$C$6*(E$54)))-($C$50))/Model!$C$7)+Model!$C$7*EXP(-((((Model!$C$5*(($C58)+Model!$C$6*(E$54)))-($C$50))/Model!$C$7)^2)/2)/SQRT(2*PI()))-(((Model!$C$5*(($C58)+Model!$C$6*(E$54)))-($C$51))*NORMSDIST(((Model!$C$5*(($C58)+Model!$C$6*(E$54)))-($C$51))/Model!$C$7)+Model!$C$7*EXP(-((((Model!$C$5*(($C58)+Model!$C$6*(E$54)))-($C$51))/Model!$C$7)^2)/2)/SQRT(2*PI())))-((((Model!$C$5*(($C$47)+Model!$C$6*($C$48)))-($C$50))*NORMSDIST(((Model!$C$5*(($C$47)+Model!$C$6*($C$48)))-($C$50))/Model!$C$7)+Model!$C$7*EXP(-((((Model!$C$5*(($C$47)+Model!$C$6*($C$48)))-($C$50))/Model!$C$7)^2)/2)/SQRT(2*PI()))-(((Model!$C$5*(($C$47)+Model!$C$6*($C$48)))-($C$51))*NORMSDIST(((Model!$C$5*(($C$47)+Model!$C$6*($C$48)))-($C$51))/Model!$C$7)+Model!$C$7*EXP(-((((Model!$C$5*(($C$47)+Model!$C$6*($C$48)))-($C$51))/Model!$C$7)^2)/2)/SQRT(2*PI()))))) -> 801.86577 | M58: =$C$49+$C$45*((Model!$C$5*(($C58)+Model!$C$6*(F$54)))-(Model!$C$5*(($C$47)+Model!$C$6*($C$48)))-$C$46*(((((Model!$C$5*(($C58)+Model!$C$6*(F$54)))-($C$50))*NORMSDIST(((Model!$C$5*(($C58)+Model!$C$6*(F$54)))-($C$50))/Model!$C$7)+Model!$C$7*EXP(-((((Model!$C$5*(($C58)+Model!$C$6*(F$54)))-($C$50))/Model!$C$7)^2)/2)/SQRT(2*PI()))-(((Model!$C$5*(($C58)+Model!$C$6*(F$54)))-($C$51))*NORMSDIST(((Model!$C$5*(($C58)+Model!$C$6*(F$54)))-($C$51))/Model!$C$7)+Model!$C$7*EXP(-((((Model!$C$5*(($C58)+Model!$C$6*(F$54)))-($C$51))/Model!$C$7)^2)/2)/SQRT(2*PI())))-((((Model!$C$5*(($C$47)+Model!$C$6*($C$48)))-($C$50))*NORMSDIST(((Model!$C$5*(($C$47)+Model!$C$6*($C$48)))-($C$50))/Model!$C$7)+Model!$C$7*EXP(-((((Model!$C$5*(($C$47)+Model!$C$6*($C$48)))-($C$50))/Model!$C$7)^2)/2)/SQRT(2*PI()))-(((Model!$C$5*(($C$47)+Model!$C$6*($C$48)))-($C$51))*NORMSDIST(((Model!$C$5*(($C$47)+Model!$C$6*($C$48)))-($C$51))/Model!$C$7)+Model!$C$7*EXP(-((((Model!$C$5*(($C$47)+Model!$C$6*($C$48)))-($C$51))/Model!$C$7)^2)/2)/SQRT(2*PI()))))) -> 825 | N58: =$C$49+$C$45*((Model!$C$5*(($C58)+Model!$C$6*(G$54)))-(Model!$C$5*(($C$47)+Model!$C$6*($C$48)))-$C$46*(((((Model!$C$5*(($C58)+Model!$C$6*(G$54)))-($C$50))*NORMSDIST(((Model!$C$5*(($C58)+Model!$C$6*(G$54)))-($C$50))/Model!$C$7)+Model!$C$7*EXP(-((((Model!$C$5*(($C58)+Model!$C$6*(G$54)))-($C$50))/Model!$C$7)^2)/2)/SQRT(2*PI()))-(((Model!$C$5*(($C58)+Model!$C$6*(G$54)))-($C$51))*NORMSDIST(((Model!$C$5*(($C58)+Model!$C$6*(G$54)))-($C$51))/Model!$C$7)+Model!$C$7*EXP(-((((Model!$C$5*(($C58)+Model!$C$6*(G$54)))-($C$51))/Model!$C$7)^2)/2)/SQRT(2*PI())))-((((Model!$C$5*(($C$47)+Model!$C$6*($C$48)))-($C$50))*NORMSDIST(((Model!$C$5*(($C$47)+Model!$C$6*($C$48)))-($C$50))/Model!$C$7)+Model!$C$7*EXP(-((((Model!$C$5*(($C$47)+Model!$C$6*($C$48)))-($C$50))/Model!$C$7)^2)/2)/SQRT(2*PI()))-(((Model!$C$5*(($C$47)+Model!$C$6*($C$48)))-($C$51))*NORMSDIST(((Model!$C$5*(($C$47)+Model!$C$6*($C$48)))-($C$51))/Model!$C$7)+Model!$C$7*EXP(-((((Model!$C$5*(($C$47)+Model!$C$6*($C$48)))-($C$51))/Model!$C$7)^2)/2)/SQRT(2*PI()))))) -> 846.20613 | O58: =$C$49+$C$45*((Model!$C$5*(($C58)+Model!$C$6*(H$54)))-(Model!$C$5*(($C$47)+Model!$C$6*($C$48)))-$C$46*(((((Model!$C$5*(($C58)+Model!$C$6*(H$54)))-($C$50))*NORMSDIST(((Model!$C$5*(($C58)+Model!$C$6*(H$54)))-($C$50))/Model!$C$7)+Model!$C$7*EXP(-((((Model!$C$5*(($C58)+Model!$C$6*(H$54)))-($C$50))/Model!$C$7)^2)/2)/SQRT(2*PI()))-(((Model!$C$5*(($C58)+Model!$C$6*(H$54)))-($C$51))*NORMSDIST(((Model!$C$5*(($C58)+Model!$C$6*(H$54)))-($C$51))/Model!$C$7)+Model!$C$7*EXP(-((((Model!$C$5*(($C58)+Model!$C$6*(H$54)))-($C$51))/Model!$C$7)^2)/2)/SQRT(2*PI())))-((((Model!$C$5*(($C$47)+Model!$C$6*($C$48)))-($C$50))*NORMSDIST(((Model!$C$5*(($C$47)+Model!$C$6*($C$48)))-($C$50))/Model!$C$7)+Model!$C$7*EXP(-((((Model!$C$5*(($C$47)+Model!$C$6*($C$48)))-($C$50))/Model!$C$7)^2)/2)/SQRT(2*PI()))-(((Model!$C$5*(($C$47)+Model!$C$6*($C$48)))-($C$51))*NORMSDIST(((Model!$C$5*(($C$47)+Model!$C$6*($C$48)))-($C$51))/Model!$C$7)+Model!$C$7*EXP(-((((Model!$C$5*(($C$47)+Model!$C$6*($C$48)))-($C$51))/Model!$C$7)^2)/2)/SQRT(2*PI()))))) -> 866.11987 | Q58: =C58 -> 71 | R58: =K58-D58 -> -8.5919962 | S58: =L58-E58 -> -0.13422628 | T58: =M58-F58 -> 0 | U58: =N58-G58 -> -8.7938715 | V58: =O58-H58 -> -16.880133
C59: 61 | D59: 742 | E59: 771 | F59: 791 | G59: 808 | H59: 834 | J59: =C59 -> 61 | K59: =$C$49+$C$45*((Model!$C$5*(($C59)+Model!$C$6*(D$54)))-(Model!$C$5*(($C$47)+Model!$C$6*($C$48)))-$C$46*(((((Model!$C$5*(($C59)+Model!$C$6*(D$54)))-($C$50))*NORMSDIST(((Model!$C$5*(($C59)+Model!$C$6*(D$54)))-($C$50))/Model!$C$7)+Model!$C$7*EXP(-((((Model!$C$5*(($C59)+Model!$C$6*(D$54)))-($C$50))/Model!$C$7)^2)/2)/SQRT(2*PI()))-(((Model!$C$5*(($C59)+Model!$C$6*(D$54)))-($C$51))*NORMSDIST(((Model!$C$5*(($C59)+Model!$C$6*(D$54)))-($C$51))/Model!$C$7)+Model!$C$7*EXP(-((((Model!$C$5*(($C59)+Model!$C$6*(D$54)))-($C$51))/Model!$C$7)^2)/2)/SQRT(2*PI())))-((((Model!$C$5*(($C$47)+Model!$C$6*($C$48)))-($C$50))*NORMSDIST(((Model!$C$5*(($C$47)+Model!$C$6*($C$48)))-($C$50))/Model!$C$7)+Model!$C$7*EXP(-((((Model!$C$5*(($C$47)+Model!$C$6*($C$48)))-($C$50))/Model!$C$7)^2)/2)/SQRT(2*PI()))-(((Model!$C$5*(($C$47)+Model!$C$6*($C$48)))-($C$51))*NORMSDIST(((Model!$C$5*(($C$47)+Model!$C$6*($C$48)))-($C$51))/Model!$C$7)+Model!$C$7*EXP(-((((Model!$C$5*(($C$47)+Model!$C$6*($C$48)))-($C$51))/Model!$C$7)^2)/2)/SQRT(2*PI()))))) -> 726.33303 | L59: =$C$49+$C$45*((Model!$C$5*(($C59)+Model!$C$6*(E$54)))-(Model!$C$5*(($C$47)+Model!$C$6*($C$48)))-$C$46*(((((Model!$C$5*(($C59)+Model!$C$6*(E$54)))-($C$50))*NORMSDIST(((Model!$C$5*(($C59)+Model!$C$6*(E$54)))-($C$50))/Model!$C$7)+Model!$C$7*EXP(-((((Model!$C$5*(($C59)+Model!$C$6*(E$54)))-($C$50))/Model!$C$7)^2)/2)/SQRT(2*PI()))-(((Model!$C$5*(($C59)+Model!$C$6*(E$54)))-($C$51))*NORMSDIST(((Model!$C$5*(($C59)+Model!$C$6*(E$54)))-($C$51))/Model!$C$7)+Model!$C$7*EXP(-((((Model!$C$5*(($C59)+Model!$C$6*(E$54)))-($C$51))/Model!$C$7)^2)/2)/SQRT(2*PI())))-((((Model!$C$5*(($C$47)+Model!$C$6*($C$48)))-($C$50))*NORMSDIST(((Model!$C$5*(($C$47)+Model!$C$6*($C$48)))-($C$50))/Model!$C$7)+Model!$C$7*EXP(-((((Model!$C$5*(($C$47)+Model!$C$6*($C$48)))-($C$50))/Model!$C$7)^2)/2)/SQRT(2*PI()))-(((Model!$C$5*(($C$47)+Model!$C$6*($C$48)))-($C$51))*NORMSDIST(((Model!$C$5*(($C$47)+Model!$C$6*($C$48)))-($C$51))/Model!$C$7)+Model!$C$7*EXP(-((((Model!$C$5*(($C$47)+Model!$C$6*($C$48)))-($C$51))/Model!$C$7)^2)/2)/SQRT(2*PI()))))) -> 756.00993 | M59: =$C$49+$C$45*((Model!$C$5*(($C59)+Model!$C$6*(F$54)))-(Model!$C$5*(($C$47)+Model!$C$6*($C$48)))-$C$46*(((((Model!$C$5*(($C59)+Model!$C$6*(F$54)))-($C$50))*NORMSDIST(((Model!$C$5*(($C59)+Model!$C$6*(F$54)))-($C$50))/Model!$C$7)+Model!$C$7*EXP(-((((Model!$C$5*(($C59)+Model!$C$6*(F$54)))-($C$50))/Model!$C$7)^2)/2)/SQRT(2*PI()))-(((Model!$C$5*(($C59)+Model!$C$6*(F$54)))-($C$51))*NORMSDIST(((Model!$C$5*(($C59)+Model!$C$6*(F$54)))-($C$51))/Model!$C$7)+Model!$C$7*EXP(-((((Model!$C$5*(($C59)+Model!$C$6*(F$54)))-($C$51))/Model!$C$7)^2)/2)/SQRT(2*PI())))-((((Model!$C$5*(($C$47)+Model!$C$6*($C$48)))-($C$50))*NORMSDIST(((Model!$C$5*(($C$47)+Model!$C$6*($C$48)))-($C$50))/Model!$C$7)+Model!$C$7*EXP(-((((Model!$C$5*(($C$47)+Model!$C$6*($C$48)))-($C$50))/Model!$C$7)^2)/2)/SQRT(2*PI()))-(((Model!$C$5*(($C$47)+Model!$C$6*($C$48)))-($C$51))*NORMSDIST(((Model!$C$5*(($C$47)+Model!$C$6*($C$48)))-($C$51))/Model!$C$7)+Model!$C$7*EXP(-((((Model!$C$5*(($C$47)+Model!$C$6*($C$48)))-($C$51))/Model!$C$7)^2)/2)/SQRT(2*PI()))))) -> 783.28517 | N59: =$C$49+$C$45*((Model!$C$5*(($C59)+Model!$C$6*(G$54)))-(Model!$C$5*(($C$47)+Model!$C$6*($C$48)))-$C$46*(((((Model!$C$5*(($C59)+Model!$C$6*(G$54)))-($C$50))*NORMSDIST(((Model!$C$5*(($C59)+Model!$C$6*(G$54)))-($C$50))/Model!$C$7)+Model!$C$7*EXP(-((((Model!$C$5*(($C59)+Model!$C$6*(G$54)))-($C$50))/Model!$C$7)^2)/2)/SQRT(2*PI()))-(((Model!$C$5*(($C59)+Model!$C$6*(G$54)))-($C$51))*NORMSDIST(((Model!$C$5*(($C59)+Model!$C$6*(G$54)))-($C$51))/Model!$C$7)+Model!$C$7*EXP(-((((Model!$C$5*(($C59)+Model!$C$6*(G$54)))-($C$51))/Model!$C$7)^2)/2)/SQRT(2*PI())))-((((Model!$C$5*(($C$47)+Model!$C$6*($C$48)))-($C$50))*NORMSDIST(((Model!$C$5*(($C$47)+Model!$C$6*($C$48)))-($C$50))/Model!$C$7)+Model!$C$7*EXP(-((((Model!$C$5*(($C$47)+Model!$C$6*($C$48)))-($C$50))/Model!$C$7)^2)/2)/SQRT(2*PI()))-(((Model!$C$5*(($C$47)+Model!$C$6*($C$48)))-($C$51))*NORMSDIST(((Model!$C$5*(($C$47)+Model!$C$6*($C$48)))-($C$51))/Model!$C$7)+Model!$C$7*EXP(-((((Model!$C$5*(($C$47)+Model!$C$6*($C$48)))-($C$51))/Model!$C$7)^2)/2)/SQRT(2*PI()))))) -> 808.1134 | O59: =$C$49+$C$45*((Model!$C$5*(($C59)+Model!$C$6*(H$54)))-(Model!$C$5*(($C$47)+Model!$C$6*($C$48)))-$C$46*(((((Model!$C$5*(($C59)+Model!$C$6*(H$54)))-($C$50))*NORMSDIST(((Model!$C$5*(($C59)+Model!$C$6*(H$54)))-($C$50))/Model!$C$7)+Model!$C$7*EXP(-((((Model!$C$5*(($C59)+Model!$C$6*(H$54)))-($C$50))/Model!$C$7)^2)/2)/SQRT(2*PI()))-(((Model!$C$5*(($C59)+Model!$C$6*(H$54)))-($C$51))*NORMSDIST(((Model!$C$5*(($C59)+Model!$C$6*(H$54)))-($C$51))/Model!$C$7)+Model!$C$7*EXP(-((((Model!$C$5*(($C59)+Model!$C$6*(H$54)))-($C$51))/Model!$C$7)^2)/2)/SQRT(2*PI())))-((((Model!$C$5*(($C$47)+Model!$C$6*($C$48)))-($C$50))*NORMSDIST(((Model!$C$5*(($C$47)+Model!$C$6*($C$48)))-($C$50))/Model!$C$7)+Model!$C$7*EXP(-((((Model!$C$5*(($C$47)+Model!$C$6*($C$48)))-($C$50))/Model!$C$7)^2)/2)/SQRT(2*PI()))-(((Model!$C$5*(($C$47)+Model!$C$6*($C$48)))-($C$51))*NORMSDIST(((Model!$C$5*(($C$47)+Model!$C$6*($C$48)))-($C$51))/Model!$C$7)+Model!$C$7*EXP(-((((Model!$C$5*(($C$47)+Model!$C$6*($C$48)))-($C$51))/Model!$C$7)^2)/2)/SQRT(2*PI()))))) -> 830.69601 | Q59: =C59 -> 61 | R59: =K59-D59 -> -15.666974 | S59: =L59-E59 -> -14.990067 | T59: =M59-F59 -> -7.7148332 | U59: =N59-G59 -> 0.11339578 | V59: =O59-H59 -> -3.3039945
C60: 51 | D60: 685 | E60: 719 | F60: 752 | G60: 777 | H60: 795 | J60: =C60 -> 51 | K60: =$C$49+$C$45*((Model!$C$5*(($C60)+Model!$C$6*(D$54)))-(Model!$C$5*(($C$47)+Model!$C$6*($C$48)))-$C$46*(((((Model!$C$5*(($C60)+Model!$C$6*(D$54)))-($C$50))*NORMSDIST(((Model!$C$5*(($C60)+Model!$C$6*(D$54)))-($C$50))/Model!$C$7)+Model!$C$7*EXP(-((((Model!$C$5*(($C60)+Model!$C$6*(D$54)))-($C$50))/Model!$C$7)^2)/2)/SQRT(2*PI()))-(((Model!$C$5*(($C60)+Model!$C$6*(D$54)))-($C$51))*NORMSDIST(((Model!$C$5*(($C60)+Model!$C$6*(D$54)))-($C$51))/Model!$C$7)+Model!$C$7*EXP(-((((Model!$C$5*(($C60)+Model!$C$6*(D$54)))-($C$51))/Model!$C$7)^2)/2)/SQRT(2*PI())))-((((Model!$C$5*(($C$47)+Model!$C$6*($C$48)))-($C$50))*NORMSDIST(((Model!$C$5*(($C$47)+Model!$C$6*($C$48)))-($C$50))/Model!$C$7)+Model!$C$7*EXP(-((((Model!$C$5*(($C$47)+Model!$C$6*($C$48)))-($C$50))/Model!$C$7)^2)/2)/SQRT(2*PI()))-(((Model!$C$5*(($C$47)+Model!$C$6*($C$48)))-($C$51))*NORMSDIST(((Model!$C$5*(($C$47)+Model!$C$6*($C$48)))-($C$51))/Model!$C$7)+Model!$C$7*EXP(-((((Model!$C$5*(($C$47)+Model!$C$6*($C$48)))-($C$51))/Model!$C$7)^2)/2)/SQRT(2*PI()))))) -> 669.77823 | L60: =$C$49+$C$45*((Model!$C$5*(($C60)+Model!$C$6*(E$54)))-(Model!$C$5*(($C$47)+Model!$C$6*($C$48)))-$C$46*(((((Model!$C$5*(($C60)+Model!$C$6*(E$54)))-($C$50))*NORMSDIST(((Model!$C$5*(($C60)+Model!$C$6*(E$54)))-($C$50))/Model!$C$7)+Model!$C$7*EXP(-((((Model!$C$5*(($C60)+Model!$C$6*(E$54)))-($C$50))/Model!$C$7)^2)/2)/SQRT(2*PI()))-(((Model!$C$5*(($C60)+Model!$C$6*(E$54)))-($C$51))*NORMSDIST(((Model!$C$5*(($C60)+Model!$C$6*(E$54)))-($C$51))/Model!$C$7)+Model!$C$7*EXP(-((((Model!$C$5*(($C60)+Model!$C$6*(E$54)))-($C$51))/Model!$C$7)^2)/2)/SQRT(2*PI())))-((((Model!$C$5*(($C$47)+Model!$C$6*($C$48)))-($C$50))*NORMSDIST(((Model!$C$5*(($C$47)+Model!$C$6*($C$48)))-($C$50))/Model!$C$7)+Model!$C$7*EXP(-((((Model!$C$5*(($C$47)+Model!$C$6*($C$48)))-($C$50))/Model!$C$7)^2)/2)/SQRT(2*PI()))-(((Model!$C$5*(($C$47)+Model!$C$6*($C$48)))-($C$51))*NORMSDIST(((Model!$C$5*(($C$47)+Model!$C$6*($C$48)))-($C$51))/Model!$C$7)+Model!$C$7*EXP(-((((Model!$C$5*(($C$47)+Model!$C$6*($C$48)))-($C$51))/Model!$C$7)^2)/2)/SQRT(2*PI()))))) -> 702.98929 | M60: =$C$49+$C$45*((Model!$C$5*(($C60)+Model!$C$6*(F$54)))-(Model!$C$5*(($C$47)+Model!$C$6*($C$48)))-$C$46*(((((Model!$C$5*(($C60)+Model!$C$6*(F$54)))-($C$50))*NORMSDIST(((Model!$C$5*(($C60)+Model!$C$6*(F$54)))-($C$50))/Model!$C$7)+Model!$C$7*EXP(-((((Model!$C$5*(($C60)+Model!$C$6*(F$54)))-($C$50))/Model!$C$7)^2)/2)/SQRT(2*PI()))-(((Model!$C$5*(($C60)+Model!$C$6*(F$54)))-($C$51))*NORMSDIST(((Model!$C$5*(($C60)+Model!$C$6*(F$54)))-($C$51))/Model!$C$7)+Model!$C$7*EXP(-((((Model!$C$5*(($C60)+Model!$C$6*(F$54)))-($C$51))/Model!$C$7)^2)/2)/SQRT(2*PI())))-((((Model!$C$5*(($C$47)+Model!$C$6*($C$48)))-($C$50))*NORMSDIST(((Model!$C$5*(($C$47)+Model!$C$6*($C$48)))-($C$50))/Model!$C$7)+Model!$C$7*EXP(-((((Model!$C$5*(($C$47)+Model!$C$6*($C$48)))-($C$50))/Model!$C$7)^2)/2)/SQRT(2*PI()))-(((Model!$C$5*(($C$47)+Model!$C$6*($C$48)))-($C$51))*NORMSDIST(((Model!$C$5*(($C$47)+Model!$C$6*($C$48)))-($C$51))/Model!$C$7)+Model!$C$7*EXP(-((((Model!$C$5*(($C$47)+Model!$C$6*($C$48)))-($C$51))/Model!$C$7)^2)/2)/SQRT(2*PI()))))) -> 734.29574 | N60: =$C$49+$C$45*((Model!$C$5*(($C60)+Model!$C$6*(G$54)))-(Model!$C$5*(($C$47)+Model!$C$6*($C$48)))-$C$46*(((((Model!$C$5*(($C60)+Model!$C$6*(G$54)))-($C$50))*NORMSDIST(((Model!$C$5*(($C60)+Model!$C$6*(G$54)))-($C$50))/Model!$C$7)+Model!$C$7*EXP(-((((Model!$C$5*(($C60)+Model!$C$6*(G$54)))-($C$50))/Model!$C$7)^2)/2)/SQRT(2*PI()))-(((Model!$C$5*(($C60)+Model!$C$6*(G$54)))-($C$51))*NORMSDIST(((Model!$C$5*(($C60)+Model!$C$6*(G$54)))-($C$51))/Model!$C$7)+Model!$C$7*EXP(-((((Model!$C$5*(($C60)+Model!$C$6*(G$54)))-($C$51))/Model!$C$7)^2)/2)/SQRT(2*PI())))-((((Model!$C$5*(($C$47)+Model!$C$6*($C$48)))-($C$50))*NORMSDIST(((Model!$C$5*(($C$47)+Model!$C$6*($C$48)))-($C$50))/Model!$C$7)+Model!$C$7*EXP(-((((Model!$C$5*(($C$47)+Model!$C$6*($C$48)))-($C$50))/Model!$C$7)^2)/2)/SQRT(2*PI()))-(((Model!$C$5*(($C$47)+Model!$C$6*($C$48)))-($C$51))*NORMSDIST(((Model!$C$5*(($C$47)+Model!$C$6*($C$48)))-($C$51))/Model!$C$7)+Model!$C$7*EXP(-((((Model!$C$5*(($C$47)+Model!$C$6*($C$48)))-($C$51))/Model!$C$7)^2)/2)/SQRT(2*PI()))))) -> 763.36254 | O60: =$C$49+$C$45*((Model!$C$5*(($C60)+Model!$C$6*(H$54)))-(Model!$C$5*(($C$47)+Model!$C$6*($C$48)))-$C$46*(((((Model!$C$5*(($C60)+Model!$C$6*(H$54)))-($C$50))*NORMSDIST(((Model!$C$5*(($C60)+Model!$C$6*(H$54)))-($C$50))/Model!$C$7)+Model!$C$7*EXP(-((((Model!$C$5*(($C60)+Model!$C$6*(H$54)))-($C$50))/Model!$C$7)^2)/2)/SQRT(2*PI()))-(((Model!$C$5*(($C60)+Model!$C$6*(H$54)))-($C$51))*NORMSDIST(((Model!$C$5*(($C60)+Model!$C$6*(H$54)))-($C$51))/Model!$C$7)+Model!$C$7*EXP(-((((Model!$C$5*(($C60)+Model!$C$6*(H$54)))-($C$51))/Model!$C$7)^2)/2)/SQRT(2*PI())))-((((Model!$C$5*(($C$47)+Model!$C$6*($C$48)))-($C$50))*NORMSDIST(((Model!$C$5*(($C$47)+Model!$C$6*($C$48)))-($C$50))/Model!$C$7)+Model!$C$7*EXP(-((((Model!$C$5*(($C$47)+Model!$C$6*($C$48)))-($C$50))/Model!$C$7)^2)/2)/SQRT(2*PI()))-(((Model!$C$5*(($C$47)+Model!$C$6*($C$48)))-($C$51))*NORMSDIST(((Model!$C$5*(($C$47)+Model!$C$6*($C$48)))-($C$51))/Model!$C$7)+Model!$C$7*EXP(-((((Model!$C$5*(($C$47)+Model!$C$6*($C$48)))-($C$51))/Model!$C$7)^2)/2)/SQRT(2*PI()))))) -> 789.99447 | Q60: =C60 -> 51 | R60: =K60-D60 -> -15.221772 | S60: =L60-E60 -> -16.010709 | T60: =M60-F60 -> -17.704259 | U60: =N60-G60 -> -13.637464 | V60: =O60-H60 -> -5.0055278
C61: 41 | D61: 617 | E61: 651 | F61: 685 | G61: 719 | H61: 750 | J61: =C61 -> 41 | K61: =$C$49+$C$45*((Model!$C$5*(($C61)+Model!$C$6*(D$54)))-(Model!$C$5*(($C$47)+Model!$C$6*($C$48)))-$C$46*(((((Model!$C$5*(($C61)+Model!$C$6*(D$54)))-($C$50))*NORMSDIST(((Model!$C$5*(($C61)+Model!$C$6*(D$54)))-($C$50))/Model!$C$7)+Model!$C$7*EXP(-((((Model!$C$5*(($C61)+Model!$C$6*(D$54)))-($C$50))/Model!$C$7)^2)/2)/SQRT(2*PI()))-(((Model!$C$5*(($C61)+Model!$C$6*(D$54)))-($C$51))*NORMSDIST(((Model!$C$5*(($C61)+Model!$C$6*(D$54)))-($C$51))/Model!$C$7)+Model!$C$7*EXP(-((((Model!$C$5*(($C61)+Model!$C$6*(D$54)))-($C$51))/Model!$C$7)^2)/2)/SQRT(2*PI())))-((((Model!$C$5*(($C$47)+Model!$C$6*($C$48)))-($C$50))*NORMSDIST(((Model!$C$5*(($C$47)+Model!$C$6*($C$48)))-($C$50))/Model!$C$7)+Model!$C$7*EXP(-((((Model!$C$5*(($C$47)+Model!$C$6*($C$48)))-($C$50))/Model!$C$7)^2)/2)/SQRT(2*PI()))-(((Model!$C$5*(($C$47)+Model!$C$6*($C$48)))-($C$51))*NORMSDIST(((Model!$C$5*(($C$47)+Model!$C$6*($C$48)))-($C$51))/Model!$C$7)+Model!$C$7*EXP(-((((Model!$C$5*(($C$47)+Model!$C$6*($C$48)))-($C$51))/Model!$C$7)^2)/2)/SQRT(2*PI()))))) -> 608.66284 | L61: =$C$49+$C$45*((Model!$C$5*(($C61)+Model!$C$6*(E$54)))-(Model!$C$5*(($C$47)+Model!$C$6*($C$48)))-$C$46*(((((Model!$C$5*(($C61)+Model!$C$6*(E$54)))-($C$50))*NORMSDIST(((Model!$C$5*(($C61)+Model!$C$6*(E$54)))-($C$50))/Model!$C$7)+Model!$C$7*EXP(-((((Model!$C$5*(($C61)+Model!$C$6*(E$54)))-($C$50))/Model!$C$7)^2)/2)/SQRT(2*PI()))-(((Model!$C$5*(($C61)+Model!$C$6*(E$54)))-($C$51))*NORMSDIST(((Model!$C$5*(($C61)+Model!$C$6*(E$54)))-($C$51))/Model!$C$7)+Model!$C$7*EXP(-((((Model!$C$5*(($C61)+Model!$C$6*(E$54)))-($C$51))/Model!$C$7)^2)/2)/SQRT(2*PI())))-((((Model!$C$5*(($C$47)+Model!$C$6*($C$48)))-($C$50))*NORMSDIST(((Model!$C$5*(($C$47)+Model!$C$6*($C$48)))-($C$50))/Model!$C$7)+Model!$C$7*EXP(-((((Model!$C$5*(($C$47)+Model!$C$6*($C$48)))-($C$50))/Model!$C$7)^2)/2)/SQRT(2*PI()))-(((Model!$C$5*(($C$47)+Model!$C$6*($C$48)))-($C$51))*NORMSDIST(((Model!$C$5*(($C$47)+Model!$C$6*($C$48)))-($C$51))/Model!$C$7)+Model!$C$7*EXP(-((((Model!$C$5*(($C$47)+Model!$C$6*($C$48)))-($C$51))/Model!$C$7)^2)/2)/SQRT(2*PI()))))) -> 644.23974 | M61: =$C$49+$C$45*((Model!$C$5*(($C61)+Model!$C$6*(F$54)))-(Model!$C$5*(($C$47)+Model!$C$6*($C$48)))-$C$46*(((((Model!$C$5*(($C61)+Model!$C$6*(F$54)))-($C$50))*NORMSDIST(((Model!$C$5*(($C61)+Model!$C$6*(F$54)))-($C$50))/Model!$C$7)+Model!$C$7*EXP(-((((Model!$C$5*(($C61)+Model!$C$6*(F$54)))-($C$50))/Model!$C$7)^2)/2)/SQRT(2*PI()))-(((Model!$C$5*(($C61)+Model!$C$6*(F$54)))-($C$51))*NORMSDIST(((Model!$C$5*(($C61)+Model!$C$6*(F$54)))-($C$51))/Model!$C$7)+Model!$C$7*EXP(-((((Model!$C$5*(($C61)+Model!$C$6*(F$54)))-($C$51))/Model!$C$7)^2)/2)/SQRT(2*PI())))-((((Model!$C$5*(($C$47)+Model!$C$6*($C$48)))-($C$50))*NORMSDIST(((Model!$C$5*(($C$47)+Model!$C$6*($C$48)))-($C$50))/Model!$C$7)+Model!$C$7*EXP(-((((Model!$C$5*(($C$47)+Model!$C$6*($C$48)))-($C$50))/Model!$C$7)^2)/2)/SQRT(2*PI()))-(((Model!$C$5*(($C$47)+Model!$C$6*($C$48)))-($C$51))*NORMSDIST(((Model!$C$5*(($C$47)+Model!$C$6*($C$48)))-($C$51))/Model!$C$7)+Model!$C$7*EXP(-((((Model!$C$5*(($C$47)+Model!$C$6*($C$48)))-($C$51))/Model!$C$7)^2)/2)/SQRT(2*PI()))))) -> 678.60378 | N61: =$C$49+$C$45*((Model!$C$5*(($C61)+Model!$C$6*(G$54)))-(Model!$C$5*(($C$47)+Model!$C$6*($C$48)))-$C$46*(((((Model!$C$5*(($C61)+Model!$C$6*(G$54)))-($C$50))*NORMSDIST(((Model!$C$5*(($C61)+Model!$C$6*(G$54)))-($C$50))/Model!$C$7)+Model!$C$7*EXP(-((((Model!$C$5*(($C61)+Model!$C$6*(G$54)))-($C$50))/Model!$C$7)^2)/2)/SQRT(2*PI()))-(((Model!$C$5*(($C61)+Model!$C$6*(G$54)))-($C$51))*NORMSDIST(((Model!$C$5*(($C61)+Model!$C$6*(G$54)))-($C$51))/Model!$C$7)+Model!$C$7*EXP(-((((Model!$C$5*(($C61)+Model!$C$6*(G$54)))-($C$51))/Model!$C$7)^2)/2)/SQRT(2*PI())))-((((Model!$C$5*(($C$47)+Model!$C$6*($C$48)))-($C$50))*NORMSDIST(((Model!$C$5*(($C$47)+Model!$C$6*($C$48)))-($C$50))/Model!$C$7)+Model!$C$7*EXP(-((((Model!$C$5*(($C$47)+Model!$C$6*($C$48)))-($C$50))/Model!$C$7)^2)/2)/SQRT(2*PI()))-(((Model!$C$5*(($C$47)+Model!$C$6*($C$48)))-($C$51))*NORMSDIST(((Model!$C$5*(($C$47)+Model!$C$6*($C$48)))-($C$51))/Model!$C$7)+Model!$C$7*EXP(-((((Model!$C$5*(($C$47)+Model!$C$6*($C$48)))-($C$51))/Model!$C$7)^2)/2)/SQRT(2*PI()))))) -> 711.35509 | O61: =$C$49+$C$45*((Model!$C$5*(($C61)+Model!$C$6*(H$54)))-(Model!$C$5*(($C$47)+Model!$C$6*($C$48)))-$C$46*(((((Model!$C$5*(($C61)+Model!$C$6*(H$54)))-($C$50))*NORMSDIST(((Model!$C$5*(($C61)+Model!$C$6*(H$54)))-($C$50))/Model!$C$7)+Model!$C$7*EXP(-((((Model!$C$5*(($C61)+Model!$C$6*(H$54)))-($C$50))/Model!$C$7)^2)/2)/SQRT(2*PI()))-(((Model!$C$5*(($C61)+Model!$C$6*(H$54)))-($C$51))*NORMSDIST(((Model!$C$5*(($C61)+Model!$C$6*(H$54)))-($C$51))/Model!$C$7)+Model!$C$7*EXP(-((((Model!$C$5*(($C61)+Model!$C$6*(H$54)))-($C$51))/Model!$C$7)^2)/2)/SQRT(2*PI())))-((((Model!$C$5*(($C$47)+Model!$C$6*($C$48)))-($C$50))*NORMSDIST(((Model!$C$5*(($C$47)+Model!$C$6*($C$48)))-($C$50))/Model!$C$7)+Model!$C$7*EXP(-((((Model!$C$5*(($C$47)+Model!$C$6*($C$48)))-($C$50))/Model!$C$7)^2)/2)/SQRT(2*PI()))-(((Model!$C$5*(($C$47)+Model!$C$6*($C$48)))-($C$51))*NORMSDIST(((Model!$C$5*(($C$47)+Model!$C$6*($C$48)))-($C$51))/Model!$C$7)+Model!$C$7*EXP(-((((Model!$C$5*(($C$47)+Model!$C$6*($C$48)))-($C$51))/Model!$C$7)^2)/2)/SQRT(2*PI()))))) -> 742.1053 | Q61: =C61 -> 41 | R61: =K61-D61 -> -8.3371636 | S61: =L61-E61 -> -6.7602569 | T61: =M61-F61 -> -6.3962247 | U61: =N61-G61 -> -7.6449086 | V61: =O61-H61 -> -7.8947019
B62: Naive model SSE | C62: =($C$49+$C$45*(1-$C$46)*Model!$C$5*((C55-$C$47)+(D54-$C$48))-D55)^2+($C$49+$C$45*(1-$C$46)*Model!$C$5*((C55-$C$47)+(E54-$C$48))-E55)^2+($C$49+$C$45*(1-$C$46)*Model!$C$5*((C55-$C$47)+(F54-$C$48))-F55)^2+($C$49+$C$45*(1-$C$46)*Model!$C$5*((C55-$C$47)+(G54-$C$48))-G55)^2+($C$49+$C$45*(1-$C$46)*Model!$C$5*((C55-$C$47)+(H54-$C$48))-H55)^2+($C$49+$C$45*(1-$C$46)*Model!$C$5*((C56-$C$47)+(D54-$C$48))-D56)^2+($C$49+$C$45*(1-$C$46)*Model!$C$5*((C56-$C$47)+(E54-$C$48))-E56)^2+($C$49+$C$45*(1-$C$46)*Model!$C$5*((C56-$C$47)+(F54-$C$48))-F56)^2+($C$49+$C$45*(1-$C$46)*Model!$C$5*((C56-$C$47)+(G54-$C$48))-G56)^2+($C$49+$C$45*(1-$C$46)*Model!$C$5*((C56-$C$47)+(H54-$C$48))-H56)^2+($C$49+$C$45*(1-$C$46)*Model!$C$5*((C57-$C$47)+(D54-$C$48))-D57)^2+($C$49+$C$45*(1-$C$46)*Model!$C$5*((C57-$C$47)+(E54-$C$48))-E57)^2+($C$49+$C$45*(1-$C$46)*Model!$C$5*((C57-$C$47)+(F54-$C$48))-F57)^2+($C$49+$C$45*(1-$C$46)*Model!$C$5*((C57-$C$47)+(G54-$C$48))-G57)^2+($C$49+$C$45*(1-$C$46)*Model!$C$5*((C57-$C$47)+(H54-$C$48))-H57)^2+($C$49+$C$45*(1-$C$46)*Model!$C$5*((C58-$C$47)+(D54-$C$48))-D58)^2+($C$49+$C$45*(1-$C$46)*Model!$C$5*((C58-$C$47)+(E54-$C$48))-E58)^2+($C$49+$C$45*(1-$C$46)*Model!$C$5*((C58-$C$47)+(F54-$C$48))-F58)^2+($C$49+$C$45*(1-$C$46)*Model!$C$5*((C58-$C$47)+(G54-$C$48))-G58)^2+($C$49+$C$45*(1-$C$46)*Model!$C$5*((C58-$C$47)+(H54-$C$48))-H58)^2+($C$49+$C$45*(1-$C$46)*Model!$C$5*((C59-$C$47)+(D54-$C$48))-D59)^2+($C$49+$C$45*(1-$C$46)*Model!$C$5*((C59-$C$47)+(E54-$C$48))-E59)^2+($C$49+$C$45*(1-$C$46)*Model!$C$5*((C59-$C$47)+(F54-$C$48))-F59)^2+($C$49+$C$45*(1-$C$46)*Model!$C$5*((C59-$C$47)+(G54-$C$48))-G59)^2+($C$49+$C$45*(1-$C$46)*Model!$C$5*((C59-$C$47)+(H54-$C$48))-H59)^2+($C$49+$C$45*(1-$C$46)*Model!$C$5*((C60-$C$47)+(D54-$C$48))-D60)^2+($C$49+$C$45*(1-$C$46)*Model!$C$5*((C60-$C$47)+(E54-$C$48))-E60)^2+($C$49+$C$45*(1-$C$46)*Model!$C$5*((C60-$C$47)+(F54-$C$48))-F60)^2+($C$49+$C$45*(1-$C$46)*Model!$C$5*((C60-$C$47)+(G54-$C$48))-G60)^2+($C$49+$C$45*(1-$C$46)*Model!$C$5*((C60-$C$47)+(H54-$C$48))-H60)^2+($C$49+$C$45*(1-$C$46)*Model!$C$5*((C61-$C$47)+(D54-$C$48))-D61)^2+($C$49+$C$45*(1-$C$46)*Model!$C$5*((C61-$C$47)+(E54-$C$48))-E61)^2+($C$49+$C$45*(1-$C$46)*Model!$C$5*((C61-$C$47)+(F54-$C$48))-F61)^2+($C$49+$C$45*(1-$C$46)*Model!$C$5*((C61-$C$47)+(G54-$C$48))-G61)^2+($C$49+$C$45*(1-$C$46)*Model!$C$5*((C61-$C$47)+(H54-$C$48))-H61)^2 -> 120569.16
B65: FY25@2025-04-24 | C65: Source: Q1 2025 results presentation
B66: Hedge year | C66: 2025
B67: Months not yet realised | C67: 8
B68: s | C68: =C67/12 -> 0.66666667
B69: Hedge ratio h | C69: 0.81
B70: Base Brent | C70: 65
B71: Base crack | C71: 19
B72: P0 (centre cell) | C72: =INDEX(D78:H84,MATCH(C70,C78:C84,0),MATCH(C71,D77:H77,0)) -> 807
B73: K1 | C73: =INDEX($C$6:$C$8,MATCH(C66,$B$6:$B$8,0)) -> 690
B74: K2 | C74: =INDEX($D$6:$D$8,MATCH(C66,$B$6:$B$8,0)) -> 1005
C76: Published | J76: Model | Q76: Model − published
C77: Brent \ crack | D77: 9 | E77: 14 | F77: 19 | G77: 24 | H77: 29 | J77: Brent \ crack | K77: =D77 -> 9 | L77: =E77 -> 14 | M77: =F77 -> 19 | N77: =G77 -> 24 | O77: =H77 -> 29 | Q77: Brent \ crack | R77: =D77 -> 9 | S77: =E77 -> 14 | T77: =F77 -> 19 | U77: =G77 -> 24 | V77: =H77 -> 29
C78: 95 | D78: 874 | E78: 893 | F78: 906 | G78: 920 | H78: 934 | J78: =C78 -> 95 | K78: =$C$72+$C$68*((Model!$C$5*(($C78)+Model!$C$6*(D$77)))-(Model!$C$5*(($C$70)+Model!$C$6*($C$71)))-$C$69*(((((Model!$C$5*(($C78)+Model!$C$6*(D$77)))-($C$73))*NORMSDIST(((Model!$C$5*(($C78)+Model!$C$6*(D$77)))-($C$73))/Model!$C$7)+Model!$C$7*EXP(-((((Model!$C$5*(($C78)+Model!$C$6*(D$77)))-($C$73))/Model!$C$7)^2)/2)/SQRT(2*PI()))-(((Model!$C$5*(($C78)+Model!$C$6*(D$77)))-($C$74))*NORMSDIST(((Model!$C$5*(($C78)+Model!$C$6*(D$77)))-($C$74))/Model!$C$7)+Model!$C$7*EXP(-((((Model!$C$5*(($C78)+Model!$C$6*(D$77)))-($C$74))/Model!$C$7)^2)/2)/SQRT(2*PI())))-((((Model!$C$5*(($C$70)+Model!$C$6*($C$71)))-($C$73))*NORMSDIST(((Model!$C$5*(($C$70)+Model!$C$6*($C$71)))-($C$73))/Model!$C$7)+Model!$C$7*EXP(-((((Model!$C$5*(($C$70)+Model!$C$6*($C$71)))-($C$73))/Model!$C$7)^2)/2)/SQRT(2*PI()))-(((Model!$C$5*(($C$70)+Model!$C$6*($C$71)))-($C$74))*NORMSDIST(((Model!$C$5*(($C$70)+Model!$C$6*($C$71)))-($C$74))/Model!$C$7)+Model!$C$7*EXP(-((((Model!$C$5*(($C$70)+Model!$C$6*($C$71)))-($C$74))/Model!$C$7)^2)/2)/SQRT(2*PI()))))) -> 860.89105 | L78: =$C$72+$C$68*((Model!$C$5*(($C78)+Model!$C$6*(E$77)))-(Model!$C$5*(($C$70)+Model!$C$6*($C$71)))-$C$69*(((((Model!$C$5*(($C78)+Model!$C$6*(E$77)))-($C$73))*NORMSDIST(((Model!$C$5*(($C78)+Model!$C$6*(E$77)))-($C$73))/Model!$C$7)+Model!$C$7*EXP(-((((Model!$C$5*(($C78)+Model!$C$6*(E$77)))-($C$73))/Model!$C$7)^2)/2)/SQRT(2*PI()))-(((Model!$C$5*(($C78)+Model!$C$6*(E$77)))-($C$74))*NORMSDIST(((Model!$C$5*(($C78)+Model!$C$6*(E$77)))-($C$74))/Model!$C$7)+Model!$C$7*EXP(-((((Model!$C$5*(($C78)+Model!$C$6*(E$77)))-($C$74))/Model!$C$7)^2)/2)/SQRT(2*PI())))-((((Model!$C$5*(($C$70)+Model!$C$6*($C$71)))-($C$73))*NORMSDIST(((Model!$C$5*(($C$70)+Model!$C$6*($C$71)))-($C$73))/Model!$C$7)+Model!$C$7*EXP(-((((Model!$C$5*(($C$70)+Model!$C$6*($C$71)))-($C$73))/Model!$C$7)^2)/2)/SQRT(2*PI()))-(((Model!$C$5*(($C$70)+Model!$C$6*($C$71)))-($C$74))*NORMSDIST(((Model!$C$5*(($C$70)+Model!$C$6*($C$71)))-($C$74))/Model!$C$7)+Model!$C$7*EXP(-((((Model!$C$5*(($C$70)+Model!$C$6*($C$71)))-($C$74))/Model!$C$7)^2)/2)/SQRT(2*PI()))))) -> 876.06624 | M78: =$C$72+$C$68*((Model!$C$5*(($C78)+Model!$C$6*(F$77)))-(Model!$C$5*(($C$70)+Model!$C$6*($C$71)))-$C$69*(((((Model!$C$5*(($C78)+Model!$C$6*(F$77)))-($C$73))*NORMSDIST(((Model!$C$5*(($C78)+Model!$C$6*(F$77)))-($C$73))/Model!$C$7)+Model!$C$7*EXP(-((((Model!$C$5*(($C78)+Model!$C$6*(F$77)))-($C$73))/Model!$C$7)^2)/2)/SQRT(2*PI()))-(((Model!$C$5*(($C78)+Model!$C$6*(F$77)))-($C$74))*NORMSDIST(((Model!$C$5*(($C78)+Model!$C$6*(F$77)))-($C$74))/Model!$C$7)+Model!$C$7*EXP(-((((Model!$C$5*(($C78)+Model!$C$6*(F$77)))-($C$74))/Model!$C$7)^2)/2)/SQRT(2*PI())))-((((Model!$C$5*(($C$70)+Model!$C$6*($C$71)))-($C$73))*NORMSDIST(((Model!$C$5*(($C$70)+Model!$C$6*($C$71)))-($C$73))/Model!$C$7)+Model!$C$7*EXP(-((((Model!$C$5*(($C$70)+Model!$C$6*($C$71)))-($C$73))/Model!$C$7)^2)/2)/SQRT(2*PI()))-(((Model!$C$5*(($C$70)+Model!$C$6*($C$71)))-($C$74))*NORMSDIST(((Model!$C$5*(($C$70)+Model!$C$6*($C$71)))-($C$74))/Model!$C$7)+Model!$C$7*EXP(-((((Model!$C$5*(($C$70)+Model!$C$6*($C$71)))-($C$74))/Model!$C$7)^2)/2)/SQRT(2*PI()))))) -> 891.68226 | N78: =$C$72+$C$68*((Model!$C$5*(($C78)+Model!$C$6*(G$77)))-(Model!$C$5*(($C$70)+Model!$C$6*($C$71)))-$C$69*(((((Model!$C$5*(($C78)+Model!$C$6*(G$77)))-($C$73))*NORMSDIST(((Model!$C$5*(($C78)+Model!$C$6*(G$77)))-($C$73))/Model!$C$7)+Model!$C$7*EXP(-((((Model!$C$5*(($C78)+Model!$C$6*(G$77)))-($C$73))/Model!$C$7)^2)/2)/SQRT(2*PI()))-(((Model!$C$5*(($C78)+Model!$C$6*(G$77)))-($C$74))*NORMSDIST(((Model!$C$5*(($C78)+Model!$C$6*(G$77)))-($C$74))/Model!$C$7)+Model!$C$7*EXP(-((((Model!$C$5*(($C78)+Model!$C$6*(G$77)))-($C$74))/Model!$C$7)^2)/2)/SQRT(2*PI())))-((((Model!$C$5*(($C$70)+Model!$C$6*($C$71)))-($C$73))*NORMSDIST(((Model!$C$5*(($C$70)+Model!$C$6*($C$71)))-($C$73))/Model!$C$7)+Model!$C$7*EXP(-((((Model!$C$5*(($C$70)+Model!$C$6*($C$71)))-($C$73))/Model!$C$7)^2)/2)/SQRT(2*PI()))-(((Model!$C$5*(($C$70)+Model!$C$6*($C$71)))-($C$74))*NORMSDIST(((Model!$C$5*(($C$70)+Model!$C$6*($C$71)))-($C$74))/Model!$C$7)+Model!$C$7*EXP(-((((Model!$C$5*(($C$70)+Model!$C$6*($C$71)))-($C$74))/Model!$C$7)^2)/2)/SQRT(2*PI()))))) -> 908.39472 | O78: =$C$72+$C$68*((Model!$C$5*(($C78)+Model!$C$6*(H$77)))-(Model!$C$5*(($C$70)+Model!$C$6*($C$71)))-$C$69*(((((Model!$C$5*(($C78)+Model!$C$6*(H$77)))-($C$73))*NORMSDIST(((Model!$C$5*(($C78)+Model!$C$6*(H$77)))-($C$73))/Model!$C$7)+Model!$C$7*EXP(-((((Model!$C$5*(($C78)+Model!$C$6*(H$77)))-($C$73))/Model!$C$7)^2)/2)/SQRT(2*PI()))-(((Model!$C$5*(($C78)+Model!$C$6*(H$77)))-($C$74))*NORMSDIST(((Model!$C$5*(($C78)+Model!$C$6*(H$77)))-($C$74))/Model!$C$7)+Model!$C$7*EXP(-((((Model!$C$5*(($C78)+Model!$C$6*(H$77)))-($C$74))/Model!$C$7)^2)/2)/SQRT(2*PI())))-((((Model!$C$5*(($C$70)+Model!$C$6*($C$71)))-($C$73))*NORMSDIST(((Model!$C$5*(($C$70)+Model!$C$6*($C$71)))-($C$73))/Model!$C$7)+Model!$C$7*EXP(-((((Model!$C$5*(($C$70)+Model!$C$6*($C$71)))-($C$73))/Model!$C$7)^2)/2)/SQRT(2*PI()))-(((Model!$C$5*(($C$70)+Model!$C$6*($C$71)))-($C$74))*NORMSDIST(((Model!$C$5*(($C$70)+Model!$C$6*($C$71)))-($C$74))/Model!$C$7)+Model!$C$7*EXP(-((((Model!$C$5*(($C$70)+Model!$C$6*($C$71)))-($C$74))/Model!$C$7)^2)/2)/SQRT(2*PI()))))) -> 926.71434 | Q78: =C78 -> 95 | R78: =K78-D78 -> -13.108948 | S78: =L78-E78 -> -16.933761 | T78: =M78-F78 -> -14.317737 | U78: =N78-G78 -> -11.605284 | V78: =O78-H78 -> -7.2856578
C79: 85 | D79: 840 | E79: 867 | F79: 890 | G79: 907 | H79: 920 | J79: =C79 -> 85 | K79: =$C$72+$C$68*((Model!$C$5*(($C79)+Model!$C$6*(D$77)))-(Model!$C$5*(($C$70)+Model!$C$6*($C$71)))-$C$69*(((((Model!$C$5*(($C79)+Model!$C$6*(D$77)))-($C$73))*NORMSDIST(((Model!$C$5*(($C79)+Model!$C$6*(D$77)))-($C$73))/Model!$C$7)+Model!$C$7*EXP(-((((Model!$C$5*(($C79)+Model!$C$6*(D$77)))-($C$73))/Model!$C$7)^2)/2)/SQRT(2*PI()))-(((Model!$C$5*(($C79)+Model!$C$6*(D$77)))-($C$74))*NORMSDIST(((Model!$C$5*(($C79)+Model!$C$6*(D$77)))-($C$74))/Model!$C$7)+Model!$C$7*EXP(-((((Model!$C$5*(($C79)+Model!$C$6*(D$77)))-($C$74))/Model!$C$7)^2)/2)/SQRT(2*PI())))-((((Model!$C$5*(($C$70)+Model!$C$6*($C$71)))-($C$73))*NORMSDIST(((Model!$C$5*(($C$70)+Model!$C$6*($C$71)))-($C$73))/Model!$C$7)+Model!$C$7*EXP(-((((Model!$C$5*(($C$70)+Model!$C$6*($C$71)))-($C$73))/Model!$C$7)^2)/2)/SQRT(2*PI()))-(((Model!$C$5*(($C$70)+Model!$C$6*($C$71)))-($C$74))*NORMSDIST(((Model!$C$5*(($C$70)+Model!$C$6*($C$71)))-($C$74))/Model!$C$7)+Model!$C$7*EXP(-((((Model!$C$5*(($C$70)+Model!$C$6*($C$71)))-($C$74))/Model!$C$7)^2)/2)/SQRT(2*PI()))))) -> 833.44272 | L79: =$C$72+$C$68*((Model!$C$5*(($C79)+Model!$C$6*(E$77)))-(Model!$C$5*(($C$70)+Model!$C$6*($C$71)))-$C$69*(((((Model!$C$5*(($C79)+Model!$C$6*(E$77)))-($C$73))*NORMSDIST(((Model!$C$5*(($C79)+Model!$C$6*(E$77)))-($C$73))/Model!$C$7)+Model!$C$7*EXP(-((((Model!$C$5*(($C79)+Model!$C$6*(E$77)))-($C$73))/Model!$C$7)^2)/2)/SQRT(2*PI()))-(((Model!$C$5*(($C79)+Model!$C$6*(E$77)))-($C$74))*NORMSDIST(((Model!$C$5*(($C79)+Model!$C$6*(E$77)))-($C$74))/Model!$C$7)+Model!$C$7*EXP(-((((Model!$C$5*(($C79)+Model!$C$6*(E$77)))-($C$74))/Model!$C$7)^2)/2)/SQRT(2*PI())))-((((Model!$C$5*(($C$70)+Model!$C$6*($C$71)))-($C$73))*NORMSDIST(((Model!$C$5*(($C$70)+Model!$C$6*($C$71)))-($C$73))/Model!$C$7)+Model!$C$7*EXP(-((((Model!$C$5*(($C$70)+Model!$C$6*($C$71)))-($C$73))/Model!$C$7)^2)/2)/SQRT(2*PI()))-(((Model!$C$5*(($C$70)+Model!$C$6*($C$71)))-($C$74))*NORMSDIST(((Model!$C$5*(($C$70)+Model!$C$6*($C$71)))-($C$74))/Model!$C$7)+Model!$C$7*EXP(-((((Model!$C$5*(($C$70)+Model!$C$6*($C$71)))-($C$74))/Model!$C$7)^2)/2)/SQRT(2*PI()))))) -> 849.53746 | M79: =$C$72+$C$68*((Model!$C$5*(($C79)+Model!$C$6*(F$77)))-(Model!$C$5*(($C$70)+Model!$C$6*($C$71)))-$C$69*(((((Model!$C$5*(($C79)+Model!$C$6*(F$77)))-($C$73))*NORMSDIST(((Model!$C$5*(($C79)+Model!$C$6*(F$77)))-($C$73))/Model!$C$7)+Model!$C$7*EXP(-((((Model!$C$5*(($C79)+Model!$C$6*(F$77)))-($C$73))/Model!$C$7)^2)/2)/SQRT(2*PI()))-(((Model!$C$5*(($C79)+Model!$C$6*(F$77)))-($C$74))*NORMSDIST(((Model!$C$5*(($C79)+Model!$C$6*(F$77)))-($C$74))/Model!$C$7)+Model!$C$7*EXP(-((((Model!$C$5*(($C79)+Model!$C$6*(F$77)))-($C$74))/Model!$C$7)^2)/2)/SQRT(2*PI())))-((((Model!$C$5*(($C$70)+Model!$C$6*($C$71)))-($C$73))*NORMSDIST(((Model!$C$5*(($C$70)+Model!$C$6*($C$71)))-($C$73))/Model!$C$7)+Model!$C$7*EXP(-((((Model!$C$5*(($C$70)+Model!$C$6*($C$71)))-($C$73))/Model!$C$7)^2)/2)/SQRT(2*PI()))-(((Model!$C$5*(($C$70)+Model!$C$6*($C$71)))-($C$74))*NORMSDIST(((Model!$C$5*(($C$70)+Model!$C$6*($C$71)))-($C$74))/Model!$C$7)+Model!$C$7*EXP(-((((Model!$C$5*(($C$70)+Model!$C$6*($C$71)))-($C$74))/Model!$C$7)^2)/2)/SQRT(2*PI()))))) -> 864.84717 | N79: =$C$72+$C$68*((Model!$C$5*(($C79)+Model!$C$6*(G$77)))-(Model!$C$5*(($C$70)+Model!$C$6*($C$71)))-$C$69*(((((Model!$C$5*(($C79)+Model!$C$6*(G$77)))-($C$73))*NORMSDIST(((Model!$C$5*(($C79)+Model!$C$6*(G$77)))-($C$73))/Model!$C$7)+Model!$C$7*EXP(-((((Model!$C$5*(($C79)+Model!$C$6*(G$77)))-($C$73))/Model!$C$7)^2)/2)/SQRT(2*PI()))-(((Model!$C$5*(($C79)+Model!$C$6*(G$77)))-($C$74))*NORMSDIST(((Model!$C$5*(($C79)+Model!$C$6*(G$77)))-($C$74))/Model!$C$7)+Model!$C$7*EXP(-((((Model!$C$5*(($C79)+Model!$C$6*(G$77)))-($C$74))/Model!$C$7)^2)/2)/SQRT(2*PI())))-((((Model!$C$5*(($C$70)+Model!$C$6*($C$71)))-($C$73))*NORMSDIST(((Model!$C$5*(($C$70)+Model!$C$6*($C$71)))-($C$73))/Model!$C$7)+Model!$C$7*EXP(-((((Model!$C$5*(($C$70)+Model!$C$6*($C$71)))-($C$73))/Model!$C$7)^2)/2)/SQRT(2*PI()))-(((Model!$C$5*(($C$70)+Model!$C$6*($C$71)))-($C$74))*NORMSDIST(((Model!$C$5*(($C$70)+Model!$C$6*($C$71)))-($C$74))/Model!$C$7)+Model!$C$7*EXP(-((((Model!$C$5*(($C$70)+Model!$C$6*($C$71)))-($C$74))/Model!$C$7)^2)/2)/SQRT(2*PI()))))) -> 880.0691 | O79: =$C$72+$C$68*((Model!$C$5*(($C79)+Model!$C$6*(H$77)))-(Model!$C$5*(($C$70)+Model!$C$6*($C$71)))-$C$69*(((((Model!$C$5*(($C79)+Model!$C$6*(H$77)))-($C$73))*NORMSDIST(((Model!$C$5*(($C79)+Model!$C$6*(H$77)))-($C$73))/Model!$C$7)+Model!$C$7*EXP(-((((Model!$C$5*(($C79)+Model!$C$6*(H$77)))-($C$73))/Model!$C$7)^2)/2)/SQRT(2*PI()))-(((Model!$C$5*(($C79)+Model!$C$6*(H$77)))-($C$74))*NORMSDIST(((Model!$C$5*(($C79)+Model!$C$6*(H$77)))-($C$74))/Model!$C$7)+Model!$C$7*EXP(-((((Model!$C$5*(($C79)+Model!$C$6*(H$77)))-($C$74))/Model!$C$7)^2)/2)/SQRT(2*PI())))-((((Model!$C$5*(($C$70)+Model!$C$6*($C$71)))-($C$73))*NORMSDIST(((Model!$C$5*(($C$70)+Model!$C$6*($C$71)))-($C$73))/Model!$C$7)+Model!$C$7*EXP(-((((Model!$C$5*(($C$70)+Model!$C$6*($C$71)))-($C$73))/Model!$C$7)^2)/2)/SQRT(2*PI()))-(((Model!$C$5*(($C$70)+Model!$C$6*($C$71)))-($C$74))*NORMSDIST(((Model!$C$5*(($C$70)+Model!$C$6*($C$71)))-($C$74))/Model!$C$7)+Model!$C$7*EXP(-((((Model!$C$5*(($C$70)+Model!$C$6*($C$71)))-($C$74))/Model!$C$7)^2)/2)/SQRT(2*PI()))))) -> 895.91251 | Q79: =C79 -> 85 | R79: =K79-D79 -> -6.5572787 | S79: =L79-E79 -> -17.462544 | T79: =M79-F79 -> -25.152828 | U79: =N79-G79 -> -26.930896 | V79: =O79-H79 -> -24.087486
C80: 75 | D80: 809 | E80: 826 | F80: 851 | G80: 877 | H80: 898 | J80: =C80 -> 75 | K80: =$C$72+$C$68*((Model!$C$5*(($C80)+Model!$C$6*(D$77)))-(Model!$C$5*(($C$70)+Model!$C$6*($C$71)))-$C$69*(((((Model!$C$5*(($C80)+Model!$C$6*(D$77)))-($C$73))*NORMSDIST(((Model!$C$5*(($C80)+Model!$C$6*(D$77)))-($C$73))/Model!$C$7)+Model!$C$7*EXP(-((((Model!$C$5*(($C80)+Model!$C$6*(D$77)))-($C$73))/Model!$C$7)^2)/2)/SQRT(2*PI()))-(((Model!$C$5*(($C80)+Model!$C$6*(D$77)))-($C$74))*NORMSDIST(((Model!$C$5*(($C80)+Model!$C$6*(D$77)))-($C$74))/Model!$C$7)+Model!$C$7*EXP(-((((Model!$C$5*(($C80)+Model!$C$6*(D$77)))-($C$74))/Model!$C$7)^2)/2)/SQRT(2*PI())))-((((Model!$C$5*(($C$70)+Model!$C$6*($C$71)))-($C$73))*NORMSDIST(((Model!$C$5*(($C$70)+Model!$C$6*($C$71)))-($C$73))/Model!$C$7)+Model!$C$7*EXP(-((((Model!$C$5*(($C$70)+Model!$C$6*($C$71)))-($C$73))/Model!$C$7)^2)/2)/SQRT(2*PI()))-(((Model!$C$5*(($C$70)+Model!$C$6*($C$71)))-($C$74))*NORMSDIST(((Model!$C$5*(($C$70)+Model!$C$6*($C$71)))-($C$74))/Model!$C$7)+Model!$C$7*EXP(-((((Model!$C$5*(($C$70)+Model!$C$6*($C$71)))-($C$74))/Model!$C$7)^2)/2)/SQRT(2*PI()))))) -> 801.92184 | L80: =$C$72+$C$68*((Model!$C$5*(($C80)+Model!$C$6*(E$77)))-(Model!$C$5*(($C$70)+Model!$C$6*($C$71)))-$C$69*(((((Model!$C$5*(($C80)+Model!$C$6*(E$77)))-($C$73))*NORMSDIST(((Model!$C$5*(($C80)+Model!$C$6*(E$77)))-($C$73))/Model!$C$7)+Model!$C$7*EXP(-((((Model!$C$5*(($C80)+Model!$C$6*(E$77)))-($C$73))/Model!$C$7)^2)/2)/SQRT(2*PI()))-(((Model!$C$5*(($C80)+Model!$C$6*(E$77)))-($C$74))*NORMSDIST(((Model!$C$5*(($C80)+Model!$C$6*(E$77)))-($C$74))/Model!$C$7)+Model!$C$7*EXP(-((((Model!$C$5*(($C80)+Model!$C$6*(E$77)))-($C$74))/Model!$C$7)^2)/2)/SQRT(2*PI())))-((((Model!$C$5*(($C$70)+Model!$C$6*($C$71)))-($C$73))*NORMSDIST(((Model!$C$5*(($C$70)+Model!$C$6*($C$71)))-($C$73))/Model!$C$7)+Model!$C$7*EXP(-((((Model!$C$5*(($C$70)+Model!$C$6*($C$71)))-($C$73))/Model!$C$7)^2)/2)/SQRT(2*PI()))-(((Model!$C$5*(($C$70)+Model!$C$6*($C$71)))-($C$74))*NORMSDIST(((Model!$C$5*(($C$70)+Model!$C$6*($C$71)))-($C$74))/Model!$C$7)+Model!$C$7*EXP(-((((Model!$C$5*(($C$70)+Model!$C$6*($C$71)))-($C$74))/Model!$C$7)^2)/2)/SQRT(2*PI()))))) -> 820.68865 | M80: =$C$72+$C$68*((Model!$C$5*(($C80)+Model!$C$6*(F$77)))-(Model!$C$5*(($C$70)+Model!$C$6*($C$71)))-$C$69*(((((Model!$C$5*(($C80)+Model!$C$6*(F$77)))-($C$73))*NORMSDIST(((Model!$C$5*(($C80)+Model!$C$6*(F$77)))-($C$73))/Model!$C$7)+Model!$C$7*EXP(-((((Model!$C$5*(($C80)+Model!$C$6*(F$77)))-($C$73))/Model!$C$7)^2)/2)/SQRT(2*PI()))-(((Model!$C$5*(($C80)+Model!$C$6*(F$77)))-($C$74))*NORMSDIST(((Model!$C$5*(($C80)+Model!$C$6*(F$77)))-($C$74))/Model!$C$7)+Model!$C$7*EXP(-((((Model!$C$5*(($C80)+Model!$C$6*(F$77)))-($C$74))/Model!$C$7)^2)/2)/SQRT(2*PI())))-((((Model!$C$5*(($C$70)+Model!$C$6*($C$71)))-($C$73))*NORMSDIST(((Model!$C$5*(($C$70)+Model!$C$6*($C$71)))-($C$73))/Model!$C$7)+Model!$C$7*EXP(-((((Model!$C$5*(($C$70)+Model!$C$6*($C$71)))-($C$73))/Model!$C$7)^2)/2)/SQRT(2*PI()))-(((Model!$C$5*(($C$70)+Model!$C$6*($C$71)))-($C$74))*NORMSDIST(((Model!$C$5*(($C$70)+Model!$C$6*($C$71)))-($C$74))/Model!$C$7)+Model!$C$7*EXP(-((((Model!$C$5*(($C$70)+Model!$C$6*($C$71)))-($C$74))/Model!$C$7)^2)/2)/SQRT(2*PI()))))) -> 837.75275 | N80: =$C$72+$C$68*((Model!$C$5*(($C80)+Model!$C$6*(G$77)))-(Model!$C$5*(($C$70)+Model!$C$6*($C$71)))-$C$69*(((((Model!$C$5*(($C80)+Model!$C$6*(G$77)))-($C$73))*NORMSDIST(((Model!$C$5*(($C80)+Model!$C$6*(G$77)))-($C$73))/Model!$C$7)+Model!$C$7*EXP(-((((Model!$C$5*(($C80)+Model!$C$6*(G$77)))-($C$73))/Model!$C$7)^2)/2)/SQRT(2*PI()))-(((Model!$C$5*(($C80)+Model!$C$6*(G$77)))-($C$74))*NORMSDIST(((Model!$C$5*(($C80)+Model!$C$6*(G$77)))-($C$74))/Model!$C$7)+Model!$C$7*EXP(-((((Model!$C$5*(($C80)+Model!$C$6*(G$77)))-($C$74))/Model!$C$7)^2)/2)/SQRT(2*PI())))-((((Model!$C$5*(($C$70)+Model!$C$6*($C$71)))-($C$73))*NORMSDIST(((Model!$C$5*(($C$70)+Model!$C$6*($C$71)))-($C$73))/Model!$C$7)+Model!$C$7*EXP(-((((Model!$C$5*(($C$70)+Model!$C$6*($C$71)))-($C$73))/Model!$C$7)^2)/2)/SQRT(2*PI()))-(((Model!$C$5*(($C$70)+Model!$C$6*($C$71)))-($C$74))*NORMSDIST(((Model!$C$5*(($C$70)+Model!$C$6*($C$71)))-($C$74))/Model!$C$7)+Model!$C$7*EXP(-((((Model!$C$5*(($C$70)+Model!$C$6*($C$71)))-($C$74))/Model!$C$7)^2)/2)/SQRT(2*PI()))))) -> 853.57989 | O80: =$C$72+$C$68*((Model!$C$5*(($C80)+Model!$C$6*(H$77)))-(Model!$C$5*(($C$70)+Model!$C$6*($C$71)))-$C$69*(((((Model!$C$5*(($C80)+Model!$C$6*(H$77)))-($C$73))*NORMSDIST(((Model!$C$5*(($C80)+Model!$C$6*(H$77)))-($C$73))/Model!$C$7)+Model!$C$7*EXP(-((((Model!$C$5*(($C80)+Model!$C$6*(H$77)))-($C$73))/Model!$C$7)^2)/2)/SQRT(2*PI()))-(((Model!$C$5*(($C80)+Model!$C$6*(H$77)))-($C$74))*NORMSDIST(((Model!$C$5*(($C80)+Model!$C$6*(H$77)))-($C$74))/Model!$C$7)+Model!$C$7*EXP(-((((Model!$C$5*(($C80)+Model!$C$6*(H$77)))-($C$74))/Model!$C$7)^2)/2)/SQRT(2*PI())))-((((Model!$C$5*(($C$70)+Model!$C$6*($C$71)))-($C$73))*NORMSDIST(((Model!$C$5*(($C$70)+Model!$C$6*($C$71)))-($C$73))/Model!$C$7)+Model!$C$7*EXP(-((((Model!$C$5*(($C$70)+Model!$C$6*($C$71)))-($C$73))/Model!$C$7)^2)/2)/SQRT(2*PI()))-(((Model!$C$5*(($C$70)+Model!$C$6*($C$71)))-($C$74))*NORMSDIST(((Model!$C$5*(($C$70)+Model!$C$6*($C$71)))-($C$74))/Model!$C$7)+Model!$C$7*EXP(-((((Model!$C$5*(($C$70)+Model!$C$6*($C$71)))-($C$74))/Model!$C$7)^2)/2)/SQRT(2*PI()))))) -> 868.79725 | Q80: =C80 -> 75 | R80: =K80-D80 -> -7.0781634 | S80: =L80-E80 -> -5.3113461 | T80: =M80-F80 -> -13.247246 | U80: =N80-G80 -> -23.420107 | V80: =O80-H80 -> -29.202747
C81: 65 | D81: 772 | E81: 793 | F81: 807 | G81: 827 | H81: 853 | J81: =C81 -> 65 | K81: =$C$72+$C$68*((Model!$C$5*(($C81)+Model!$C$6*(D$77)))-(Model!$C$5*(($C$70)+Model!$C$6*($C$71)))-$C$69*(((((Model!$C$5*(($C81)+Model!$C$6*(D$77)))-($C$73))*NORMSDIST(((Model!$C$5*(($C81)+Model!$C$6*(D$77)))-($C$73))/Model!$C$7)+Model!$C$7*EXP(-((((Model!$C$5*(($C81)+Model!$C$6*(D$77)))-($C$73))/Model!$C$7)^2)/2)/SQRT(2*PI()))-(((Model!$C$5*(($C81)+Model!$C$6*(D$77)))-($C$74))*NORMSDIST(((Model!$C$5*(($C81)+Model!$C$6*(D$77)))-($C$74))/Model!$C$7)+Model!$C$7*EXP(-((((Model!$C$5*(($C81)+Model!$C$6*(D$77)))-($C$74))/Model!$C$7)^2)/2)/SQRT(2*PI())))-((((Model!$C$5*(($C$70)+Model!$C$6*($C$71)))-($C$73))*NORMSDIST(((Model!$C$5*(($C$70)+Model!$C$6*($C$71)))-($C$73))/Model!$C$7)+Model!$C$7*EXP(-((((Model!$C$5*(($C$70)+Model!$C$6*($C$71)))-($C$73))/Model!$C$7)^2)/2)/SQRT(2*PI()))-(((Model!$C$5*(($C$70)+Model!$C$6*($C$71)))-($C$74))*NORMSDIST(((Model!$C$5*(($C$70)+Model!$C$6*($C$71)))-($C$74))/Model!$C$7)+Model!$C$7*EXP(-((((Model!$C$5*(($C$70)+Model!$C$6*($C$71)))-($C$74))/Model!$C$7)^2)/2)/SQRT(2*PI()))))) -> 764.57628 | L81: =$C$72+$C$68*((Model!$C$5*(($C81)+Model!$C$6*(E$77)))-(Model!$C$5*(($C$70)+Model!$C$6*($C$71)))-$C$69*(((((Model!$C$5*(($C81)+Model!$C$6*(E$77)))-($C$73))*NORMSDIST(((Model!$C$5*(($C81)+Model!$C$6*(E$77)))-($C$73))/Model!$C$7)+Model!$C$7*EXP(-((((Model!$C$5*(($C81)+Model!$C$6*(E$77)))-($C$73))/Model!$C$7)^2)/2)/SQRT(2*PI()))-(((Model!$C$5*(($C81)+Model!$C$6*(E$77)))-($C$74))*NORMSDIST(((Model!$C$5*(($C81)+Model!$C$6*(E$77)))-($C$74))/Model!$C$7)+Model!$C$7*EXP(-((((Model!$C$5*(($C81)+Model!$C$6*(E$77)))-($C$74))/Model!$C$7)^2)/2)/SQRT(2*PI())))-((((Model!$C$5*(($C$70)+Model!$C$6*($C$71)))-($C$73))*NORMSDIST(((Model!$C$5*(($C$70)+Model!$C$6*($C$71)))-($C$73))/Model!$C$7)+Model!$C$7*EXP(-((((Model!$C$5*(($C$70)+Model!$C$6*($C$71)))-($C$73))/Model!$C$7)^2)/2)/SQRT(2*PI()))-(((Model!$C$5*(($C$70)+Model!$C$6*($C$71)))-($C$74))*NORMSDIST(((Model!$C$5*(($C$70)+Model!$C$6*($C$71)))-($C$74))/Model!$C$7)+Model!$C$7*EXP(-((((Model!$C$5*(($C$70)+Model!$C$6*($C$71)))-($C$74))/Model!$C$7)^2)/2)/SQRT(2*PI()))))) -> 786.79603 | M81: =$C$72+$C$68*((Model!$C$5*(($C81)+Model!$C$6*(F$77)))-(Model!$C$5*(($C$70)+Model!$C$6*($C$71)))-$C$69*(((((Model!$C$5*(($C81)+Model!$C$6*(F$77)))-($C$73))*NORMSDIST(((Model!$C$5*(($C81)+Model!$C$6*(F$77)))-($C$73))/Model!$C$7)+Model!$C$7*EXP(-((((Model!$C$5*(($C81)+Model!$C$6*(F$77)))-($C$73))/Model!$C$7)^2)/2)/SQRT(2*PI()))-(((Model!$C$5*(($C81)+Model!$C$6*(F$77)))-($C$74))*NORMSDIST(((Model!$C$5*(($C81)+Model!$C$6*(F$77)))-($C$74))/Model!$C$7)+Model!$C$7*EXP(-((((Model!$C$5*(($C81)+Model!$C$6*(F$77)))-($C$74))/Model!$C$7)^2)/2)/SQRT(2*PI())))-((((Model!$C$5*(($C$70)+Model!$C$6*($C$71)))-($C$73))*NORMSDIST(((Model!$C$5*(($C$70)+Model!$C$6*($C$71)))-($C$73))/Model!$C$7)+Model!$C$7*EXP(-((((Model!$C$5*(($C$70)+Model!$C$6*($C$71)))-($C$73))/Model!$C$7)^2)/2)/SQRT(2*PI()))-(((Model!$C$5*(($C$70)+Model!$C$6*($C$71)))-($C$74))*NORMSDIST(((Model!$C$5*(($C$70)+Model!$C$6*($C$71)))-($C$74))/Model!$C$7)+Model!$C$7*EXP(-((((Model!$C$5*(($C$70)+Model!$C$6*($C$71)))-($C$74))/Model!$C$7)^2)/2)/SQRT(2*PI()))))) -> 807 | N81: =$C$72+$C$68*((Model!$C$5*(($C81)+Model!$C$6*(G$77)))-(Model!$C$5*(($C$70)+Model!$C$6*($C$71)))-$C$69*(((((Model!$C$5*(($C81)+Model!$C$6*(G$77)))-($C$73))*NORMSDIST(((Model!$C$5*(($C81)+Model!$C$6*(G$77)))-($C$73))/Model!$C$7)+Model!$C$7*EXP(-((((Model!$C$5*(($C81)+Model!$C$6*(G$77)))-($C$73))/Model!$C$7)^2)/2)/SQRT(2*PI()))-(((Model!$C$5*(($C81)+Model!$C$6*(G$77)))-($C$74))*NORMSDIST(((Model!$C$5*(($C81)+Model!$C$6*(G$77)))-($C$74))/Model!$C$7)+Model!$C$7*EXP(-((((Model!$C$5*(($C81)+Model!$C$6*(G$77)))-($C$74))/Model!$C$7)^2)/2)/SQRT(2*PI())))-((((Model!$C$5*(($C$70)+Model!$C$6*($C$71)))-($C$73))*NORMSDIST(((Model!$C$5*(($C$70)+Model!$C$6*($C$71)))-($C$73))/Model!$C$7)+Model!$C$7*EXP(-((((Model!$C$5*(($C$70)+Model!$C$6*($C$71)))-($C$73))/Model!$C$7)^2)/2)/SQRT(2*PI()))-(((Model!$C$5*(($C$70)+Model!$C$6*($C$71)))-($C$74))*NORMSDIST(((Model!$C$5*(($C$70)+Model!$C$6*($C$71)))-($C$74))/Model!$C$7)+Model!$C$7*EXP(-((((Model!$C$5*(($C$70)+Model!$C$6*($C$71)))-($C$74))/Model!$C$7)^2)/2)/SQRT(2*PI()))))) -> 825.28887 | O81: =$C$72+$C$68*((Model!$C$5*(($C81)+Model!$C$6*(H$77)))-(Model!$C$5*(($C$70)+Model!$C$6*($C$71)))-$C$69*(((((Model!$C$5*(($C81)+Model!$C$6*(H$77)))-($C$73))*NORMSDIST(((Model!$C$5*(($C81)+Model!$C$6*(H$77)))-($C$73))/Model!$C$7)+Model!$C$7*EXP(-((((Model!$C$5*(($C81)+Model!$C$6*(H$77)))-($C$73))/Model!$C$7)^2)/2)/SQRT(2*PI()))-(((Model!$C$5*(($C81)+Model!$C$6*(H$77)))-($C$74))*NORMSDIST(((Model!$C$5*(($C81)+Model!$C$6*(H$77)))-($C$74))/Model!$C$7)+Model!$C$7*EXP(-((((Model!$C$5*(($C81)+Model!$C$6*(H$77)))-($C$74))/Model!$C$7)^2)/2)/SQRT(2*PI())))-((((Model!$C$5*(($C$70)+Model!$C$6*($C$71)))-($C$73))*NORMSDIST(((Model!$C$5*(($C$70)+Model!$C$6*($C$71)))-($C$73))/Model!$C$7)+Model!$C$7*EXP(-((((Model!$C$5*(($C$70)+Model!$C$6*($C$71)))-($C$73))/Model!$C$7)^2)/2)/SQRT(2*PI()))-(((Model!$C$5*(($C$70)+Model!$C$6*($C$71)))-($C$74))*NORMSDIST(((Model!$C$5*(($C$70)+Model!$C$6*($C$71)))-($C$74))/Model!$C$7)+Model!$C$7*EXP(-((((Model!$C$5*(($C$70)+Model!$C$6*($C$71)))-($C$74))/Model!$C$7)^2)/2)/SQRT(2*PI()))))) -> 841.97773 | Q81: =C81 -> 65 | R81: =K81-D81 -> -7.4237237 | S81: =L81-E81 -> -6.2039712 | T81: =M81-F81 -> 0 | U81: =N81-G81 -> -1.7111339 | V81: =O81-H81 -> -11.022269
C82: 55 | D82: 729 | E82: 759 | F82: 785 | G82: 803 | H82: 818 | J82: =C82 -> 55 | K82: =$C$72+$C$68*((Model!$C$5*(($C82)+Model!$C$6*(D$77)))-(Model!$C$5*(($C$70)+Model!$C$6*($C$71)))-$C$69*(((((Model!$C$5*(($C82)+Model!$C$6*(D$77)))-($C$73))*NORMSDIST(((Model!$C$5*(($C82)+Model!$C$6*(D$77)))-($C$73))/Model!$C$7)+Model!$C$7*EXP(-((((Model!$C$5*(($C82)+Model!$C$6*(D$77)))-($C$73))/Model!$C$7)^2)/2)/SQRT(2*PI()))-(((Model!$C$5*(($C82)+Model!$C$6*(D$77)))-($C$74))*NORMSDIST(((Model!$C$5*(($C82)+Model!$C$6*(D$77)))-($C$74))/Model!$C$7)+Model!$C$7*EXP(-((((Model!$C$5*(($C82)+Model!$C$6*(D$77)))-($C$74))/Model!$C$7)^2)/2)/SQRT(2*PI())))-((((Model!$C$5*(($C$70)+Model!$C$6*($C$71)))-($C$73))*NORMSDIST(((Model!$C$5*(($C$70)+Model!$C$6*($C$71)))-($C$73))/Model!$C$7)+Model!$C$7*EXP(-((((Model!$C$5*(($C$70)+Model!$C$6*($C$71)))-($C$73))/Model!$C$7)^2)/2)/SQRT(2*PI()))-(((Model!$C$5*(($C$70)+Model!$C$6*($C$71)))-($C$74))*NORMSDIST(((Model!$C$5*(($C$70)+Model!$C$6*($C$71)))-($C$74))/Model!$C$7)+Model!$C$7*EXP(-((((Model!$C$5*(($C$70)+Model!$C$6*($C$71)))-($C$74))/Model!$C$7)^2)/2)/SQRT(2*PI()))))) -> 721.48232 | L82: =$C$72+$C$68*((Model!$C$5*(($C82)+Model!$C$6*(E$77)))-(Model!$C$5*(($C$70)+Model!$C$6*($C$71)))-$C$69*(((((Model!$C$5*(($C82)+Model!$C$6*(E$77)))-($C$73))*NORMSDIST(((Model!$C$5*(($C82)+Model!$C$6*(E$77)))-($C$73))/Model!$C$7)+Model!$C$7*EXP(-((((Model!$C$5*(($C82)+Model!$C$6*(E$77)))-($C$73))/Model!$C$7)^2)/2)/SQRT(2*PI()))-(((Model!$C$5*(($C82)+Model!$C$6*(E$77)))-($C$74))*NORMSDIST(((Model!$C$5*(($C82)+Model!$C$6*(E$77)))-($C$74))/Model!$C$7)+Model!$C$7*EXP(-((((Model!$C$5*(($C82)+Model!$C$6*(E$77)))-($C$74))/Model!$C$7)^2)/2)/SQRT(2*PI())))-((((Model!$C$5*(($C$70)+Model!$C$6*($C$71)))-($C$73))*NORMSDIST(((Model!$C$5*(($C$70)+Model!$C$6*($C$71)))-($C$73))/Model!$C$7)+Model!$C$7*EXP(-((((Model!$C$5*(($C$70)+Model!$C$6*($C$71)))-($C$73))/Model!$C$7)^2)/2)/SQRT(2*PI()))-(((Model!$C$5*(($C$70)+Model!$C$6*($C$71)))-($C$74))*NORMSDIST(((Model!$C$5*(($C$70)+Model!$C$6*($C$71)))-($C$74))/Model!$C$7)+Model!$C$7*EXP(-((((Model!$C$5*(($C$70)+Model!$C$6*($C$71)))-($C$74))/Model!$C$7)^2)/2)/SQRT(2*PI()))))) -> 746.90495 | M82: =$C$72+$C$68*((Model!$C$5*(($C82)+Model!$C$6*(F$77)))-(Model!$C$5*(($C$70)+Model!$C$6*($C$71)))-$C$69*(((((Model!$C$5*(($C82)+Model!$C$6*(F$77)))-($C$73))*NORMSDIST(((Model!$C$5*(($C82)+Model!$C$6*(F$77)))-($C$73))/Model!$C$7)+Model!$C$7*EXP(-((((Model!$C$5*(($C82)+Model!$C$6*(F$77)))-($C$73))/Model!$C$7)^2)/2)/SQRT(2*PI()))-(((Model!$C$5*(($C82)+Model!$C$6*(F$77)))-($C$74))*NORMSDIST(((Model!$C$5*(($C82)+Model!$C$6*(F$77)))-($C$74))/Model!$C$7)+Model!$C$7*EXP(-((((Model!$C$5*(($C82)+Model!$C$6*(F$77)))-($C$74))/Model!$C$7)^2)/2)/SQRT(2*PI())))-((((Model!$C$5*(($C$70)+Model!$C$6*($C$71)))-($C$73))*NORMSDIST(((Model!$C$5*(($C$70)+Model!$C$6*($C$71)))-($C$73))/Model!$C$7)+Model!$C$7*EXP(-((((Model!$C$5*(($C$70)+Model!$C$6*($C$71)))-($C$73))/Model!$C$7)^2)/2)/SQRT(2*PI()))-(((Model!$C$5*(($C$70)+Model!$C$6*($C$71)))-($C$74))*NORMSDIST(((Model!$C$5*(($C$70)+Model!$C$6*($C$71)))-($C$74))/Model!$C$7)+Model!$C$7*EXP(-((((Model!$C$5*(($C$70)+Model!$C$6*($C$71)))-($C$74))/Model!$C$7)^2)/2)/SQRT(2*PI()))))) -> 770.56494 | N82: =$C$72+$C$68*((Model!$C$5*(($C82)+Model!$C$6*(G$77)))-(Model!$C$5*(($C$70)+Model!$C$6*($C$71)))-$C$69*(((((Model!$C$5*(($C82)+Model!$C$6*(G$77)))-($C$73))*NORMSDIST(((Model!$C$5*(($C82)+Model!$C$6*(G$77)))-($C$73))/Model!$C$7)+Model!$C$7*EXP(-((((Model!$C$5*(($C82)+Model!$C$6*(G$77)))-($C$73))/Model!$C$7)^2)/2)/SQRT(2*PI()))-(((Model!$C$5*(($C82)+Model!$C$6*(G$77)))-($C$74))*NORMSDIST(((Model!$C$5*(($C82)+Model!$C$6*(G$77)))-($C$74))/Model!$C$7)+Model!$C$7*EXP(-((((Model!$C$5*(($C82)+Model!$C$6*(G$77)))-($C$74))/Model!$C$7)^2)/2)/SQRT(2*PI())))-((((Model!$C$5*(($C$70)+Model!$C$6*($C$71)))-($C$73))*NORMSDIST(((Model!$C$5*(($C$70)+Model!$C$6*($C$71)))-($C$73))/Model!$C$7)+Model!$C$7*EXP(-((((Model!$C$5*(($C$70)+Model!$C$6*($C$71)))-($C$73))/Model!$C$7)^2)/2)/SQRT(2*PI()))-(((Model!$C$5*(($C$70)+Model!$C$6*($C$71)))-($C$74))*NORMSDIST(((Model!$C$5*(($C$70)+Model!$C$6*($C$71)))-($C$74))/Model!$C$7)+Model!$C$7*EXP(-((((Model!$C$5*(($C$70)+Model!$C$6*($C$71)))-($C$74))/Model!$C$7)^2)/2)/SQRT(2*PI()))))) -> 792.26057 | O82: =$C$72+$C$68*((Model!$C$5*(($C82)+Model!$C$6*(H$77)))-(Model!$C$5*(($C$70)+Model!$C$6*($C$71)))-$C$69*(((((Model!$C$5*(($C82)+Model!$C$6*(H$77)))-($C$73))*NORMSDIST(((Model!$C$5*(($C82)+Model!$C$6*(H$77)))-($C$73))/Model!$C$7)+Model!$C$7*EXP(-((((Model!$C$5*(($C82)+Model!$C$6*(H$77)))-($C$73))/Model!$C$7)^2)/2)/SQRT(2*PI()))-(((Model!$C$5*(($C82)+Model!$C$6*(H$77)))-($C$74))*NORMSDIST(((Model!$C$5*(($C82)+Model!$C$6*(H$77)))-($C$74))/Model!$C$7)+Model!$C$7*EXP(-((((Model!$C$5*(($C82)+Model!$C$6*(H$77)))-($C$74))/Model!$C$7)^2)/2)/SQRT(2*PI())))-((((Model!$C$5*(($C$70)+Model!$C$6*($C$71)))-($C$73))*NORMSDIST(((Model!$C$5*(($C$70)+Model!$C$6*($C$71)))-($C$73))/Model!$C$7)+Model!$C$7*EXP(-((((Model!$C$5*(($C$70)+Model!$C$6*($C$71)))-($C$73))/Model!$C$7)^2)/2)/SQRT(2*PI()))-(((Model!$C$5*(($C$70)+Model!$C$6*($C$71)))-($C$74))*NORMSDIST(((Model!$C$5*(($C$70)+Model!$C$6*($C$71)))-($C$74))/Model!$C$7)+Model!$C$7*EXP(-((((Model!$C$5*(($C$70)+Model!$C$6*($C$71)))-($C$74))/Model!$C$7)^2)/2)/SQRT(2*PI()))))) -> 811.94667 | Q82: =C82 -> 55 | R82: =K82-D82 -> -7.5176758 | S82: =L82-E82 -> -12.095053 | T82: =M82-F82 -> -14.435061 | U82: =N82-G82 -> -10.739426 | V82: =O82-H82 -> -6.0533259
